Workbook
Name __MXH08: #REF!
Name _006: #REF!
Name _1: [1]原材料!$A$1:$R$945
Name _1_1223: #REF!
Name _1223: #REF!
Name _123: #REF!
Name _12456: #REF!
Name _2_1223: #REF!
Name _2_123: #REF!
Name _2成本: #REF!
Name _2电力收入: #REF!
Name _2年成本: #REF!
Name _2年收入: #REF!
Name _3.1: #N/A
Name _3.2: #N/A
Name _3.U: #N/A
Name _3_12456: #REF!
Name _3年成本: #REF!
Name _3年收入: #REF!
Name _4_123: #REF!
Name _4_898: #REF!
Name _4年成本: #REF!
Name _4年收入: #REF!
Name _5年成本: #REF!
Name _5年收入: #REF!
Name _6_12456: #REF!
Name _8_898: #REF!
Name _898: #REF!
Name _A91: #REF!
Name _A99: #REF!
Name _MXH08: #REF!
Name Apr: #REF!="04月"
Name ASFJDFLDFSLALFA: #REF!
Name Aug: #REF!="08月"
Name b: #REF!
Name bianzhi: #REF!
Name bianzhiriqi: #REF!
Name butie: #REF!
Name CanSave: FALSE
Name COL_NUM: [2]细节测试审计抽样!$U$76
Name Confidence_Factor: [2]细节测试审计抽样!$W$73:$Z$76
Name daqu: #REF!
Name DATA: OFFSET([3]汇总明细!$A$1,,,COUNTA([3]汇总明细!$A$1:$A$65536),COUNTA([3]汇总明细!$A$1:$IV$1))
Name DATA1: OFFSET([3]进销存模板!$A$1,,,COUNTA([3]进销存模板!$A$1:$A$65536),COUNTA([3]进销存模板!$A$1:$IV$1))
Name data2: [4]销售分公司!$H$5:$H$7,[4]销售分公司!$H$9:$H$11,[4]销售分公司!$H$13:$H$14,[4]销售分公司!$H$16
Name data3: [4]销售分公司!$F$22:$F$26,[4]销售分公司!$F$28:$F$30,[4]销售分公司!$F$32:$F$33,[4]销售分公司!$F$35
Name data4: [4]销售分公司!$H$24:$H$26,[4]销售分公司!$H$28:$H$30,[4]销售分公司!$H$32:$H$33,[4]销售分公司!$H$35
Name Database: #REF!
Name DBPATH: "湖北杰之行股份2015_数据.cxt"
Name Dec: #REF!="12月"
Name diaop: '[5]数据库(万元)'!$L$2:$L$24990
Name dpe: #REF!
Name dpjb: #REF!
Name dpname: OFFSET(#REF!,ROW()-11,MATCH(#REF!,#REF!,)-1)
Name dpyt: #REF!
Name dq: #REF!
Name dxn: [6]dxnsjtempsheet!$A$1:$G$65536
Name E: [7]Sheet1!$A$9
Name Feb: #REF!="02月"
Name FeiY: #REF!

Sheet 封面
A1: 收益法评估明细表
A2: 1 | B2: 被评估单位：福建卫东新能源股份有限公司
A3: 2 | B3: 评估基准日： | C3: 2017年12月31日
A4: 3 | B4: 企业负责人： | C4: 李恒
A5: 4 | B5: 财务负责人： | C5: 林岗
A6: 5 | B6: 填表人： | C6: 林岗
A7: 6 | B7: 填表日期： | C7: 43179
A9: 7 | B9: 评估机构： | C9: 万隆（上海）资产评估有限公司
A10: 8 | B10: 法人代表人： | C10: 刘宏
A11: 9 | B11: 项目负责人：
A12: 10 | B12: 签字评估师：
B15: 基本要求
A16: 1 | B16: 申报表由企业根据实际情况填写，相关数据应该与审计报告/会计报表一致。
A17: 2 | B17: （1）绿色应由企业填报。（2）黄色表格可根据实际情况选择是否填列。（3）红色表格由评估人员评估计算使用。
A18: 3 | B18: 预测总要求 | C18: 数据和财务指标应与历史情况衔接，如果出现超常规变化（这也是审核的重点），应有充分的理由认为预测可实现。
B19: 主营收入预测要点 | C19: （1）市场需求容量；（2）企业产能；（3）企业前几年销量及市场占有率；（4）行业竞争企业在行业中的竞争能力（优劣势分析）；（5）行业龙头企业的销量情况；（6）企业在细分产品领域、营销和宣传方面的策略；（7）企业发展规划。（8）支出企业预期收益实现的各种资源是否有保障。
B20: 主营业务成本预测要点 | C20: 基本应与历史情况一致。
B21: 期间费用预测要点 | C21: 基本应与历史情况相当，但应考虑规模效益导致的变化。同时可参考行业企业的费率情况。
C22: 注意各科目中，是否存在溢余资产、非经营性资产和负债。

Sheet 资产负债分析调整表
D1: 资产负债分析调整表
A2: =封面!B2 -> 被评估单位：福建卫东新能源股份有限公司 | F2: 评估基准日： | G2: =封面!C3 -> 2017年12月31日
A4: 序号 | B4: 项目\年份 | C4: ='[34]表I-2调整后利润表'!B6&"年12月31日" -> 2015年12月31日 | D4: ='[34]表I-2调整后利润表'!C6&"年12月31日" -> 2016年12月31日 | E4: ='[34]表I-1近年利润表'!D6&"年12月31日" -> 2017年12月31日
C5: 账面值 | D5: 账面值 | E5: 账面值 | F5: 其中：非经营性资产 | G5: 经营性资产
A6: 1 | B6: 一、流动资产合计 | C6: =C7+C8+C9+C10+C11+C12+C14+C15+C13+C16+C17+C18+C19 -> 83116651 | D6: =D7+D8+D9+D10+D11+D12+D14+D15+D13+D16+D17+D18+D19 -> 76673213 | E6: =SUM(E7:E19) -> 70610292 | F6: =F7+F8+F9+F10+F11+F12+F13+F14+F15+F16+F17+F18+F19 -> 60511670 | G6: =E6-F6 -> 10098622
A7: 2 | B7: 货币资金 | C7: 6628414.3 | D7: 117476.61 | E7: 64080.64 | G7: =E7-F7 -> 64080.64
A8: 3 | B8: 交易性金融资产净额 | C8: 619575 | D8: 0 | E8: 0 | G8: =E8-F8 -> 0
A9: 4 | B9: 应收票据 | D9: 1900000 | E9: 0 | G9: =E9-F9 -> 0
A10: 5 | B10: 应收股利(应收利润) | D10: 0 | E10: 0 | G10: =E10-F10 -> 0
A11: 6 | B11: 应收利息 | D11: 0 | E11: 0 | G11: =E11-F11 -> 0
A12: 7 | B12: 应收账款净额 | C12: 3440854.1 | D12: 8809335.9 | E12: 3259831.8 | G12: =E12-F12 -> 3259831.8
A13: 8 | B13: 其他应收款净额 | C13: 64618993 | D13: 62267599 | E13: 59701035 | F13: 60511670 | G13: =E14-F13 -> -58230227
A14: 9 | B14: 预付帐款 | C14: 4346083.5 | D14: 896722.35 | E14: 2281443.4 | G14: =E14-F14 -> 2281443.4
A15: 10 | B15: 应收补贴款 | G15: =E13-F15 -> 59701035
A16: 11 | B16: 存货净额 | C16: 3462731.8 | D16: 2682078.7 | E16: 5303901.6 | G16: =E16-F16 -> 5303901.6
A17: 12 | B17: 待摊费用 | E17: 0 | G17: =E17-F17 -> 0
A18: 13 | B18: 一年内到期的非流动资产
A19: 14 | B19: 其他流动资产 | G19: =E19-F19 -> 0
A20: 15 | B20: 二、非流动资产合计 | C20: =C21+C22+C23+C24+C25+C26+C32+C33+C34+C35+C36+C37+C38+C39+C40+C41+C42 -> 19411960 | D20: =D21+D22+D23+D24+D25+D26+D32+D33+D34+D35+D36+D37+D38+D39+D40+D41+D42 -> 35364860 | E20: =E21+E22+E23+E24+E25+E26+E32+E33+E34+E35+E36+E37+E38+E39+E40+E41+E42 -> 34674500 | F20: =F21+F22+F23+F24+F25+F26+F32+F33+F34+F35+F36+F37+F38+F39+F40+F41+F42 -> 15000000 | G20: =E20-F20 -> 19674500
A21: 16 | B21: 可供出售金融资产净额 | C21: 0 | D21: 0 | E21: 0 | G21: =E21-F21 -> 0
A22: 17 | B22: 持有至到期投资净额 | C22: 0 | D22: 0 | E22: 0 | G22: =E22-F22 -> 0
A23: 18 | B23: 长期股权投资净额 | C23: 0 | D23: 15000000 | E23: 15000000 | F23: =E23 -> 15000000 | G23: =E23-F23 -> 0
A24: 19 | B24: 长期应收款 | C24: 0 | D24: 0 | E24: 0 | G24: =E24-F24 -> 0
A25: 20 | B25: 投资性房地产 | C25: 0 | G25: =E25-F25 -> 0
A26: 21 | B26: 固定资产 | C26: =C31 -> 11310294 | D26: =D31 -> 12444368 | E26: =E31 -> 11938056 | G26: =E26-F26 -> 11938056
A27: 22 | B27: 固定资产原价 | C27: 11942890 | D27: 14780443 | E27: 16120369 | G27: =E27-F27 -> 16120369
A28: 23 | B28: 减：累计折旧 | C28: 632596.26 | D28: 2336075.6 | E28: 4182313.5 | G28: =E28-F28 -> 4182313.5
A29: 24 | B29: 固定资产净值 | C29: =C27-C28 -> 11310294 | D29: =D27-D28 -> 12444368 | E29: =E27-E28 -> 11938056 | G29: =E29-F29 -> 11938056
A30: 25 | B30: 减：固定资产减值准备 | C30: 0 | D30: 0 | E30: 0 | G30: =E30-F30 -> 0
A31: 26 | B31: 固定资产净额 | C31: =C29-C30 -> 11310294 | D31: =D29-D30 -> 12444368 | E31: =E29-E30 -> 11938056 | F31: =F29-F30 -> 0 | G31: =E31-F31 -> 11938056
A32: 27 | B32: 工程物资 | C32: 0 | D32: 0 | E32: 0 | G32: =E32-F32 -> 0
A33: 28 | B33: 在建工程 | G33: =E33-F33 -> 0
A34: 29 | B34: 固定资产清理 | C34: 0 | D34: 0 | E34: 0 | G34: =E34-F34 -> 0
A35: 30 | B35: 生产性生物资产净额 | C35: 0 | D35: 0 | E35: 0 | G35: =E35-F35 -> 0
A36: 31 | B36: 油气资产净值 | C36: 0 | D36: 0 | E36: 0 | G36: =E36-F36 -> 0
A37: 32 | B37: 开发支出 | C37: 0 | D37: 0 | E37: 0 | G37: =E37-F37 -> 0
A38: 33 | B38: 商誉 | C38: 0 | D38: 0 | E38: 0 | G38: =E38-F38 -> 0
A39: 34 | B39: 无形资产净额 | C39: 4812245.4 | D39: 4496075.8 | E39: 4165377.7 | G39: =E39-F39 -> 4165377.7
A40: 35 | B40: 长期待摊费用 | G40: =E40-F40 -> 0
A41: 36 | B41: 其他非流动资产 | C41: 0 | D41: 0 | E41: 0 | G41: =E41-F41 -> 0
A42: 37 | B42: 递延所得税资产 | C42: 3289421 | D42: 3424417 | E42: 3571067 | G42: =E42-F42 -> 3571067
A43: 38 | B43: 三、资产合计 | C43: =C6+C20 -> 1.0252861e+08 | D43: =D6+D20 -> 1.1203807e+08 | E43: =E6+E20 -> 1.0528479e+08 | F43: =F6+F20 -> 75511670 | G43: =E43-F43 -> 29773122
A44: 39 | B44: 四、流动负债合计 | C44: =C45+C46+C47+C48+C49+C50+C51+C52+C53+C54+C55+C56+C57 -> -2320238.6 | D44: =D45+D46+D47+D48+D49+D50+D51+D52+D53+D54+D55+D56+D57 -> 10622801 | E44: =E45+E46+E47+E48+E49+E50+E51+E52+E53+E54+E55+E56+E57 -> 11115104 | F44: =F45+F46+F47+F48+F49+F50+F51+F52+F53+F54+F55+F56+F57 -> 11525000 | G44: =E44-F44 -> -409895.62
A45: 40 | B45: 短期借款 | C45: 0 | D45: 0 | G45: =E45-F45 -> 0
A46: 41 | B46: 交易性金融负债 | G46: =E46-F46 -> 0
A47: 42 | B47: 应付票据 | C47: 0 | D47: 0 | G47: =E47-F47 -> 0
A48: 43 | B48: 应付帐款 | C48: 372935.94 | D48: 2000239.4 | E48: 2014399.5 | G48: =E48-F48 -> 2014399.5
A49: 44 | B49: 预收帐款 | C49: 0 | D49: 60417.5 | E49: 240455.6 | G49: =E49-F49 -> 240455.6
A50: 45 | B50: 应付职工薪酬 | G50: =E50-F50 -> 0
A51: 46 | B51: 应付利润（应付股利） | G51: =E51-F51 -> 0
A52: 47 | B52: 应交税费 | C52: -2732732.3 | D52: -2337671 | E52: -2708268.1 | G52: =E52-F52 -> -2708268.1
A53: 48 | B53: 应付利息 | C53: 0 | D53: 0 | G53: =E53-F53 -> 0
A54: 49 | B54: 其他应付款 | C54: 39557.74 | D54: 10899815 | E54: 11568517 | F54: 11525000 | G54: =E54-F54 -> 43517.42
A55: 50 | B55: 预提费用 | C55: 0 | D55: 0 | G55: =E55-F55 -> 0
A56: 51 | B56: 一年内到期的非流动负债 | C56: 0 | D56: 0 | G56: =E56-F56 -> 0
A57: 52 | B57: 其他流动负债 | C57: 0 | D57: 0 | G57: =E57-F57 -> 0
A58: 53 | B58: 五、非流动负债合计 | C58: =C59+C60+C61+C62+C63+C64+C65 -> 0 | D58: =D59+D60+D61+D62+D63+D64+D65 -> 0 | E58: =E59+E60+E61+E62+E63+E64+E65 -> 0 | F58: =F59+F60+F61+F62+F63+F64+F65 -> 0 | G58: =E58-F58 -> 0
A59: 54 | B59: 长期借款 | F59: 0 | G59: =E59-F59 -> 0
A60: 55 | B60: 应付债券 | C60: 0 | D60: 0 | E60: 0 | F60: 0 | G60: =E60-F60 -> 0
A61: 56 | B61: 长期应付款 | C61: 0 | D61: 0 | E61: 0 | F61: 0 | G61: =E61-F61 -> 0
A62: 57 | B62: 专项应付款 | C62: 0 | D62: 0 | E62: 0 | F62: 0 | G62: =E62-F62 -> 0
A63: 58 | B63: 预计负债 | G63: =E63-F63 -> 0
A64: 59 | B64: 其他非流动负债 | G64: =E64-F64 -> 0
A65: 60 | B65: 递延所得税负债 | G65: =E65-F65 -> 0
A66: 61 | B66: 六、负债合计 | C66: =C58+C44 -> -2320238.6 | D66: =D58+D44 -> 10622801 | E66: =E58+E44 -> 11115104 | F66: =F58+F44 -> 11525000 | G66: =G58+G44 -> -409895.62
A67: 62 | B67: 七、净资产 | C67: =C43-C66 -> 1.0484885e+08 | D67: =D43-D66 -> 1.0141527e+08 | E67: =E43-E66 -> 94169688 | F67: =F43-F66 -> 63986670 | G67: =G43-G66 -> 30183018
A68: 63 | B68: 其中：少数股东权益
A69: 64 | B69: 八、归属于母公司的净资产 | C69: =C67-C68 -> 1.0484885e+08 | D69: =D67-D68 -> 1.0141527e+08 | E69: =E67-E68 -> 94169688 | F69: =F67-F68 -> 63986670

Sheet 利润分析调整表
C1: 利润表分析调整表
A3: =封面!B2 -> 被评估单位：福建卫东新能源股份有限公司 | D3: 评估基准日 | E3: =封面!C3 -> 2017年12月31日
E5: 单位：元
A6: 项目 \ 年份 | B6: ='[34]表I-1近年利润表'!B6 -> 2015 | C6: ='[34]表I-1近年利润表'!C6 -> 2016 | D6: ='[34]表I-1近年利润表'!D6 -> 2017 | E6: 调整分析说明
A7: ='[34]表I-1近年利润表'!A7 -> 一、营业总收入 | B7: =B8+B9 -> 2935047.1 | C7: =C8+C9 -> 10814268 | D7: =D8+D9 -> 3114175.7
A8: ='[34]表I-1近年利润表'!A8 -> 其中：主营业务收入 | B8: 2935047.1 | C8: 10473622 | D8: =2167194.48+946981.23 -> 3114175.7
A9: ='[34]表I-1近年利润表'!A9 -> 其他业务收入 | B9: 0 | C9: 340646.29
A10: ='[34]表I-1近年利润表'!A10 -> 二、营业总成本 | B10: =B11+B15+B16+B17+B18+B19 -> 11306485 | C10: =C11+C15+C16+C17+C18+C19 -> 15930623 | D10: =D11+D15+D16+D17+D18+D19 -> 10507876
A11: ='[34]表I-1近年利润表'!A11 -> 其中:营业成本 | B11: =B12+B14 -> 2114358.2 | C11: =C12+C14 -> 7060951.5 | D11: =D12+D14 -> 4577497.7
A12: ='[34]表I-1近年利润表'!A12 -> 其中:主营业务成本 | B12: 2114358.2 | C12: 7060951.5 | D12: 4577497.7
B13: 2418428.9 | C13: 8839205.2 | D13: 9843943.6
A14: ='[34]表I-1近年利润表'!A13 -> 其他业务成本
A15: ='[34]表I-1近年利润表'!A14 -> 营业税金及附加 | B15: 0 | C15: 19772.45 | D15: 4228.6
A16: ='[34]表I-1近年利润表'!A15 -> 营业费用 | B16: 206429.86 | C16: 159667.88 | D16: 142374.42
A17: ='[34]表I-1近年利润表'!A16 -> 管理费用 | B17: 8885053.8 | C17: 8515846.9 | D17: 5194277.1
A18: ='[34]表I-1近年利润表'!A17 -> 财务费用 | B18: -31334.51 | C18: 700.17 | D18: 2898.07
A19: ='[34]表I-1近年利润表'!A18 -> 资产减值损失 | B19: 131977.38 | C19: 173684.15 | D19: 586599.74
A20: ='[34]表I-1近年利润表'!A19 -> 加：公允价值变动收益 | B20: -72073 | C20: 72073 | D20: 0
A21: ='[34]表I-1近年利润表'!A20 -> 投资收益 | B21: 63559.56 | C21: 1832010.4 | D21: 0
A22: ='[34]表I-1近年利润表'!A21 -> 三、营业利润 | B22: =B7-B10+B20+B21 -> -8379951 | C22: =C7-C10+C20+C21 -> -3212271.9 | D22: =D7-D10+D20+D21 -> -7393699.9
A23: ='[34]表I-1近年利润表'!A22 -> 加：营业外收入 | B23: 175926.16 | C23: 10000 | D23: 1501.06
A24: ='[34]表I-1近年利润表'!A23 -> 减: 营业外支出 | B24: 0 | C24: 2.23 | D24: 35.4
A25: ='[34]表I-1近年利润表'!A24 -> 四、利润总额 | B25: =B22+B23-B24 -> -8204024.9 | C25: =C22+C23-C24 -> -3202274.1 | D25: =D22+D23-D24 -> -7392234.2
A26: ='[34]表I-1近年利润表'!A25 -> 减: 所得税 | B26: -1492947.6 | C26: -43421.04 | D26: -146649.94
A27: ='[34]表I-1近年利润表'!A26 -> 五、净利润 | B27: =B25-B26 -> -6711077.2 | C27: =C25-C26 -> -3158853.1 | D27: =D25-D26 -> -7245584.3
A28: ='[34]表I-1近年利润表'!A27 -> 净利润增长率 | C28: =IF(B27=0,"",ROUND((C27-B27)/B27,4)) -> -0.5293 | D28: =IF(C27=0,"",ROUND((D27-C27)/C27,4)) -> 1.2937
A29: ='[34]表I-1近年利润表'!A28 -> 其中：少数股东损益
A30: ='[34]表I-1近年利润表'!A29 -> 占总利润比例 | B30: =IF(B27=0,"",IF(B29<>0,B29/B27,"")) | C30: =IF(C27=0,"",IF(C29<>0,C29/C27,"")) | D30: =IF(D27=0,"",IF(D29<>0,D29/D27,""))
A31: ='[34]表I-1近年利润表'!A30 -> 六、归属于母公司损益 | B31: =B27-B29 -> -6711077.2 | C31: =C27-C29 -> -3158853.1 | D31: =D27-D29 -> -7245584.3

Sheet 财务指标分析表
A2: =封面!B2 -> 被评估单位：福建卫东新能源股份有限公司 | F2: 评估基准日： | G2: =封面!C3 -> 2017年12月31日
A4: 序号 | B4: 项目名称 \ 年份 | C4: 单位 | D4: ='[34]表I-2调整后利润表'!B6 -> 2015 | E4: ='[34]表I-2调整后利润表'!C6 -> 2016 | F4: ='[34]表I-2调整后利润表'!D6 -> 2017 | G4: 均值
A5: 1 | B5: 主营收入增长率 | C5: % | D5: —— | E5: =(利润分析调整表!C8-利润分析调整表!B8)/利润分析调整表!B8*100 -> 256.84679 | F5: =(利润分析调整表!D7-利润分析调整表!C7)/利润分析调整表!C7*100 -> -71.203083 | G5: =(E5+F5)/2 -> 92.821853
A6: 2 | B6: 主营业务毛利率 | C6: % | D6: =(利润分析调整表!B8-利润分析调整表!B12)/利润分析调整表!B8*100 -> 27.961695 | E6: =(利润分析调整表!C8-利润分析调整表!C12)/利润分析调整表!C8*100 -> 32.583477 | F6: =(利润分析调整表!D8-利润分析调整表!D12)/利润分析调整表!D8*100 -> -46.989062 | G6: =(D6+E6+F6)/3 -> 4.5187033
A7: 3 | B7: 其他业务毛利率 | C7: % | D7: —— | E7: =(利润分析调整表!C9-利润分析调整表!C14)/利润分析调整表!C9*100 -> 100 | F7: =(利润分析调整表!D9-利润分析调整表!D14)/利润分析调整表!D9*100 -> #DIV/0!
A8: 4 | B8: 营业税金比率 | C8: % | D8: =利润分析调整表!B15/利润分析调整表!B7*100 -> 0 | E8: =利润分析调整表!C15/利润分析调整表!C7*100 -> 0.1828367 | F8: =利润分析调整表!D15/利润分析调整表!D7*100 -> 0.13578553 | G8: =(D8+E8+F8)/3 -> 0.10620741
A9: 5 | B9: 营业费用比率 | C9: % | D9: =利润分析调整表!B16/利润分析调整表!B7*100 -> 7.0332724 | E9: =利润分析调整表!C16/利润分析调整表!C7*100 -> 1.4764558 | F9: =利润分析调整表!D16/利润分析调整表!D7*100 -> 4.5718172 | G9: =(D9+E9+F9)/3 -> 4.3605151
A10: 6 | B10: 管理费用比率 | C10: % | D10: =利润分析调整表!B17/利润分析调整表!B7*100 -> 302.72269 | E10: =利润分析调整表!C17/利润分析调整表!C7*100 -> 78.746404 | F10: =利润分析调整表!D17/利润分析调整表!D7*100 -> 166.79461 | G10: =(D10+E10+F10)/3 -> 182.75457
A11: 7 | B11: 财务费用比率 | C11: % | D11: =利润分析调整表!B18/利润分析调整表!B7*100 -> -1.0675982 | E11: =利润分析调整表!C18/利润分析调整表!C7*100 -> 0.0064745021 | F11: =利润分析调整表!D18/利润分析调整表!D7*100 -> 0.093060581 | G11: =(D11+E11+F11)/3 -> -0.3226877
A12: 8 | B12: 投资收益比率 | C12: % | D12: =利润分析调整表!B21/利润分析调整表!B7*100 -> 2.165538 | E12: =利润分析调整表!C21/利润分析调整表!C7*100 -> 16.940679 | F12: =利润分析调整表!D21/利润分析调整表!D7*100 -> 0 | G12: =(D12+E12+F12)/3 -> 6.3687389
A13: 9 | B13: 营业利润比率 | C13: % | D13: =利润分析调整表!B22/利润分析调整表!B7*100 -> -285.51334 | E13: =利润分析调整表!C22/利润分析调整表!C7*100 -> -29.704017 | F13: =利润分析调整表!D22/利润分析调整表!D7*100 -> -237.42077 | G13: =(D13+E13+F13)/3 -> -184.21271
A14: 10 | B14: 营业外收入比率 | C14: % | D14: =利润分析调整表!B23/利润分析调整表!B7*100 -> 5.9939807 | E14: =利润分析调整表!C23/利润分析调整表!C7*100 -> 0.092470431 | F14: =利润分析调整表!D23/利润分析调整表!D7*100 -> 0.048200877 | G14: =(D14+E14+F14)/3 -> 2.044884
A15: 11 | B15: 营业外支出比率 | C15: % | D15: =利润分析调整表!B24/利润分析调整表!B7*100 -> 0 | E15: =利润分析调整表!C24/利润分析调整表!C7*100 -> 2.0620906e-05 | F15: =利润分析调整表!D24/利润分析调整表!D7*100 -> 0.0011367374 | G15: =(D15+E15+F15)/3 -> 0.0003857861
A16: 一、 | B16: 营运能力
A17: 1 | B17: 存货周转率 | C17: 次 | D17: =利润分析调整表!B11/资产负债分析调整表!C16 -> 0.61060409 | E17: =利润分析调整表!C11/((资产负债分析调整表!C16+资产负债分析调整表!D16)/2) -> 2.2981836 | F17: =利润分析调整表!B12/((资产负债分析调整表!D16+资产负债分析调整表!E16)/2) -> 0.52951752 | G17: =360/(30) -> 12 | H17: 企业以销定产，存货的生产周期为30天
A18: 2 | B18: 应收账款周转率 | C18: 次 | D18: =利润分析调整表!B7/资产负债分析调整表!C12 -> 0.8529996 | E18: =利润分析调整表!C7/((资产负债分析调整表!C12+资产负债分析调整表!D12)/2) -> 1.7655674 | F18: =利润分析调整表!D7/((资产负债分析调整表!D12+资产负债分析调整表!E12)/2) -> 0.51605476 | G18: =360/30 -> 12 | H18: 交货后的收款周期为30天,一般预收为20%，应收则80%
B19: 预付账款周转率 | C19: 次 | D19: =利润分析调整表!B11/资产负债分析调整表!C14 -> 0.48649737 | E19: =利润分析调整表!C11/((资产负债分析调整表!D14+资产负债分析调整表!C14)/2) -> 2.6935773 | F19: =利润分析调整表!D11/((资产负债分析调整表!E14+资产负债分析调整表!D14)/2) -> 2.8805909 | G19: =360/30 -> 12 | H19: 企业预付款后一般30天可以提货，预付款约20%
A20: 3 | B20: 流动资产周转率 | C20: 次 | D20: =利润分析调整表!B7/资产负债分析调整表!C6 -> 0.035312384 | E20: =利润分析调整表!C7/((资产负债分析调整表!C6+资产负债分析调整表!D6)/2) -> 0.13535612 | F20: =利润分析调整表!D7/((资产负债分析调整表!D6+资产负债分析调整表!E6)/2) -> 0.04228818 | G20: =(D20+E20+F20)/3 -> 0.070985561
A21: 4 | B21: 资产周转率 | C21: 次 | D21: =利润分析调整表!B7/资产负债分析调整表!C43 -> 0.028626616 | E21: =利润分析调整表!C7/((资产负债分析调整表!C43+资产负债分析调整表!D43)/2) -> 0.100801 | F21: =利润分析调整表!D7/((资产负债分析调整表!D43+资产负债分析调整表!E43)/2) -> 0.028659439 | G21: =(D21+E21+F21)/3 -> 0.052695684
B22: 应付账款周转率 | C22: 次 | D22: =利润分析调整表!B12/资产负债分析调整表!C48 -> 5.6694944 | E22: =利润分析调整表!C12/((资产负债分析调整表!C48+资产负债分析调整表!D48)/2) -> 5.9506362 | F22: =利润分析调整表!D11/((资产负债分析调整表!D48+资产负债分析调整表!E48)/2) -> 2.2804032 | G22: =360/30 -> 12 | H22: 提货后一般一个月内付款，应付款一般比例为80%
B23: 预收账款周转率 | C23: 次 | E23: =利润分析调整表!C8/((资产负债分析调整表!C49+资产负债分析调整表!D49)/1) -> 173.3541 | F23: =利润分析调整表!D8/((资产负债分析调整表!D49+资产负债分析调整表!E49)/1) -> 10.350462 | G23: =360/60 -> 6 | H23: 付款后至提货时间一般为30天，加上采购时间30天。预收比例为20%
A25: 二、 | B25: 短期偿债能力
A26: 1 | B26: 流动比率 | D26: =资产负债分析调整表!C6/资产负债分析调整表!C44 -> -35.822459 | E26: =资产负债分析调整表!D6/((资产负债分析调整表!D44+资产负债分析调整表!C44)/2) -> 18.469771 | F26: =资产负债分析调整表!E6/((资产负债分析调整表!E44+资产负债分析调整表!D44)/2) -> 6.496513 | G26: =(D26+E26+F26)/3 -> -3.6187249
A27: 2 | B27: 速动比率 | D27: =(资产负债分析调整表!C6-资产负债分析调整表!C16)/资产负债分析调整表!C44 -> -34.330055 | E27: =(资产负债分析调整表!D6-资产负债分析调整表!D16)/((资产负债分析调整表!D44+资产负债分析调整表!C44)/2) -> 17.823686 | F27: =(资产负债分析调整表!E6-资产负债分析调整表!E16)/((资产负债分析调整表!E44+资产负债分析调整表!D44)/2) -> 6.0085265 | G27: =(D27+E27+F27)/3 -> -3.4992808
A28: 三、 | B28: 长期偿债能力
A29: 1 | B29: 资产负债率 | C29: % | D29: =资产负债分析调整表!C66/资产负债分析调整表!C43*100 -> -2.2630157 | E29: =资产负债分析调整表!D66/((资产负债分析调整表!D43+资产负债分析调整表!C43)/2)*100 -> 9.9016312 | F29: =资产负债分析调整表!E66/((资产负债分析调整表!E43+资产负债分析调整表!D43)/2)*100 -> 10.229116 | G29: =(D29+E29+F29)/3 -> 5.9559106
A30: 2 | B30: 负债与股权比率 | C30: % | D30: =资产负债分析调整表!C66/资产负债分析调整表!C67*100 -> -2.2129366 | E30: =资产负债分析调整表!D66/((资产负债分析调整表!C67+资产负债分析调整表!D67)/2)*100 -> 10.300193 | F30: =资产负债分析调整表!E66/((资产负债分析调整表!D67+资产负债分析调整表!E67)/2)*100 -> 11.366011 | G30: =(D30+E30+F30)/3 -> 6.4844224
A31: 四、 | B31: 获利能力
A32: 1 | B32: 销售净利率 | C32: % | D32: =利润分析调整表!B25/利润分析调整表!B7*100 -> -279.51936 | E32: =利润分析调整表!C25/利润分析调整表!C7*100 -> -29.611567 | F32: =利润分析调整表!D25/利润分析调整表!D7*100 -> -237.3737 | G32: =(D32+E32+F32)/3 -> -182.16821
A33: 2 | B33: 资产净利率 | C33: % | D33: =利润分析调整表!B27/资产负债分析调整表!C43*100 -> -6.5455653 | E33: =利润分析调整表!C27/((资产负债分析调整表!C43+资产负债分析调整表!D43)/2)*100 -> -2.9444022 | F33: =利润分析调整表!D27/((资产负债分析调整表!D43+资产负债分析调整表!E43)/2)*100 -> -6.6680368 | G33: =(D33+E33+F33)/3 -> -5.3860014
A34: 3 | B34: 成本费用利润率 | C34: % | D34: =利润分析调整表!B25/利润分析调整表!B10*100 -> -72.56035 | E34: =利润分析调整表!C25/利润分析调整表!C10*100 -> -20.101374 | F34: =利润分析调整表!D25/利润分析调整表!D10*100 -> -70.349465 | G34: =(D34+E34+F34)/3 -> -54.337063
A35: 4 | B35: 净资产收益率 | C35: % | D35: =利润分析调整表!B27/资产负债分析调整表!C67*100 -> -6.4007161 | E35: =(利润分析调整表!C27/(资产负债分析调整表!C67+资产负债分析调整表!D67)/2)*100 -> -0.76573013 | F35: =(利润分析调整表!D27/(资产负债分析调整表!D67+资产负债分析调整表!E67)/2)*100 -> -1.8522856 | G35: =(D35+E35+F35)/3 -> -3.006244
B36: 注：运营能力的周转率指标，分母采用期初和期末的均值计算。

Sheet 财务指标详表
A2: =封面!B2 -> 被评估单位：福建卫东新能源股份有限公司 | E2: 评估基准日： | F2: =封面!C3 -> 2017年12月31日
A4: 一、资产负债结构分析
A5: 1.资产结构及变化分析
A6: 序号 | B6: 项目名称 | C6: =资产负债分析调整表!C4 -> 2015年12月31日 | E6: =资产负债分析调整表!D4 -> 2016年12月31日 | G6: =资产负债分析调整表!E4 -> 2017年12月31日
C7: 金额（万元） | D7: 比例% | E7: 金额（万元） | F7: 比例% | G7: 金额（万元） | H7: 比例%
A8: 1 | B8: 流动资产 | C8: =资产负债分析调整表!C6/10000 -> 8311.6651 | D8: =C8/C$10 -> 0.81066787 | E8: =资产负债分析调整表!D6/10000 -> 7667.3213 | F8: =E8/E$10 -> 0.68434962 | G8: =资产负债分析调整表!E6/10000 -> 7061.0292 | H8: =G8/G$10 -> 0.67065994
A9: 2 | B9: 非流动资产 | C9: =资产负债分析调整表!C20/10000 -> 1941.196 | D9: =C9/C$10 -> 0.18933213 | E9: =资产负债分析调整表!D20/10000 -> 3536.486 | F9: =E9/E$10 -> 0.31565038 | G9: =资产负债分析调整表!E20/10000 -> 3467.45 | H9: =G9/G$10 -> 0.32934006
A10: 3 | B10: 合计 | C10: =SUM(C8:C9) -> 10252.861 | D10: =C10/C$10 -> 1 | E10: =SUM(E8:E9) -> 11203.807 | F10: =E10/E$10 -> 1 | G10: =SUM(G8:G9) -> 10528.479 | H10: =G10/G$10 -> 1
A12: 2.流动资产结构及变化分析
A13: 序号 | B13: 项目名称 | C13: =C6 -> 2015年12月31日 | E13: =E6 -> 2016年12月31日 | G13: =G6 -> 2017年12月31日
C14: 金额（万元） | D14: 比例% | E14: 金额（万元） | F14: 比例% | G14: 金额（万元） | H14: 比例%
A15: 1 | B15: ='[34]表I-3资产负债分析调整表'!B7 -> 货币资金 | C15: =资产负债分析调整表!C7/10000 -> 662.84143 | D15: =IF(C$28=0,0,C15/C$28) -> 0.079748332 | E15: =资产负债分析调整表!D7/10000 -> 11.747661 | F15: =IF(E$28=0,0,E15/E$28) -> 0.0015321728 | G15: =资产负债分析调整表!E7/10000 -> 6.408064 | H15: =IF(G$28=0,0,G15/G$28) -> 0.00090752549
A16: 2 | B16: ='[34]表I-3资产负债分析调整表'!B8 -> 交易性金融资产净额 | C16: =资产负债分析调整表!C8/10000 -> 61.9575 | D16: =IF(C$28=0,0,C16/C$28) -> 0.0074542825 | E16: =资产负债分析调整表!D8/10000 -> 0 | F16: =IF(E$28=0,0,E16/E$28) -> 0 | G16: =资产负债分析调整表!E8/10000 -> 0 | H16: =IF(G$28=0,0,G16/G$28) -> 0
A17: 3 | B17: ='[34]表I-3资产负债分析调整表'!B9 -> 应收票据 | C17: =资产负债分析调整表!C9/10000 -> 0 | D17: =IF(C$28=0,0,C17/C$28) -> 0 | E17: =资产负债分析调整表!D9/10000 -> 190 | F17: =IF(E$28=0,0,E17/E$28) -> 0.024780493 | G17: =资产负债分析调整表!E9/10000 -> 0 | H17: =IF(G$28=0,0,G17/G$28) -> 0
A18: 4 | B18: ='[34]表I-3资产负债分析调整表'!B10 -> 应收股利(应收利润) | C18: =资产负债分析调整表!C10/10000 -> 0 | D18: =IF(C$28=0,0,C18/C$28) -> 0 | E18: =资产负债分析调整表!D10/10000 -> 0 | F18: =IF(E$28=0,0,E18/E$28) -> 0 | G18: =资产负债分析调整表!E10/10000 -> 0 | H18: =IF(G$28=0,0,G18/G$28) -> 0
A19: 5 | B19: ='[34]表I-3资产负债分析调整表'!B11 -> 应收利息 | C19: =资产负债分析调整表!C11/10000 -> 0 | D19: =IF(C$28=0,0,C19/C$28) -> 0 | E19: =资产负债分析调整表!D11/10000 -> 0 | F19: =IF(E$28=0,0,E19/E$28) -> 0 | G19: =资产负债分析调整表!E11/10000 -> 0 | H19: =IF(G$28=0,0,G19/G$28) -> 0
A20: 6 | B20: ='[34]表I-3资产负债分析调整表'!B12 -> 应收账款净额 | C20: =资产负债分析调整表!C12/10000 -> 344.08541 | D20: =IF(C$28=0,0,C20/C$28) -> 0.041397891 | E20: =资产负债分析调整表!D12/10000 -> 880.93359 | F20: =IF(E$28=0,0,E20/E$28) -> 0.11489457 | G20: =资产负债分析调整表!E12/10000 -> 325.98318 | H20: =IF(G$28=0,0,G20/G$28) -> 0.046166525
A21: 7 | B21: ='[34]表I-3资产负债分析调整表'!B13 -> 其他应收款净额 | C21: =资产负债分析调整表!C13/10000 -> 6461.8993 | D21: =IF(C$28=0,0,C21/C$28) -> 0.77744942 | E21: =资产负债分析调整表!D13/10000 -> 6226.7599 | F21: =IF(E$28=0,0,E21/E$28) -> 0.81211674 | G21: =资产负债分析调整表!E13/10000 -> 5970.1035 | H21: =IF(G$28=0,0,G21/G$28) -> 0.84550046
A22: 8 | B22: ='[34]表I-3资产负债分析调整表'!B14 -> 预付帐款 | C22: =资产负债分析调整表!C14/10000 -> 434.60836 | D22: =IF(C$28=0,0,C22/C$28) -> 0.052288963 | E22: =资产负债分析调整表!D14/10000 -> 89.672235 | F22: =IF(E$28=0,0,E22/E$28) -> 0.01169538 | G22: =资产负债分析调整表!E14/10000 -> 228.14434 | H22: =IF(G$28=0,0,G22/G$28) -> 0.032310352
A23: 9 | B23: ='[34]表I-3资产负债分析调整表'!B15 -> 应收补贴款 | C23: =资产负债分析调整表!C15/10000 -> 0 | D23: =IF(C$28=0,0,C23/C$28) -> 0 | E23: =资产负债分析调整表!D15/10000 -> 0 | F23: =IF(E$28=0,0,E23/E$28) -> 0 | G23: =资产负债分析调整表!E15/10000 -> 0 | H23: =IF(G$28=0,0,G23/G$28) -> 0
A24: 10 | B24: ='[34]表I-3资产负债分析调整表'!B16 -> 存货净额 | C24: =资产负债分析调整表!C16/10000 -> 346.27318 | D24: =IF(C$28=0,0,C24/C$28) -> 0.041661108 | E24: =资产负债分析调整表!D16/10000 -> 268.20787 | F24: =IF(E$28=0,0,E24/E$28) -> 0.034980649 | G24: =资产负债分析调整表!E16/10000 -> 530.39016 | H24: =IF(G$28=0,0,G24/G$28) -> 0.075115134
A25: 11 | B25: ='[34]表I-3资产负债分析调整表'!B17 -> 待摊费用 | C25: =资产负债分析调整表!C17/10000 -> 0 | D25: =IF(C$28=0,0,C25/C$28) -> 0 | E25: =资产负债分析调整表!D17/10000 -> 0 | F25: =IF(E$28=0,0,E25/E$28) -> 0 | G25: =资产负债分析调整表!E17/10000 -> 0 | H25: =IF(G$28=0,0,G25/G$28) -> 0
A26: 12 | B26: ='[34]表I-3资产负债分析调整表'!B18 -> 一年内到期的非流动资产 | C26: =资产负债分析调整表!C18/10000 -> 0 | D26: =IF(C$28=0,0,C26/C$28) -> 0 | E26: =资产负债分析调整表!D18/10000 -> 0 | F26: =IF(E$28=0,0,E26/E$28) -> 0 | G26: =资产负债分析调整表!E18
A27: 13 | B27: ='[34]表I-3资产负债分析调整表'!B19 -> 其他流动资产 | C27: =资产负债分析调整表!C19/10000 -> 0 | D27: =IF(C$28=0,0,C27/C$28) -> 0 | E27: =资产负债分析调整表!D19/10000 -> 0 | F27: =IF(E$28=0,0,E27/E$28) -> 0 | G27: =资产负债分析调整表!E19 -> 0 | H27: =IF(G$28=0,0,G27/G$28) -> 0
A28: 14 | B28: 合计 | C28: =SUM(C15:C27) -> 8311.6651 | D28: =SUM(D15:D27) -> 1 | E28: =SUM(E15:E27) -> 7667.3213 | F28: =SUM(F15:F27) -> 1 | G28: =SUM(G15:G27) -> 7061.0292 | H28: =SUM(H15:H27) -> 1
A30: 3.应收账款分析
A31: 序号 | B31: 账龄 | C31: =C13 -> 2015年12月31日
C32: 账面原值（万元） | D32: 比例 | E32: 坏账准备（万元） | F32: 计提比例 | G32: 账面净值（万元）
A33: 1 | B33: 1年以内 | C33: 356434.06 | D33: =IF(C$37=0,0,C33/C$37) -> 0.096557398 | F33: =IF(C33=0,0,ROUND(E33/C33,3)) -> 0 | G33: =C33-E33 -> 356434.06
A34: 2 | B34: 1～2年 | C34: 3322387.5 | D34: =IF(C$37=0,0,C34/C$37) -> 0.90002928 | F34: =IF(C34=0,0,ROUND(E34/C34,3)) -> 0 | G34: =C34-E34 -> 3322387.5
A35: 3 | B35: 2～3年 | D35: =IF(C$37=0,0,C35/C$37) -> 0 | F35: =IF(C35=0,0,ROUND(E35/C35,3)) -> 0 | G35: =C35-E35 -> 0
A36: 4 | B36: 3年以上 | C36: 12600 | D36: =IF(C$37=0,0,C36/C$37) -> 0.0034133192 | F36: =IF(C36=0,0,ROUND(E36/C36,3)) -> 0 | G36: =C36-E36 -> 12600
A37: 5 | B37: 合计 | C37: =SUM(C33:C36) -> 3691421.6 | D37: =IF(C$37=0,0,C37/C$37) -> 1 | E37: =SUM(E33:E36) -> 0 | G37: =C37-E37 -> 3691421.6
A39: 序号 | B39: 账龄 | C39: =E6 -> 2016年12月31日
C40: 账面原值（万元） | D40: 比例 | E40: 坏账准备（万元） | F40: 计提比例 | G40: 账面净值（万元）
A41: 1 | B41: 1年以内 | C41: 1430.0284 | D41: =IF(C$45=0,0,C41/C$45) -> 0.99982129 | E41: 71.50142 | F41: =IF(C41=0,0,ROUND(E41/C41,3)) -> 0.05 | G41: =C41-E41 -> 1358.527
A42: 2 | B42: 1～2年 | C42: 0 | D42: =IF(C$45=0,0,C42/C$45) -> 0 | F42: =IF(C42=0,0,ROUND(E42/C42,3)) -> 0 | G42: =C42-E42 -> 0
A43: 3 | B43: 2～3年 | C43: 0.2556 | D43: =IF(C$45=0,0,C43/C$45) -> 0.00017870577 | E43: 0.07668 | F43: =IF(C43=0,0,ROUND(E43/C43,3)) -> 0.3 | G43: =C43-E43 -> 0.17892
A44: 4 | B44: 3年以上 | D44: =IF(C$45=0,0,C44/C$45) -> 0 | F44: =IF(C44=0,0,ROUND(E44/C44,3)) -> 0 | G44: =C44-E44 -> 0
A45: 5 | B45: 合计 | C45: =SUM(C41:C44) -> 1430.284 | D45: =IF(C$45=0,0,C45/C$45) -> 1 | E45: =SUM(E41:E44) -> 71.5781 | G45: =C45-E45 -> 1358.7059
A47: 序号 | B47: 账龄 | C47: =G6 -> 2017年12月31日
C48: 账面原值（万元） | D48: 比例 | E48: 坏账准备（万元） | F48: 计提比例 | G48: 账面净值（万元）
A49: 1 | B49: 1年以内 | C49: =356434.06/10000 -> 35.643406 | D49: =IF(C$54=0,0,C49/C$54) -> 0.093679573 | F49: =IF(C49=0,0,ROUND(E49/C49,3)) -> 0 | G49: =C49-E49 -> 35.643406
A50: 2 | B50: 1～3年 | C50: =3322387.5/10000 -> 332.23875 | D50: =IF(C$54=0,0,C50/C$54) -> 0.87320455 | F50: =IF(C50=0,0,ROUND(E50/C50,3)) -> 0 | G50: =C50-E50 -> 332.23875
A51: 3 | B51: 2～3年 | D51: =IF(C$54=0,0,C51/C$54) -> 0 | E51: 0.07668 | F51: =IF(C51=0,0,ROUND(E51/C51,3)) -> 0 | G51: =C51-E51 -> -0.07668
A52: 4 | B52: 3年以上 | C52: =126000/10000 -> 12.6 | D52: =IF(C$54=0,0,C52/C$54) -> 0.033115876 | F52: =IF(C52=0,0,ROUND(E52/C52,3)) -> 0 | G52: =C52-E52 -> 12.6
B53: 坏帐准备 | D53: =IF(C$54=0,0,C53/C$54) -> 0 | E53: =544989.77/10000 -> 54.498977 | F53: =IF(C53=0,0,ROUND(E53/C53,3)) -> 0 | G53: =C53-E53 -> -54.498977
A54: 5 | B54: 合计 | C54: =SUM(C49:C53) -> 380.48216 | D54: =IF(C$54=0,0,C54/C$54) -> 1 | E54: =SUM(E49:E53) -> 54.575657 | G54: =C54-E54 -> 325.9065
A56: 4.存货分析
A57: 序号 | B57: 项目名称 | C57: =C6 -> 2015年12月31日 | E57: =E6 -> 2016年12月31日 | G57: =G6 -> 2017年12月31日
C58: 金额（万元） | D58: 比例% | E58: 金额（万元） | F58: 比例% | G58: 金额（万元） | H58: 比例%
A59: 1 | B59: 材料采购（在途材料） | D59: =IF(C$67=0,0,C59/C$67) -> 0 | F59: =IF(E$67=0,0,E59/E$67) -> 0 | H59: =IF(G$67=0,0,G59/G$67) -> 0
A60: 2 | B60: 原材料 | D60: =IF(C$67=0,0,C60/C$67) -> 0 | F60: =IF(E$67=0,0,E60/E$67) -> 0 | G60: =1745470.4/10000 -> 174.54704 | H60: =IF(G$67=0,0,G60/G$67) -> 0.32909178
A61: 3 | B61: 在库周转材料 | D61: =IF(C$67=0,0,C61/C$67) -> 0 | F61: =IF(E$67=0,0,E61/E$67) -> 0 | H61: =IF(G$67=0,0,G61/G$67) -> 0
A62: 4 | B62: 委托外加工物质 | D62: =IF(C$67=0,0,C62/C$67) -> 0 | F62: =IF(E$67=0,0,E62/E$67) -> 0 | H62: =IF(G$67=0,0,G62/G$67) -> 0
A63: 5 | B63: 产成品（库存商品） | D63: =IF(C$67=0,0,C63/C$67) -> 0 | F63: =IF(E$67=0,0,E63/E$67) -> 0 | G63: =2215836.3/10000 -> 221.58363 | H63: =IF(G$67=0,0,G63/G$67) -> 0.41777478
A64: 6 | B64: 在产品（自制半成品） | D64: =IF(C$67=0,0,C64/C$67) -> 0 | F64: =IF(E$67=0,0,E64/E$67) -> 0 | G64: =1342594.86/10000 -> 134.25949 | H64: =IF(G$67=0,0,G64/G$67) -> 0.25313344
A65: 7 | B65: 发出商品 | D65: =IF(C$67=0,0,C65/C$67) -> 0 | F65: =IF(E$67=0,0,E65/E$67) -> 0 | H65: =IF(G$67=0,0,G65/G$67) -> 0
A66: 8 | B66: 在用周转材料 | D66: =IF(C$67=0,0,C66/C$67) -> 0 | F66: =IF(E$67=0,0,E66/E$67) -> 0 | H66: =IF(G$67=0,0,G66/G$67) -> 0
A67: 9 | B67: 存货合计 | C67: =C59+C60+C61+C62+C63+C64+C65+C66 -> 0 | D67: =IF(C$67=0,0,C67/C$67) -> 0 | E67: =E59+E60+E61+E62+E63+E64+E65+E66 -> 0 | F67: =IF(E$67=0,0,E67/E$67) -> 0 | G67: =G59+G60+G61+G62+G63+G64+G65+G66 -> 530.39016 | H67: =IF(G$67=0,0,G67/G$67) -> 1
A68: 10 | B68: 减：存货跌价准备 | C68: 0 | E68: 0 | G68: 0
A69: 11 | B69: 存货净额 | C69: =资产负债分析调整表!C16/10000 -> 346.27318 | E69: =资产负债分析调整表!D16/10000 -> 268.20787 | G69: =G67-G68 -> 530.39016
A70: 12 | B70: 存货增加额 | E70: =E69-C69 -> -78.065312 | G70: =G69-E69 -> 262.18228
A71: 13 | B71: 增长比率 | E71: =E70/C69 -> -0.22544429 | G71: =G70/E69 -> 0.9775339
B72: check | C72: =IF(C69='[34]表I-3资产负债分析调整表'!D16,"","false") -> false | E72: =IF(E69='[34]表I-3资产负债分析调整表'!F16,"","false") -> #REF! | G72: =IF(G69='[34]表I-3资产负债分析调整表'!H16,"","false") -> false
A74: 5.非流动资产结构及分析
A75: 序号 | B75: 项目名称 | C75: =C6 -> 2015年12月31日 | E75: =E6 -> 2016年12月31日 | G75: =G6 -> 2017年12月31日
C76: 金额（万元） | D76: 比例% | E76: 金额（万元） | F76: 比例% | G76: 金额（万元） | H76: 比例%
A77: 1 | B77: ='[34]表I-3资产负债分析调整表'!B21 -> 可供出售金融资产净额 | C77: =资产负债分析调整表!C21 -> 0 | D77: =IF(C$94=0,0,C77/C$94) -> 0 | E77: =资产负债分析调整表!D21 -> 0 | F77: =IF(E$94=0,0,E77/E$94) -> 0 | G77: =资产负债分析调整表!E21 -> 0 | H77: =IF(G$94=0,0,G77/G$94) -> 0
A78: 2 | B78: ='[34]表I-3资产负债分析调整表'!B22 -> 持有至到期投资净额 | C78: =资产负债分析调整表!C22 -> 0 | D78: =IF(C$94=0,0,C78/C$94) -> 0 | E78: =资产负债分析调整表!D22 -> 0 | F78: =IF(E$94=0,0,E78/E$94) -> 0 | G78: =资产负债分析调整表!E22 -> 0 | H78: =IF(G$94=0,0,G78/G$94) -> 0
A79: 3 | B79: ='[34]表I-3资产负债分析调整表'!B23 -> 长期股权投资净额 | C79: =资产负债分析调整表!C23 -> 0 | D79: =IF(C$94=0,0,C79/C$94) -> 0 | E79: =资产负债分析调整表!D23/10000 -> 1500 | F79: =IF(E$94=0,0,E79/E$94) -> 0.42414984 | G79: =资产负债分析调整表!E23/10000 -> 1500 | H79: =IF(G$94=0,0,G79/G$94) -> 0.43259455
A80: 4 | B80: ='[34]表I-3资产负债分析调整表'!B24 -> 长期应收款 | C80: =资产负债分析调整表!C24 -> 0 | D80: =IF(C$94=0,0,C80/C$94) -> 0 | E80: =资产负债分析调整表!D24 -> 0 | F80: =IF(E$94=0,0,E80/E$94) -> 0 | G80: =资产负债分析调整表!E24 -> 0 | H80: =IF(G$94=0,0,G80/G$94) -> 0
A81: 5 | B81: ='[34]表I-3资产负债分析调整表'!B25 -> 投资性房地产 | C81: =资产负债分析调整表!C25 -> 0 | D81: =IF(C$94=0,0,C81/C$94) -> 0 | E81: =资产负债分析调整表!D25 -> 0 | F81: =IF(E$94=0,0,E81/E$94) -> 0 | G81: =资产负债分析调整表!E25 -> 0 | H81: =IF(G$94=0,0,G81/G$94) -> 0
A82: 6 | B82: ='[34]表I-3资产负债分析调整表'!B31 -> 固定资产净额 | C82: =资产负债分析调整表!C31/10000 -> 1131.0294 | D82: =IF(C$94=0,0,C82/C$94) -> 0.58264563 | E82: =资产负债分析调整表!D31/10000 -> 1244.4368 | F82: =IF(E$94=0,0,E82/E$94) -> 0.3518851 | G82: =资产负债分析调整表!E31/10000 -> 1193.8056 | H82: =IF(G$94=0,0,G82/G$94) -> 0.34428919
A83: 7 | B83: ='[34]表I-3资产负债分析调整表'!B32 -> 工程物资 | C83: =资产负债分析调整表!C32 -> 0 | D83: =IF(C$94=0,0,C83/C$94) -> 0 | E83: =资产负债分析调整表!D32/10000 -> 0 | F83: =IF(E$94=0,0,E83/E$94) -> 0 | G83: =资产负债分析调整表!E32 -> 0 | H83: =IF(G$94=0,0,G83/G$94) -> 0
A84: 8 | B84: ='[34]表I-3资产负债分析调整表'!B33 -> 在建工程 | C84: =资产负债分析调整表!C33 -> 0 | D84: =IF(C$94=0,0,C84/C$94) -> 0 | E84: =资产负债分析调整表!D33/10000 -> 0 | F84: =IF(E$94=0,0,E84/E$94) -> 0 | G84: =资产负债分析调整表!E33 -> 0 | H84: =IF(G$94=0,0,G84/G$94) -> 0
A85: 9 | B85: ='[34]表I-3资产负债分析调整表'!B34 -> 固定资产清理 | C85: =资产负债分析调整表!C34 -> 0 | D85: =IF(C$94=0,0,C85/C$94) -> 0 | E85: =资产负债分析调整表!D34/10000 -> 0 | F85: =IF(E$94=0,0,E85/E$94) -> 0 | G85: =资产负债分析调整表!E34 -> 0 | H85: =IF(G$94=0,0,G85/G$94) -> 0
A86: 10 | B86: ='[34]表I-3资产负债分析调整表'!B35 -> 生产性生物资产净额 | C86: =资产负债分析调整表!C35 -> 0 | D86: =IF(C$94=0,0,C86/C$94) -> 0 | E86: =资产负债分析调整表!D35/10000 -> 0 | F86: =IF(E$94=0,0,E86/E$94) -> 0 | G86: =资产负债分析调整表!E35 -> 0 | H86: =IF(G$94=0,0,G86/G$94) -> 0
A87: 11 | B87: ='[34]表I-3资产负债分析调整表'!B36 -> 油气资产净值 | C87: =资产负债分析调整表!C36 -> 0 | D87: =IF(C$94=0,0,C87/C$94) -> 0 | E87: =资产负债分析调整表!D36/10000 -> 0 | F87: =IF(E$94=0,0,E87/E$94) -> 0 | G87: =资产负债分析调整表!E36 -> 0 | H87: =IF(G$94=0,0,G87/G$94) -> 0
A88: 12 | B88: ='[34]表I-3资产负债分析调整表'!B37 -> 开发支出 | C88: =资产负债分析调整表!C37 -> 0 | D88: =IF(C$94=0,0,C88/C$94) -> 0 | E88: =资产负债分析调整表!D37/10000 -> 0 | F88: =IF(E$94=0,0,E88/E$94) -> 0 | G88: =资产负债分析调整表!E37 -> 0 | H88: =IF(G$94=0,0,G88/G$94) -> 0
A89: 13 | B89: ='[34]表I-3资产负债分析调整表'!B38 -> 商誉 | C89: =资产负债分析调整表!C38 -> 0 | D89: =IF(C$94=0,0,C89/C$94) -> 0 | E89: =资产负债分析调整表!D38/10000 -> 0 | F89: =IF(E$94=0,0,E89/E$94) -> 0 | G89: =资产负债分析调整表!E38 -> 0 | H89: =IF(G$94=0,0,G89/G$94) -> 0
A90: 14 | B90: ='[34]表I-3资产负债分析调整表'!B39 -> 无形资产净额 | C90: =资产负债分析调整表!C39/10000 -> 481.22454 | D90: =IF(C$94=0,0,C90/C$94) -> 0.24790105 | E90: =资产负债分析调整表!D39/10000 -> 449.60758 | F90: =IF(E$94=0,0,E90/E$94) -> 0.12713399 | G90: =资产负债分析调整表!E39/10000 -> 416.53777 | H90: =IF(G$94=0,0,G90/G$94) -> 0.12012798
A91: 15 | B91: ='[34]表I-3资产负债分析调整表'!B40 -> 长期待摊费用 | C91: =资产负债分析调整表!C40/10000 -> 0 | D91: =IF(C$94=0,0,C91/C$94) -> 0 | E91: =资产负债分析调整表!D40/10000 -> 0 | F91: =IF(E$94=0,0,E91/E$94) -> 0 | G91: =资产负债分析调整表!E40 -> 0 | H91: =IF(G$94=0,0,G91/G$94) -> 0
A92: 16 | B92: ='[34]表I-3资产负债分析调整表'!B41 -> 其他非流动资产 | C92: =资产负债分析调整表!C41/10000 -> 0 | D92: =IF(C$94=0,0,C92/C$94) -> 0 | E92: =资产负债分析调整表!D41/10000 -> 0 | F92: =IF(E$94=0,0,E92/E$94) -> 0 | G92: =资产负债分析调整表!E41 -> 0 | H92: =IF(G$94=0,0,G92/G$94) -> 0
A93: 17 | B93: ='[34]表I-3资产负债分析调整表'!B42 -> 递延所得税资产 | C93: =资产负债分析调整表!C42/10000 -> 328.9421 | D93: =IF(C$94=0,0,C93/C$94) -> 0.16945331 | E93: =资产负债分析调整表!D42/10000 -> 342.4417 | F93: =IF(E$94=0,0,E93/E$94) -> 0.096831064 | G93: =资产负债分析调整表!E42/10000 -> 357.1067 | H93: =IF(G$94=0,0,G93/G$94) -> 0.10298828
A94: 18 | B94: 合计 | C94: =SUM(C77:C93) -> 1941.196 | D94: =IF(C$94=0,0,C94/C$94) -> 1 | E94: =SUM(E77:E93) -> 3536.486 | F94: =IF(E$94=0,0,E94/E$94) -> 1 | G94: =SUM(G77:G93) -> 3467.45 | H94: =IF(G$94=0,0,G94/G$94) -> 1
A96: 6.固定资产结构分析
A97: 序号 | B97: 项目名称 | C97: =C75 -> 2015年12月31日 | E97: =E75 -> 2016年12月31日 | G97: =G75 -> 2017年12月31日
C98: 金额（万元） | D98: 比例% | E98: 金额（万元） | F98: 比例% | G98: 金额（万元） | H98: 比例%
A99: 1 | B99: 房屋建筑物类 | D99: =IF(C$103=0,0,C99/C$103) -> 0 | F99: =IF(E$103=0,0,E99/E$103) -> 0 | H99: =IF(G$103=0,0,G99/G$103) -> 0
A100: 2 | B100: 机器设备 | D100: =IF(C$103=0,0,C100/C$103) -> 0 | F100: =IF(E$103=0,0,E100/E$103) -> 0 | G100: =11170704.83/10000 -> 1117.0705 | H100: =IF(G$103=0,0,G100/G$103) -> 0.9357223
A101: 3 | B101: 车辆 | D101: =IF(C$103=0,0,C101/C$103) -> 0 | F101: =IF(E$103=0,0,E101/E$103) -> 0 | G101: =663735.04/10000 -> 66.373504 | H101: =IF(G$103=0,0,G101/G$103) -> 0.055598253
A102: 4 | B102: 电子类和其他设备 | D102: =IF(C$103=0,0,C102/C$103) -> 0 | F102: =IF(E$103=0,0,E102/E$103) -> 0 | G102: =103615.71/10000 -> 10.361571 | H102: =IF(G$103=0,0,G102/G$103) -> 0.0086794461
A103: 5 | B103: 固定资产合计 | D103: =IF(C$103=0,0,C103/C$103) -> 0 | F103: =IF(E$103=0,0,E103/E$103) -> 0 | G103: =G99+G100+G101+G102 -> 1193.8056 | H103: =IF(G$103=0,0,G103/G$103) -> 1
A104: 6 | B104: 减：固定资产减值准备 | G104: 0
A105: 7 | B105: 固定资产净额 | G105: =G103-G104 -> 1193.8056
A106: 8 | B106: 固定资产增加额 | G106: =G105-E105 -> 1193.8056
A107: 9 | B107: 增长比率 | E107: =E106/C105 -> #DIV/0! | G107: =G106/E105 -> #DIV/0!
B108: check | C108: =IF(C105='[34]表I-3资产负债分析调整表'!D26,"","false") -> false | E108: =IF(E105='[34]表I-3资产负债分析调整表'!F26,"","false") -> #REF! | G108: =IF(G105='[34]表I-3资产负债分析调整表'!H26,"","false") -> false
A109: 7.基准日固定资产成新率分析
...

Sheet 收入--历史经营情况分析
B2: 项目 | C2: 2017 年 | E2: 2016年 | G2: 2015 年
C3: 金额 | D3: 比例 | E3: 金额 | F3: 比例 | G3: 金额 | H3: 比例
B4: 一、产品销售收入 | C4: =SUM(C5:C9) -> 216.72 | D4: =C4/C11 -> 0.69591326 | E4: =SUM(E5:E9) -> 717.95 | F4: =E4/E11 -> 0.68548524 | G4: =SUM(G5:G9) -> 221.83 | H4: =G4/G11 -> 0.75579463
B5: 其中： 镍氢电池组 | C5: 92.48 | D5: =C5/$C$4 -> 0.42672573 | E5: 15.77 | F5: =E5/$E$4 -> 0.021965318 | G5: 57.73 | H5: =G5/$G$4 -> 0.26024433
B6: 镍氢电池单体 | C6: 0.41 | D6: =C6/$C$4 -> 0.001891842 | E6: 0 | F6: =E6/$E$4 -> 0 | G6: 164.1 | H6: =G6/$G$4 -> 0.73975567
B7: 镍氢动力电池系统 | C7: 120.11 | D7: =C7/$C$4 -> 0.55421742 | E7: 692.31 | F7: =E7/$E$4 -> 0.96428721 | G7: 0 | H7: =G7/$G$4 -> 0
B8: 镍氢动力电池正负极板 | C8: 3.72 | D8: =C8/$C$4 -> 0.017165006 | E8: 9.87 | F8: =E8/$E$4 -> 0.013747475 | G8: 0 | H8: =G8/$G$4 -> 0
B9: 镍氢电池生产设备 | C9: 0 | D9: =C9/$C$4 -> 0 | E9: 0 | F9: =E9/$E$4 -> 0 | G9: 0 | H9: =G9/$G$4 -> 0
B10: 二、材料销售收入 | C10: =946981.23/10000 -> 94.698123 | D10: =C10/C11 -> 0.30408674 | E10: =3294102.57/10000 -> 329.41026 | F10: =E10/E11 -> 0.31451476 | G10: =716756.56/10000 -> 71.675656 | H10: =G10/G11 -> 0.24420537
B11: 收入合计 | C11: =C4+C10 -> 311.41812 | D11: =D4+D10 -> 1 | E11: =E4+E10 -> 1047.3603 | F11: =F4+F10 -> 1 | G11: =G4+G10 -> 293.50566 | H11: =H4+H10 -> 1

Sheet 收入--2018年收入分析表
A1: 一、主要管理者的访谈 | B1: 根据访谈情况：卫东新能源公司实行“以销定产”的经营模式，而15年到17年由于处于对购买的非专利技术进行吸收改进创新阶段，未能大规模地投入量产，且产品处于初投入市场状态，销售未达到预期，产能未能满负荷生产，造成各项经营数据都不正常。2018年随着公司销售渠道的拓展，生产电池生产设备及电池组及配件等让其销售收入有了大幅的增加。随着卫东新能源公司销售的拓展，各种盈利能力、营运能力指标将逐渐向良性方向发展。
A2: 二、截至现场勘查日已签订的销售合同
A3: 1、合同情况 | B3: 根据统计，截至现场勘查日，被评估企业已经签订的销售合同有8份（其中2份为同一客户），合同总金额为3218.26万元。
A11: 2、主要合同访谈分析情况 | B11: 福建翰飞新能源科技有限公司
B12: 同创精密自动化设备有限公司
A13: 3、登记的合同统计分析 | B13: 项目 | C13: 合同金额（不含税）
B14: 镍氢电池组 | C14: 3.67
B15: 镍氢电池单体 | C15: 328.13
B16: 镍氢动力电池系统 | C16: 218.8
B17: 镍氢动力电池正负极板 | C17: 1039.32
B18: 镍氢电池生产设备 | C18: 1161.25
B19: 收入合计 | C19: 2751.17

Sheet 收入预测表
D2: 0.2 | E2: 0.18 | F2: 0.15 | G2: 0.1 | H2: 0
B3: 产品品称 | C3: 2018年 | D3: 2019年 | E3: 2020年 | F3: 2021年 | G3: 2022年 | H3: 2023年及以后
B4: 镍氢电池组 | C4: ='收入--2018年收入分析表'!C14 -> 3.67 | D4: =C4*(1+$D$2) -> 4.404 | E4: =D4*(1+$E$2) -> 5.19672 | F4: =E4*(1+$F$2) -> 5.976228 | G4: =F4*(1+$G$2) -> 6.5738508 | H4: =G4*(1+$H$2) -> 6.5738508
B5: 镍氢电池单体 | C5: ='收入--2018年收入分析表'!C15 -> 328.13 | D5: =C5*(1+$D$2) -> 393.756 | E5: =D5*(1+$E$2) -> 464.63208 | F5: =E5*(1+$F$2) -> 534.32689 | G5: =F5*(1+$G$2) -> 587.75958 | H5: =G5*(1+$H$2) -> 587.75958
B6: 镍氢动力电池系统 | C6: ='收入--2018年收入分析表'!C16 -> 218.8 | D6: =C6*(1+$D$2) -> 262.56 | E6: =D6*(1+$E$2) -> 309.8208 | F6: =E6*(1+$F$2) -> 356.29392 | G6: =F6*(1+$G$2) -> 391.92331 | H6: =G6*(1+$H$2) -> 391.92331
B7: 镍氢动力电池正负极板 | C7: ='收入--2018年收入分析表'!C17 -> 1039.32 | D7: =C7*(1+$D$2) -> 1247.184 | E7: =D7*(1+$E$2) -> 1471.6771 | F7: =E7*(1+$F$2) -> 1692.4287 | G7: =F7*(1+$G$2) -> 1861.6716 | H7: =G7*(1+$H$2) -> 1861.6716
B8: 镍氢电池生产设备 | C8: ='收入--2018年收入分析表'!C18 -> 1161.25 | D8: =C8*(1+$D$2) -> 1393.5 | E8: =D8*(1+$E$2) -> 1644.33 | F8: =E8*(1+$F$2) -> 1890.9795 | G8: =F8*(1+$G$2) -> 2080.0775 | H8: =G8*(1+$H$2) -> 2080.0775
B9: 合 计 | C9: =SUM(C4:C8) -> 2751.17 | D9: =SUM(D4:D8) -> 3301.404 | E9: =SUM(E4:E8) -> 3895.6567 | F9: =SUM(F4:F8) -> 4480.0052 | G9: =SUM(G4:G8) -> 4928.0058 | H9: =SUM(H4:H8) -> 4928.0058

Sheet 成本--成本比例分析
A3: 一、历史数据分析
B5: 项目内容 | C5: 2015年 | D5: 2016年 | E5: 2017年
A6: 镍氢电池组 | B6: 收入 | C6: ='收入--历史经营情况分析'!G5 -> 57.73 | D6: ='收入--历史经营情况分析'!E5 -> 15.77 | E6: ='收入--历史经营情况分析'!C5 -> 92.48
B7: 成本 | C7: =395108.82/10000 -> 39.510882 | D7: =250700.6/10000 -> 25.07006 | E7: =2688733.16/10000 -> 268.87332
B8: 成本收入占比 | C8: =C7/C6 -> 0.68440814 | D8: =D7/D6 -> 1.5897311 | E8: =E7/E6 -> 2.9073672
A9: 镍氢电池单体 | B9: 收入 | C9: ='收入--历史经营情况分析'!G6 -> 164.1 | D9: ='收入--历史经营情况分析'!E6 -> 0 | E9: ='收入--历史经营情况分析'!C6 -> 0.41
B10: 成本 | C10: =1023950.68/10000 -> 102.39507 | E10: =9077.54/10000 -> 0.907754
B11: 成本收入占比 | C11: =C10/C9 -> 0.6239797 | E11: =E10/E9 -> 2.2140341
A12: 镍氢动力电池系统 | B12: 收入 | C12: ='收入--历史经营情况分析'!G7 -> 0 | D12: ='收入--历史经营情况分析'!E7 -> 692.31 | E12: ='收入--历史经营情况分析'!C7 -> 120.11
B13: 成本 | D13: =4463888.7/10000 -> 446.38887 | E13: =931465.8/10000 -> 93.14658
B14: 成本收入占比 | D14: =D13/D12 -> 0.64478177 | E14: =E13/E12 -> 0.77551062
A15: 镍氢动力电池正负极板 | B15: 收入 | C15: ='收入--历史经营情况分析'!G8 -> 0 | D15: ='收入--历史经营情况分析'!E8 -> 9.87 | E15: ='收入--历史经营情况分析'!C8 -> 3.72
B16: 成本 | D16: =352163.16/10000 -> 35.216316 | E16: =86580.89/10000 -> 8.658089
B17: 成本收入占比 | D17: =D16/D15 -> 3.5680158 | E17: =E16/E15 -> 2.3274433
A18: 镍氢电池生产设备 | B18: 收入
B19: 成本
B20: 成本收入占比
A21: 材料 | B21: 收入 | C21: ='收入--历史经营情况分析'!G10 -> 71.675656 | D21: ='收入--历史经营情况分析'!E10 -> 329.41026 | E21: ='收入--历史经营情况分析'!C10 -> 94.698123
B22: 成本 | C22: 69.53 | D22: 199.42 | E22: 86.16
B23: 成本收入占比
A24: 产品成本合计 | C24: =C7+C10+C13+C16+C19+C22 -> 211.43595 | D24: =D7+D10+D13+D16+D19+D22 -> 706.09525 | E24: =E7+E10+E13+E16+E19+E22 -> 457.74574
A25: 收入合计 | C25: =C6+C9+C12+C15+C18+C21 -> 293.50566 | D25: =D6+D9+D12+D15+D18+D21 -> 1047.3603 | E25: =E6+E9+E12+E15+E18+E21 -> 311.41812
A26: 总成本占主总收入比例 | C26: 0.7204 | D26: 0.6742 | E26: 1.4699
G28: 成本占比
A29: 分析： | B29: 2015年-2017年卫东新能源的生产不足产能的10%，在成本核算上固定成本相对较高，造成单位成本偏高，甚至出现成本倒挂的现象。特别是2017年的营业收入偏低，其中的折旧费跟制造费用则按照实际发生列支，造成2017年的营业成本占营业收入的比例超高，而2015年-2016年的总成本与主营业务收入的比例属于比较正常的范围，在这二年，产能也不未充分发挥。 | F29: 分析结论：17年数据差异较大，若剔除17年因素，采用15、16年的经营数据平均值综合考虑，成本占收入的比率约为70%。 | G29: 0.7
A32: 二、行业数据分析
A34: 通过万得数据查找类似上市公司的经营数据，评估人员发现电池产品的平均销售毛利大部分位于12%~20%区间，
A38: 600478
A40: 镍
A51: 300068
A52: 锂电池
A62: 300438
A74: 000049
A76: 锂电池
A84: 002580
A86: 阀控密封式铅酸蓄电池
A97: 300207
A99: 锂离子电池
B112: 上市公司名称 | C112: 编号 | D112: 主营产品 | E112: 近4期平均毛利率
B113: 科力远 | C113: 600478 | D113: 电池占比45.52% | E113: 0.1033
B114: 南都电池 | C114: 300068 | D114: 电池占比60.49% | E114: 0.1444
B115: 鹏辉能源 | C115: 300438 | D115: 电池占比97.54% | E115: 0.2508
B116: 德赛电池 | C116: 000049 | D116: 电池占比100% | E116: 0.0817
B117: 圣阳股份 | C117: 002580 | D117: 电池占比100% | E117: 0.1626
B118: 欣旺达 | C118: 300207 | D118: 电池占比87.14% | E118: 0.1298

Sheet 主要材料情况
D3: 厂家 | E3: 产量 | F3: 采购单价
F4: 2016（7-12） | G4: 2017 | H4: 2018 | I4: 2019 | J4: 2020 | K4: 2021 | L4: 2022 | M4: 2023 | N4: 2024 | O4: 2025 | P4: 2026-2039 | Q4: 2040 | R4: 2041-2043 | S4: 2044 | T4: 2045-2048 | U4: 2049-2051
C5: 药剂PAM | F5: =$V$5*'收入--历史经营情况分析'!#REF! -> #REF! | G5: =$V$5*'收入--历史经营情况分析'!#REF! -> #REF! | H5: =$V$5*'收入--历史经营情况分析'!#REF! -> #REF! | I5: =$V$5*'收入--历史经营情况分析'!#REF! -> #REF! | J5: =$V$5*'收入--历史经营情况分析'!#REF! -> #REF! | K5: =$V$5*'收入--历史经营情况分析'!#REF! -> #REF! | L5: =$V$5*'收入--历史经营情况分析'!#REF! -> #REF! | M5: =$V$5*'收入--历史经营情况分析'!#REF! -> #REF! | ... U5: =$V$5*'收入--历史经营情况分析'!#REF! -> #REF! | V5: 0.003 | W5: 吨
C6: 单价 | F6: =$V$6 -> 12000 | G6: =$V$6 -> 12000 | H6: =$V$6 -> 12000 | I6: =$V$6 -> 12000 | J6: =$V$6 -> 12000 | K6: =$V$6 -> 12000 | L6: =$V$6 -> 12000 | M6: =$V$6 -> 12000 | ... U6: =$V$6 -> 12000 | V6: 12000 | W6: 元/吨
C7: 药剂PAC | F7: =ROUND($V$7*'收入--历史经营情况分析'!#REF!,2) -> #REF! | G7: =ROUND($V$7*'收入--历史经营情况分析'!#REF!,2) -> #REF! | H7: =ROUND($V$7*'收入--历史经营情况分析'!#REF!,2) -> #REF! | I7: =ROUND($V$7*'收入--历史经营情况分析'!#REF!,2) -> #REF! | J7: =ROUND($V$7*'收入--历史经营情况分析'!#REF!,2) -> #REF! | K7: =ROUND($V$7*'收入--历史经营情况分析'!#REF!,2) -> #REF! | L7: =ROUND($V$7*'收入--历史经营情况分析'!#REF!,2) -> #REF! | M7: =ROUND($V$7*'收入--历史经营情况分析'!#REF!,2) -> #REF! | ... U7: =ROUND($V$7*'收入--历史经营情况分析'!#REF!,2) -> #REF! | V7: 0.03 | W7: 吨
C8: 药剂单价 | F8: =$V$8 -> 1700 | G8: =$V$8 -> 1700 | H8: =$V$8 -> 1700 | I8: =$V$8 -> 1700 | J8: =$V$8 -> 1700 | K8: =$V$8 -> 1700 | L8: =$V$8 -> 1700 | M8: =$V$8 -> 1700 | ... U8: =$V$8 -> 1700 | V8: 1700 | W8: 元/吨
C9: 药剂费用 | F9: =ROUND((F5*F6+F7*F8)/10000,2) -> #REF! | G9: =ROUND((G5*G6+G7*G8)/10000,2) -> #REF! | H9: =ROUND((H5*H6+H7*H8)/10000,2) -> #REF! | I9: =ROUND((I5*I6+I7*I8)/10000,2) -> #REF! | J9: =ROUND((J5*J6+J7*J8)/10000,2) -> #REF! | K9: =ROUND((K5*K6+K7*K8)/10000,2) -> #REF! | L9: =ROUND((L5*L6+L7*L8)/10000,2) -> #REF! | M9: =ROUND((M5*M6+M7*M8)/10000,2) -> #REF! | ... U9: =ROUND((U5*U6+U7*U8)/10000,2) -> #REF!
C10: 其他材料 | F10: =ROUND(F7*$O$10,2) -> #REF! | G10: =ROUND(G7*$O$10,2) -> #REF! | H10: =ROUND(H7*$O$10,2) -> #REF! | I10: =ROUND(I7*$O$10,2) -> #REF! | J10: =ROUND(J7*$O$10,2) -> #REF! | K10: =ROUND(K7*$O$10,2) -> #REF! | L10: =ROUND(L7*$O$10,2) -> #REF! | M10: =ROUND(M7*$O$10,2) -> #REF! | N10: =ROUND(N7*$O$10,2) -> #REF!
C13: 材料费合计 | F13: =F9+F10 -> #REF! | G13: =G9+G10 -> #REF! | H13: =H9+H10 -> #REF! | I13: =I9+I10 -> #REF! | J13: =J9+J10 -> #REF! | K13: =K9+K10 -> #REF! | L13: =L9+L10 -> #REF! | M13: =M9+M10 -> #REF! | ... U13: =U9+U10 -> #REF!

Sheet 燃料动力
A2: 项目 | B2: 2016（7-12） | C2: 2017 | D2: 2018 | E2: 2019 | F2: 2020 | G2: 2021 | H2: 2022 | I2: 2023 | J2: 2024 | K2: 2025 | L2: 2026-2039 | M2: 2040 | N2: 2041-2043 | O2: 2044 | P2: 2045-2048 | Q2: 2049-2051
A3: 水 | B3: =ROUND(B4*B5/10000,2) -> 0.3 | C3: =ROUND(C4*C5/10000,2) -> 0.6 | D3: =ROUND(D4*D5/10000,2) -> 0.6 | E3: =ROUND(E4*E5/10000,2) -> 0.6 | F3: =ROUND(F4*F5/10000,2) -> 0.9 | G3: =ROUND(G4*G5/10000,2) -> 0.9 | H3: =ROUND(H4*H5/10000,2) -> 0.9 | I3: =ROUND(I4*I5/10000,2) -> 1.2 | ... Q3: =ROUND(Q4*Q5/10000,2) -> 0.3
A4: 单价 | B4: =$R$4 -> 1.17 | C4: =$R$4 -> 1.17 | D4: =$R$4 -> 1.17 | E4: =$R$4 -> 1.17 | F4: =$R$4 -> 1.17 | G4: =$R$4 -> 1.17 | H4: =$R$4 -> 1.17 | I4: =$R$4 -> 1.17 | ... Q4: =$R$4 -> 1.17 | R4: 1.17
A5: 数量 | B5: =14*365/2 -> 2555 | C5: =365*14 -> 5110 | D5: =365*14 -> 5110 | E5: =365*14 -> 5110 | F5: =365*21 -> 7665 | G5: =365*21 -> 7665 | H5: =365*21 -> 7665 | I5: =365*28 -> 10220 | J5: =365*28 -> 10220 | K5: =365*28 -> 10220 | L5: =365*28 -> 10220 | M5: =365*21 -> 7665 | N5: =365*21 -> 7665 | O5: =365*21 -> 7665 | P5: =365*14 -> 5110 | Q5: =365*7 -> 2555
A6: 电 | B6: =ROUND(B7*B8,2) -> #REF! | C6: =ROUND(C7*C8,2) -> #REF! | D6: =ROUND(D7*D8,2) -> #REF! | E6: =ROUND(E7*E8,2) -> #REF! | F6: =ROUND(F7*F8,2) -> #REF! | G6: =ROUND(G7*G8,2) -> #REF! | H6: =ROUND(H7*H8,2) -> #REF! | I6: =ROUND(I7*I8,2) -> #REF! | ... Q6: =ROUND(Q7*Q8,2) -> #REF!
A7: 单价 | B7: =$R$7 -> 0.53 | C7: =$R$7 -> 0.53 | D7: =$R$7 -> 0.53 | E7: =$R$7 -> 0.53 | F7: =$R$7 -> 0.53 | G7: =$R$7 -> 0.53 | H7: =$R$7 -> 0.53 | I7: =$R$7 -> 0.53 | ... Q7: =$R$7 -> 0.53 | R7: 0.53
A8: 数量（万kw.h) | B8: =ROUND('收入--历史经营情况分析'!#REF!*燃料动力!$R$8,2) -> #REF! | C8: =ROUND('收入--历史经营情况分析'!#REF!*燃料动力!$R$8,2) -> #REF! | D8: =ROUND('收入--历史经营情况分析'!#REF!*燃料动力!$R$8,2) -> #REF! | E8: =ROUND('收入--历史经营情况分析'!#REF!*燃料动力!$R$8,2) -> #REF! | F8: =ROUND('收入--历史经营情况分析'!#REF!*燃料动力!$R$8,2) -> #REF! | G8: =ROUND('收入--历史经营情况分析'!#REF!*燃料动力!$R$8,2) -> #REF! | H8: =ROUND('收入--历史经营情况分析'!#REF!*燃料动力!$R$8,2) -> #REF! | I8: =ROUND('收入--历史经营情况分析'!#REF!*燃料动力!$R$8,2) -> #REF! | ... Q8: =ROUND('收入--历史经营情况分析'!#REF!*燃料动力!$R$8,2) -> #REF! | R8: 0.24
A9: 外购燃料及动力费合计 | B9: =B3+B6 -> #REF! | C9: =C3+C6 -> #REF! | D9: =D3+D6 -> #REF! | E9: =E3+E6 -> #REF! | F9: =F3+F6 -> #REF! | G9: =G3+G6 -> #REF! | H9: =H3+H6 -> #REF! | I9: =I3+I6 -> #REF! | ... Q9: =Q3+Q6 -> #REF!
B12: 水： | C12: 处理一万吨水日用水量约7吨

Sheet 经营费用
B2: 2016（7-12） | C2: 2017 | D2: 2018 | E2: 2019 | F2: 2020 | G2: 2021 | H2: 2022 | I2: 2023 | J2: 2024 | K2: 2025 | L2: 2026-2039 | M2: 2040 | N2: 2041-2043 | O2: 2044 | P2: 2045-2048 | Q2: 2049-2051
A3: 工资及员工费用 | H3: =人员费用预测表!#REF! -> #REF! | I3: =人员费用预测表!#REF! -> #REF! | J3: =人员费用预测表!#REF! -> #REF! | K3: =人员费用预测表!#REF! -> #REF! | P3: =人员费用预测表!#REF! -> #REF! | Q3: =SUM(B3:P3) -> #REF!
A4: 办公费 | H4: =ROUND(H3*$S$4,2) -> #REF! | I4: =ROUND(I3*$S$4,2) -> #REF! | J4: =ROUND(J3*$S$4,2) -> #REF! | K4: =K3*0.5% -> #REF! | P4: =P3*0.5% -> #REF! | Q4: =SUM(B4:P4) -> #REF! | R4: 按照销售工资的5% | S4: 0.05
A5: 交际费 | B5: =ROUND('收入--历史经营情况分析'!#REF!*$S$5,2) -> #REF! | C5: =ROUND('收入--历史经营情况分析'!#REF!*$S$5,2) -> #REF! | D5: =ROUND('收入--历史经营情况分析'!#REF!*$S$5,2) -> #REF! | E5: =ROUND('收入--历史经营情况分析'!#REF!*$S$5,2) -> #REF! | F5: =ROUND('收入--历史经营情况分析'!#REF!*$S$5,2) -> #REF! | G5: =ROUND('收入--历史经营情况分析'!#REF!*$S$5,2) -> #REF! | H5: =ROUND('收入--历史经营情况分析'!#REF!*$S$5,2) -> #REF! | I5: =ROUND('收入--历史经营情况分析'!#REF!*$S$5,2) -> #REF! | ... Q5: =ROUND('收入--历史经营情况分析'!#REF!*$S$5,2) -> #REF! | R5: 按照收入的0.5%
A6: 车辆交通费 | B6: =ROUND('收入--历史经营情况分析'!#REF!*$S$6,2) -> #REF! | C6: =ROUND('收入--历史经营情况分析'!#REF!*$S$6,2) -> #REF! | D6: =ROUND('收入--历史经营情况分析'!#REF!*$S$6,2) -> #REF! | E6: =ROUND('收入--历史经营情况分析'!#REF!*$S$6,2) -> #REF! | F6: =ROUND('收入--历史经营情况分析'!#REF!*$S$6,2) -> #REF! | G6: =ROUND('收入--历史经营情况分析'!#REF!*$S$6,2) -> #REF! | H6: =ROUND('收入--历史经营情况分析'!#REF!*$S$6,2) -> #REF! | I6: =ROUND('收入--历史经营情况分析'!#REF!*$S$6,2) -> #REF! | ... Q6: =ROUND('收入--历史经营情况分析'!#REF!*$S$6,2) -> #REF! | R6: 按照收入的0.5%
A7: 广告费
A8: 差旅费 | B8: =ROUND('收入--历史经营情况分析'!#REF!*经营费用!$S$8,2) -> #REF! | C8: =ROUND('收入--历史经营情况分析'!#REF!*经营费用!$S$8,2) -> #REF! | D8: =ROUND('收入--历史经营情况分析'!#REF!*经营费用!$S$8,2) -> #REF! | E8: =ROUND('收入--历史经营情况分析'!#REF!*经营费用!$S$8,2) -> #REF! | F8: =ROUND('收入--历史经营情况分析'!#REF!*经营费用!$S$8,2) -> #REF! | G8: =ROUND('收入--历史经营情况分析'!#REF!*经营费用!$S$8,2) -> #REF! | H8: =ROUND('收入--历史经营情况分析'!#REF!*经营费用!$S$8,2) -> #REF! | I8: =ROUND('收入--历史经营情况分析'!#REF!*经营费用!$S$8,2) -> #REF! | ... Q8: =ROUND('收入--历史经营情况分析'!#REF!*经营费用!$S$8,2) -> #REF! | R8: 按照收入的0.2%
A9: 合计 | B9: =SUM(B3:B8) -> #REF! | C9: =SUM(C3:C8) -> #REF! | D9: =SUM(D3:D8) -> #REF! | E9: =SUM(E3:E8) -> #REF! | F9: =SUM(F3:F8) -> #REF! | G9: =SUM(G3:G8) -> #REF! | H9: =SUM(H3:H8) -> #REF! | I9: =SUM(I3:I8) -> #REF! | ... Q9: =SUM(Q3:Q8) -> #REF!

Sheet 人员费用预测表
A1: 莆田华科 2016年6月份工资表
A3: 编 号 | B3: 姓名 | C3: 标准工资 | D3: 缺勤 天数 | E3: 扣缺勤 | F3: 午餐补贴 | G3: 通讯补贴 | I3: 计税工资 | J3: 个税 | K3: 实发工资
B4: 姓名 | C4: 标准工资 | D4: 缺勤 天数 | E4: 扣缺勤 | F4: 午餐补贴 | G4: 通讯补贴 | I4: 计税工资 | J4: 个税 | K4: 实发工资
A5: 1 | I5: =#REF!-#REF! -> #REF! | J5: =ROUND(IF((I5-msjs1)>0,(I5-msjs1)*VLOOKUP((I5-msjs1),ysfw1,4)-VLOOKUP((I5-msjs1),ysfw1,5),0),2) -> #REF! | K5: =I5-J5 -> #REF!
A6: 2 | I6: =#REF!-#REF! -> #REF! | J6: =ROUND(IF((I6-msjs1)>0,(I6-msjs1)*VLOOKUP((I6-msjs1),ysfw1,4)-VLOOKUP((I6-msjs1),ysfw1,5),0),2) -> #REF! | K6: =I6-J6 -> #REF!
A7: 3 | I7: =#REF!-#REF! -> #REF! | J7: =ROUND(IF((I7-msjs1)>0,(I7-msjs1)*VLOOKUP((I7-msjs1),ysfw1,4)-VLOOKUP((I7-msjs1),ysfw1,5),0),2) -> #REF! | K7: =I7-J7 -> #REF!
A8: 4 | I8: =#REF!-#REF! -> #REF! | J8: =ROUND(IF((I8-msjs1)>0,(I8-msjs1)*VLOOKUP((I8-msjs1),ysfw1,4)-VLOOKUP((I8-msjs1),ysfw1,5),0),2) -> #REF! | K8: =I8-J8 -> #REF!
A9: 5 | I9: =#REF!-#REF! -> #REF! | J9: =ROUND(IF((I9-msjs1)>0,(I9-msjs1)*VLOOKUP((I9-msjs1),ysfw1,4)-VLOOKUP((I9-msjs1),ysfw1,5),0),2) -> #REF! | K9: =I9-J9 -> #REF!
A10: 6 | I10: =#REF!-#REF! -> #REF! | J10: =ROUND(IF((I10-msjs1)>0,(I10-msjs1)*VLOOKUP((I10-msjs1),ysfw1,4)-VLOOKUP((I10-msjs1),ysfw1,5),0),2) -> #REF! | K10: =I10-J10 -> #REF!
A11: 7 | I11: =#REF!-#REF! -> #REF! | J11: =ROUND(IF((I11-msjs1)>0,(I11-msjs1)*VLOOKUP((I11-msjs1),ysfw1,4)-VLOOKUP((I11-msjs1),ysfw1,5),0),2) -> #REF! | K11: =I11-J11 -> #REF!
A12: 8 | I12: =#REF!-#REF! -> #REF! | J12: =ROUND(IF((I12-msjs1)>0,(I12-msjs1)*VLOOKUP((I12-msjs1),ysfw1,4)-VLOOKUP((I12-msjs1),ysfw1,5),0),2) -> #REF! | K12: =I12-J12 -> #REF!
A13: 9 | I13: =#REF!-#REF! -> #REF! | J13: =ROUND(IF((I13-msjs1)>0,(I13-msjs1)*VLOOKUP((I13-msjs1),ysfw1,4)-VLOOKUP((I13-msjs1),ysfw1,5),0),2) -> #REF! | K13: =I13-J13 -> #REF!
A14: 10 | I14: =#REF!-#REF! -> #REF! | J14: =ROUND(IF((I14-msjs1)>0,(I14-msjs1)*VLOOKUP((I14-msjs1),ysfw1,4)-VLOOKUP((I14-msjs1),ysfw1,5),0),2) -> #REF! | K14: =I14-J14 -> #REF!
A15: 11 | I15: =#REF!-#REF! -> #REF! | J15: =ROUND(IF((I15-msjs1)>0,(I15-msjs1)*VLOOKUP((I15-msjs1),ysfw1,4)-VLOOKUP((I15-msjs1),ysfw1,5),0),2) -> #REF! | K15: =I15-J15 -> #REF!
A16: 12 | I16: =#REF!-#REF! -> #REF! | J16: =ROUND(IF((I16-msjs1)>0,(I16-msjs1)*VLOOKUP((I16-msjs1),ysfw1,4)-VLOOKUP((I16-msjs1),ysfw1,5),0),2) -> #REF! | K16: =I16-J16 -> #REF!
... A20: 16 | I20: =#REF!-#REF! -> #REF! | J20: =ROUND(IF((I20-msjs1)>0,(I20-msjs1)*VLOOKUP((I20-msjs1),ysfw1,4)-VLOOKUP((I20-msjs1),ysfw1,5),0),2) -> #REF! | K20: =I20-J20 -> #REF!
A21: 合计 | C21: =SUM(C5:C20) -> 0 | D21: =SUM(D5:D20) -> 0 | E21: =SUM(E5:E20) -> 0 | F21: =SUM(F5:F20) -> 0 | G21: =SUM(G5:G20) -> 0 | I21: =SUM(I5:I20) -> #REF! | J21: =SUM(J5:J20) -> #REF! | K21: =SUM(K5:K20) -> #REF!
A22: 莆田华科 2016年6月份工资表
A24: 编 号 | B24: 姓名 | C24: 标准工资 | D24: 缺勤 天数 | E24: 扣缺勤 | F24: 午餐 补贴 | G24: 通讯 补贴 | I24: 计税工资加项 | J24: 计税工资 | K24: 个税 | L24: 实发工资
B25: 姓名 | C25: 标准工资 | D25: 缺勤 天数 | E25: 扣缺勤 | F25: 午餐补贴 | G25: 通讯补贴 | I25: 计税工资加项 | J25: 计税工资 | K25: 个税
A26: 1 | I26: 0 | J26: =#REF!-#REF!-#REF!+I26 -> #REF! | K26: =ROUND(IF((J26-msjs1)>0,(J26-msjs1)*VLOOKUP((J26-msjs1),ysfw1,4)-VLOOKUP((J26-msjs1),ysfw1,5),0),2) -> #REF! | L26: =#REF!-#REF!-#REF!-K26 -> #REF!
A27: 2 | I27: =#REF!-#REF! -> #REF! | J27: =#REF!-#REF!-#REF!+I27 -> #REF! | K27: =ROUND(IF((J27-msjs1)>0,(J27-msjs1)*VLOOKUP((J27-msjs1),ysfw1,4)-VLOOKUP((J27-msjs1),ysfw1,5),0),2) -> #REF! | L27: =#REF!-#REF!-#REF!-K27 -> #REF!
A28: 3 | I28: 0 | J28: =#REF!-#REF!-#REF!+I28 -> #REF! | K28: =ROUND(IF((J28-msjs1)>0,(J28-msjs1)*VLOOKUP((J28-msjs1),ysfw1,4)-VLOOKUP((J28-msjs1),ysfw1,5),0),2) -> #REF! | L28: =#REF!-#REF!-#REF!-K28 -> #REF!
A29: 4 | I29: =#REF!-#REF! -> #REF! | J29: =#REF!-#REF!-#REF!+I29 -> #REF! | K29: =ROUND(IF((J29-msjs1)>0,(J29-msjs1)*VLOOKUP((J29-msjs1),ysfw1,4)-VLOOKUP((J29-msjs1),ysfw1,5),0),2) -> #REF! | L29: =#REF!-#REF!-#REF!-K29 -> #REF!
A30: 5 | I30: =#REF!-#REF! -> #REF! | J30: =#REF!-#REF!-#REF!+I30 -> #REF! | K30: =ROUND(IF((J30-msjs1)>0,(J30-msjs1)*VLOOKUP((J30-msjs1),ysfw1,4)-VLOOKUP((J30-msjs1),ysfw1,5),0),2) -> #REF! | L30: =#REF!-#REF!-#REF!-K30 -> #REF!
A31: 6 | I31: 0 | J31: =#REF!-#REF!-#REF!+I31 -> #REF! | K31: =ROUND(IF((J31-msjs1)>0,(J31-msjs1)*VLOOKUP((J31-msjs1),ysfw1,4)-VLOOKUP((J31-msjs1),ysfw1,5),0),2) -> #REF! | L31: =#REF!-#REF!-#REF!-K31 -> #REF!
A32: 7 | J32: =#REF!-#REF!-#REF!+I32 -> #REF! | K32: =ROUND(IF((J32-msjs1)>0,(J32-msjs1)*VLOOKUP((J32-msjs1),ysfw1,4)-VLOOKUP((J32-msjs1),ysfw1,5),0),2) -> #REF! | L32: =#REF!-#REF!-#REF!-K32 -> #REF!
A33: 8 | I33: 0 | J33: =#REF!-#REF!-#REF!+I33 -> #REF! | K33: =ROUND(IF((J33-msjs1)>0,(J33-msjs1)*VLOOKUP((J33-msjs1),ysfw1,4)-VLOOKUP((J33-msjs1),ysfw1,5),0),2) -> #REF! | L33: =#REF!-#REF!-#REF!-K33 -> #REF!
A34: 9 | I34: =#REF!-#REF! -> #REF! | J34: =#REF!-#REF!-#REF!+I34 -> #REF! | K34: =ROUND(IF((J34-msjs1)>0,(J34-msjs1)*VLOOKUP((J34-msjs1),ysfw1,4)-VLOOKUP((J34-msjs1),ysfw1,5),0),2) -> #REF! | L34: =#REF!-#REF!-#REF!-K34 -> #REF!
A35: 10 | J35: =#REF!-#REF!-#REF!+I35 -> #REF! | K35: =ROUND(IF((J35-msjs1)>0,(J35-msjs1)*VLOOKUP((J35-msjs1),ysfw1,4)-VLOOKUP((J35-msjs1),ysfw1,5),0),2) -> #REF! | L35: =#REF!-#REF!-#REF!-K35 -> #REF!
A36: 11 | I36: 0 | J36: =#REF!-#REF!-#REF!+I36 -> #REF! | K36: =ROUND(IF((J36-msjs1)>0,(J36-msjs1)*VLOOKUP((J36-msjs1),ysfw1,4)-VLOOKUP((J36-msjs1),ysfw1,5),0),2) -> #REF! | L36: =#REF!-#REF!-#REF!-K36 -> #REF!
A37: 12 | J37: =#REF!-#REF!-#REF!+I37 -> #REF! | K37: =ROUND(IF((J37-msjs1)>0,(J37-msjs1)*VLOOKUP((J37-msjs1),ysfw1,4)-VLOOKUP((J37-msjs1),ysfw1,5),0),2) -> #REF! | L37: =#REF!-#REF!-#REF!-K37 -> #REF!
A38: 13 | I38: =#REF!-#REF! -> #REF! | J38: =#REF!-#REF!-#REF!+I38 -> #REF! | K38: =ROUND(IF((J38-msjs1)>0,(J38-msjs1)*VLOOKUP((J38-msjs1),ysfw1,4)-VLOOKUP((J38-msjs1),ysfw1,5),0),2) -> #REF! | L38: =#REF!-#REF!-#REF!-K38 -> #REF!
A39: 14 | J39: =#REF!-#REF!-#REF!+I39 -> #REF! | L39: =#REF!-#REF!-#REF!-K39 -> #REF!
A40: 15 | J40: =#REF!-#REF!-#REF!+I40 -> #REF! | L40: =#REF!-#REF!-#REF!-K40 -> #REF!
A41: 16 | J41: =#REF!-#REF!-#REF!+I41 -> #REF! | L41: =#REF!-#REF!-#REF!-K41 -> #REF!
A42: 合计 | C42: =SUM(C26:C41) -> 0 | D42: =SUM(D26:D41) -> 0 | E42: =SUM(E26:E41) -> 0 | F42: =SUM(F26:F41) -> 0 | G42: =SUM(G26:G41) -> 0 | I42: =SUM(I26:I41) -> #REF! | J42: =SUM(J26:J41) -> #REF! | K42: =SUM(K26:K41) -> #REF! | L42: =SUM(L26:L41) -> #REF!
A45: 金额单位：元 | B45: 2017年 | C45: 2018年 | D45: 2019年 | E45: 2020年 | F45: 2021年 | G45: 2022年
A46: 职工人数
A47: 总部
A48: 商务
A49: 贸易
A50: 零售
A51: 物流部
A52: 店铺 | I52: =G52-B52 -> 0
A59: 员工平均工资(单位: 元/人*月)
A60: 总部 | C60: =B60*1.02 -> 0 | D60: =C60*1.02 -> 0 | E60: =D60*1.02 -> 0 | F60: =E60*1.02 -> 0 | G60: =F60*1.02 -> 0
A61: 商务 | C61: =B61*1.02 -> 0 | D61: =C61*1.02 -> 0 | E61: =D61*1.02 -> 0 | F61: =E61*1.02 -> 0 | G61: =F61*1.02 -> 0
A62: 贸易 | C62: =B62*1.02 -> 0 | D62: =C62*1.02 -> 0 | E62: =D62*1.02 -> 0 | F62: =E62*1.02 -> 0 | G62: =F62*1.02 -> 0
A63: 零售 | C63: =B63*1.02 -> 0 | D63: =C63*1.02 -> 0 | E63: =D63*1.02 -> 0 | F63: =E63*1.02 -> 0 | G63: =F63*1.02 -> 0
A64: 物流部 | C64: =B64*1.02 -> 0 | D64: =C64*1.02 -> 0 | E64: =D64*1.02 -> 0 | F64: =E64*1.02 -> 0 | G64: =F64*1.02 -> 0
A65: 店铺 | C65: =B65*1.02 -> 0 | D65: =C65*1.02 -> 0 | E65: =D65*1.02 -> 0 | F65: =E65*1.02 -> 0 | G65: =F65*1.02 -> 0
A71: 工资汇总 | B71: =SUM(B72:B81) -> 0 | C71: =SUM(C72:C81) -> 0 | D71: =SUM(D72:D81) -> 0 | E71: =SUM(E72:E81) -> 0 | F71: =SUM(F72:F81) -> 0 | G71: =SUM(G72:G81) -> 0
A72: 总部 | B72: =ROUND(B60*B47*12/10000,2) -> 0 | C72: =ROUND(C60*C47*12/10000,2) -> 0 | D72: =ROUND(D60*D47*12/10000,2) -> 0 | E72: =ROUND(E60*E47*12/10000,2) -> 0 | F72: =ROUND(F60*F47*12/10000,2) -> 0 | G72: =ROUND(G60*G47*12/10000,2) -> 0
A73: 商务 | B73: =ROUND(B61*B48*12/10000,2) -> 0 | C73: =ROUND(C61*C48*12/10000,2) -> 0 | D73: =ROUND(D61*D48*12/10000,2) -> 0 | E73: =ROUND(E61*E48*12/10000,2) -> 0 | F73: =ROUND(F61*F48*12/10000,2) -> 0 | G73: =ROUND(G61*G48*12/10000,2) -> 0
A74: 贸易 | B74: =ROUND(B62*B49*12/10000,2) -> 0 | C74: =ROUND(C62*C49*12/10000,2) -> 0 | D74: =ROUND(D62*D49*12/10000,2) -> 0 | E74: =ROUND(E62*E49*12/10000,2) -> 0 | F74: =ROUND(F62*F49*12/10000,2) -> 0 | G74: =ROUND(G62*G49*12/10000,2) -> 0
A75: 零售 | B75: =ROUND(B63*B50*12/10000,2) -> 0 | C75: =ROUND(C63*C50*12/10000,2) -> 0 | D75: =ROUND(D63*D50*12/10000,2) -> 0 | E75: =ROUND(E63*E50*12/10000,2) -> 0 | F75: =ROUND(F63*F50*12/10000,2) -> 0 | G75: =ROUND(G63*G50*12/10000,2) -> 0
A76: 物流部 | B76: =ROUND(B64*B51*12/10000,2) -> 0 | C76: =ROUND(C64*C51*12/10000,2) -> 0 | D76: =ROUND(D64*D51*12/10000,2) -> 0 | E76: =ROUND(E64*E51*12/10000,2) -> 0 | F76: =ROUND(F64*F51*12/10000,2) -> 0 | G76: =ROUND(G64*G51*12/10000,2) -> 0
A77: 店铺 | B77: =ROUND(B65*B52*12/10000,2) -> 0 | C77: =ROUND(C65*C52*12/10000,2) -> 0 | D77: =ROUND(D65*D52*12/10000,2) -> 0 | E77: =ROUND(E65*E52*12/10000,2) -> 0 | F77: =ROUND(F65*F52*12/10000,2) -> 0 | G77: =ROUND(G65*G52*12/10000,2) -> 0

Sheet 管理费用预测表
A1: 管理费用预测表
Q2: =[35]封面!A11 -> 评估基准日:2017年12月31日
T3: 人民币万元
P4: 0.04 | Q4: 0.04 | R4: 0.04 | S4: 0.04 | T4: 0.04
C5: 历史费用情况 | O5: 三年平均 | P5: 未来费用预测
A6: 项目 | C6: =[35]未来收入预测表!C6 -> 2013年 | D6: =[35]未来收入预测表!D6 -> 2014年 | E6: 2013年 | G6: 2014年 | I6: =[35]未来收入预测表!E6 -> 2015年 | K6: =[35]未来收入预测表!F6 -> 2016年 | M6: =[35]未来收入预测表!G6 -> 2017年 | P6: =[35]未来收入预测表!H6 -> 2018年 | Q6: =[35]未来收入预测表!I6 -> 2019年 | R6: =[35]未来收入预测表!J6 -> 2020年 | S6: =[35]未来收入预测表!K6 -> 2021年 | T6: =[35]未来收入预测表!L6 -> 2022年
A7: 管理费用 | B7: 工资 | C7: 14748905 | D7: 10224824 | E7: 1474.89 | F7: =E7/'收入--历史经营情况分析'!#REF! -> #REF! | G7: 1022.48 | H7: =G7/'收入--历史经营情况分析'!#REF! -> #REF! | I7: 920.73 | J7: =I7/'收入--历史经营情况分析'!#REF! -> #REF! | K7: 771.42 | L7: =K7/'收入--历史经营情况分析'!#REF! -> #REF! | M7: 857.05 | N7: =M7/'收入--历史经营情况分析'!#REF! -> #REF! | O7: =(J7+L7+N7)/3 -> #REF! | V7: =U7*1.02 -> 0 | W7: =V7*1.02 -> 0 | X7: =W7*1.02 -> 0 | Y7: =X7*1.02 -> 0
B8: 社会保险费 | E8: 607.53 | F8: =E8/'收入--历史经营情况分析'!#REF! -> #REF! | G8: 520.07 | H8: =G8/'收入--历史经营情况分析'!#REF! -> #REF! | I8: 551.4 | J8: =I8/'收入--历史经营情况分析'!#REF! -> #REF! | K8: 550.74 | L8: =K8/'收入--历史经营情况分析'!#REF! -> #REF! | M8: 690.42 | N8: =M8/'收入--历史经营情况分析'!#REF! -> #REF! | O8: =(J8+L8+N8)/3 -> #REF! | V8: =N8*1.02 -> #REF! | W8: =O8*1.02 -> #REF! | X8: =P8*1.02 -> 0 | Y8: =Y9-Y7 -> 0
B9: 租赁费 | E9: 113.94 | F9: =E9/'收入--历史经营情况分析'!#REF! -> #REF! | G9: 89.82 | H9: =G9/'收入--历史经营情况分析'!#REF! -> #REF! | I9: 96.38 | J9: =I9/'收入--历史经营情况分析'!#REF! -> #REF! | K9: 98.69 | L9: =K9/'收入--历史经营情况分析'!#REF! -> #REF! | M9: 52.67 | N9: =M9/'收入--历史经营情况分析'!#REF! -> #REF! | O9: =(J9+L9+N9)/3 -> #REF! | U9: =P7+P8 -> 0 | V9: =Q7+Q8 -> 0 | W9: =R7+R8 -> 0 | X9: =S7+S8 -> 0 | Y9: =T7+T8 -> 0
B10: 折旧费 | E10: 389.33 | F10: =E10/'收入--历史经营情况分析'!#REF! -> #REF! | G10: 355.71 | H10: =G10/'收入--历史经营情况分析'!#REF! -> #REF! | I10: 352.33 | J10: =I10/'收入--历史经营情况分析'!#REF! -> #REF! | K10: 249.66 | L10: =K10/'收入--历史经营情况分析'!#REF! -> #REF! | M10: 215.42 | N10: =M10/'收入--历史经营情况分析'!#REF! -> #REF! | O10: =(J10+L10+N10)/3 -> #REF!
B11: 办公费 | E11: 120.19 | F11: =E11/'收入--历史经营情况分析'!#REF! -> #REF! | G11: 137.97 | H11: =G11/'收入--历史经营情况分析'!#REF! -> #REF! | I11: 159.74 | J11: =I11/'收入--历史经营情况分析'!#REF! -> #REF! | K11: 89.01 | L11: =K11/'收入--历史经营情况分析'!#REF! -> #REF! | M11: 40.28 | N11: =M11/'收入--历史经营情况分析'!#REF! -> #REF! | O11: =(L11+N11)/2 -> #REF!
B12: 税费 | C12: 1201928.8 | D12: 1379692.7 | E12: 139.11 | F12: =E12/'收入--历史经营情况分析'!#REF! -> #REF! | G12: 169.72 | H12: =G12/'收入--历史经营情况分析'!#REF! -> #REF! | I12: 105.68 | J12: =I12/'收入--历史经营情况分析'!#REF! -> #REF! | K12: 71.24 | L12: =K12/'收入--历史经营情况分析'!#REF! -> #REF! | M12: 16.17 | N12: =M12/'收入--历史经营情况分析'!#REF! -> #REF! | O12: =(J12+L12+N12)/3 -> #REF!
B13: 其他 | C13: 1391077 | D13: 1697191.3 | E13: 956.19 | F13: =E13/'收入--历史经营情况分析'!#REF! -> #REF! | G13: 743.39 | H13: =G13/'收入--历史经营情况分析'!#REF! -> #REF! | I13: 430.74 | J13: =I13/'收入--历史经营情况分析'!#REF! -> #REF! | K13: 489.94 | L13: =K13/'收入--历史经营情况分析'!#REF! -> #REF! | M13: 374.94 | N13: =M13/'收入--历史经营情况分析'!#REF! -> #REF! | O13: =(J13+L13+N13)/3 -> #REF!
B14: 合计 | C14: =SUM(C7:C13) -> 17341911 | D14: =SUM(D7:D13) -> 13301708 | E14: =SUM(E7:E13) -> 3801.18 | F14: =SUM(F7:F13) -> #REF! | G14: =SUM(G7:G13) -> 3039.16 | H14: =SUM(H7:H13) -> #REF! | I14: =SUM(I7:I13) -> 2617 | J14: =SUM(J7:J13) -> #REF! | ... L14: =SUM(L7:L13) -> #REF! | M14: =2289.78 -> 2289.78 | N14: =M14/'收入--历史经营情况分析'!#REF! -> #REF! | O14: =(J14+L14+N14)/3 -> #REF!
A16: =[35]封面!A17 -> 被评估单位填表人：
A18: =[35]封面!A15 -> 填表日期：

Sheet 销售费用预测表
A1: 销售费用预测表
O2: =[35]封面!A11 -> 评估基准日:2017年12月31日
P3: 人民币元
C5: 历史费用情况 | M5: 3年平均 | N5: 未来费用预测
A6: 项目 | C6: =[35]未来收入预测表!C6 -> 2013年 | E6: =[35]未来收入预测表!D6 -> 2014年 | G6: =[35]未来收入预测表!E6 -> 2015年 | I6: =[35]未来收入预测表!F6 -> 2016年 | K6: =[35]未来收入预测表!G6 -> 2017年 | N6: =[35]未来收入预测表!H6 -> 2018年 | O6: =[35]未来收入预测表!I6 -> 2019年 | P6: =[35]未来收入预测表!J6 -> 2020年 | Q6: =[35]未来收入预测表!K6 -> 2021年 | R6: =[35]未来收入预测表!L6 -> 2022年
A7: 销售费用 | B7: 工资 | C7: 4197.51 | D7: =C7/'收入--历史经营情况分析'!#REF! -> #REF! | E7: 5296.8829 | F7: =E7/'收入--历史经营情况分析'!#REF! -> #REF! | G7: 4161.72 | H7: =G7/'收入--历史经营情况分析'!#REF! -> #REF! | I7: 4241.4 | J7: =I7/'收入--历史经营情况分析'!#REF! -> #REF! | K7: 5179.95 | L7: =K7/'收入--历史经营情况分析'!#REF! -> #REF!
B8: 租赁费 | C8: 12497.84 | D8: =C8/'收入--历史经营情况分析'!#REF! -> #REF! | E8: 5173.3567 | F8: =E8/'收入--历史经营情况分析'!#REF! -> #REF! | G8: 5369.8 | H8: =G8/'收入--历史经营情况分析'!#REF! -> #REF! | I8: 6859.83 | J8: =I8/'收入--历史经营情况分析'!#REF! -> #REF! | K8: 8323.9 | L8: =K8/'收入--历史经营情况分析'!#REF! -> #REF! | S8: =(O8-N8)/N8 -> #DIV/0! | T8: =(P8-O8)/O8 -> #DIV/0! | U8: =(Q8-P8)/P8 -> #DIV/0! | V8: =(R8-Q8)/Q8 -> #DIV/0!
B9: 物业管理费 | C9: 2638.4 | D9: =C9/'收入--历史经营情况分析'!#REF! -> #REF! | E9: 709.17654 | F9: =E9/'收入--历史经营情况分析'!#REF! -> #REF! | G9: 956.2 | H9: =G9/'收入--历史经营情况分析'!#REF! -> #REF! | I9: 1835.7 | J9: =I9/'收入--历史经营情况分析'!#REF! -> #REF! | K9: 1936.47 | L9: =K9/'收入--历史经营情况分析'!#REF! -> #REF! | M9: =(H9+J9+L9)/3 -> #REF!
B10: 折旧与摊销 | C10: 558.79 | D10: =C10/'收入--历史经营情况分析'!#REF! -> #REF! | E10: 422.03609 | F10: =E10/'收入--历史经营情况分析'!#REF! -> #REF! | G10: 375.65 | H10: =G10/'收入--历史经营情况分析'!#REF! -> #REF! | I10: 343.4 | J10: =I10/'收入--历史经营情况分析'!#REF! -> #REF! | K10: 376.69 | L10: =K10/'收入--历史经营情况分析'!#REF! -> #REF! | M10: =(H10+J10+L10)/3 -> #REF!
B11: 水电费 | C11: 1063.62 | D11: =C11/'收入--历史经营情况分析'!#REF! -> #REF! | E11: 558.25053 | F11: =E11/'收入--历史经营情况分析'!#REF! -> #REF! | G11: 524.83 | H11: =G11/'收入--历史经营情况分析'!#REF! -> #REF! | I11: 496.44 | J11: =I11/'收入--历史经营情况分析'!#REF! -> #REF! | K11: 623.29 | L11: =K11/'收入--历史经营情况分析'!#REF! -> #REF! | M11: =(H11+J11+L11)/3 -> #REF!
B12: 商场费用 | C12: 1153.72 | D12: =C12/'收入--历史经营情况分析'!#REF! -> #REF! | E12: 1066.4156 | F12: =E12/'收入--历史经营情况分析'!#REF! -> #REF! | G12: 1202.34 | H12: =G12/'收入--历史经营情况分析'!#REF! -> #REF! | I12: 996.9 | J12: =I12/'收入--历史经营情况分析'!#REF! -> #REF! | K12: 1114.68 | L12: =K12/'收入--历史经营情况分析'!#REF! -> #REF! | M12: 0.011 | S12: =(N12-K12)/K12 -> -1 | T12: =(O12-N12)/N12 -> #DIV/0! | U12: =(P12-O12)/O12 -> #DIV/0! | V12: =(Q12-P12)/P12 -> #DIV/0! | W12: =(R12-Q12)/Q12 -> #DIV/0!
B13: 运杂费 | C13: 283.65 | D13: =C13/'收入--历史经营情况分析'!#REF! -> #REF! | E13: 215.0101 | F13: =E13/'收入--历史经营情况分析'!#REF! -> #REF! | G13: 283.67 | H13: =G13/'收入--历史经营情况分析'!#REF! -> #REF! | I13: 268.33 | J13: =I13/'收入--历史经营情况分析'!#REF! -> #REF! | K13: 254.41 | L13: =K13/'收入--历史经营情况分析'!#REF! -> #REF! | M13: =(H13+J13+L13)/3 -> #REF! | S13: =(N13-K13)/K13 -> -1 | T13: =(O13-N13)/N13 -> #DIV/0! | U13: =(P13-O13)/O13 -> #DIV/0! | V13: =(Q13-P13)/P13 -> #DIV/0! | W13: =(R13-Q13)/Q13 -> #DIV/0!
B14: 包装费 | C14: 124.73 | D14: =C14/'收入--历史经营情况分析'!#REF! -> #REF! | E14: 105.86382 | F14: =E14/'收入--历史经营情况分析'!#REF! -> #REF! | G14: 107.64 | H14: =G14/'收入--历史经营情况分析'!#REF! -> #REF! | I14: 104.48 | J14: =I14/'收入--历史经营情况分析'!#REF! -> #REF! | K14: 110.91 | L14: =K14/'收入--历史经营情况分析'!#REF! -> #REF! | M14: =(H14+J14+L14)/3 -> #REF! | S14: =(N14-K14)/K14 -> -1 | T14: =(O14-N14)/N14 -> #DIV/0! | U14: =(P14-O14)/O14 -> #DIV/0! | V14: =(Q14-P14)/P14 -> #DIV/0! | W14: =(R14-Q14)/Q14 -> #DIV/0!
B15: 修理费 | C15: 165.18 | D15: =C15/'收入--历史经营情况分析'!#REF! -> #REF! | E15: 138.79471 | F15: =E15/'收入--历史经营情况分析'!#REF! -> #REF! | G15: 121.99 | H15: =G15/'收入--历史经营情况分析'!#REF! -> #REF! | I15: 169.2 | J15: =I15/'收入--历史经营情况分析'!#REF! -> #REF! | K15: 167.68 | L15: =K15/'收入--历史经营情况分析'!#REF! -> #REF! | M15: =(H15+J15+L15)/3 -> #REF! | S15: =(N15-K15)/K15 -> -1 | T15: =(O15-N15)/N15 -> #DIV/0! | U15: =(P15-O15)/O15 -> #DIV/0! | V15: =(Q15-P15)/P15 -> #DIV/0! | W15: =(R15-Q15)/Q15 -> #DIV/0!
B16: 差旅费 | C16: 156.39 | D16: =C16/'收入--历史经营情况分析'!#REF! -> #REF! | E16: 109.70452 | F16: =E16/'收入--历史经营情况分析'!#REF! -> #REF! | G16: 126.49 | H16: =G16/'收入--历史经营情况分析'!#REF! -> #REF! | I16: 161.55 | J16: =I16/'收入--历史经营情况分析'!#REF! -> #REF! | K16: 118.79 | L16: =K16/'收入--历史经营情况分析'!#REF! -> #REF! | M16: =(H16+J16+L16)/3 -> #REF! | S16: =(N16-K16)/K16 -> -1 | T16: =(O16-N16)/N16 -> #DIV/0! | U16: =(P16-O16)/O16 -> #DIV/0! | V16: =(Q16-P16)/P16 -> #DIV/0! | W16: =(R16-Q16)/Q16 -> #DIV/0!
B17: 其他 | C17: 1937.8536 | D17: =C17/'收入--历史经营情况分析'!#REF! -> #REF! | E17: 558.73832 | F17: =E17/'收入--历史经营情况分析'!#REF! -> #REF! | G17: =536.48+207.86 -> 744.34 | H17: =G17/'收入--历史经营情况分析'!#REF! -> #REF! | I17: =440.29+56.1 -> 496.39 | J17: =I17/'收入--历史经营情况分析'!#REF! -> #REF! | K17: =346.85+2.73 -> 349.58 | L17: =K17/'收入--历史经营情况分析'!#REF! -> #REF! | M17: =(H17+J17+L17)/3 -> #REF! | S17: =(N17-K17)/K17 -> -1 | T17: =(O17-N17)/N17 -> #DIV/0! | U17: =(P17-O17)/O17 -> #DIV/0! | V17: =(Q17-P17)/P17 -> #DIV/0! | W17: =(R17-Q17)/Q17 -> #DIV/0!
B18: 合计 | C18: =SUM(C7:C17) -> 24777.684 | E18: =SUM(E7:E17) -> 14354.23 | G18: 13766.8 | H18: =G18/'收入--历史经营情况分析'!#REF! -> #REF! | I18: 15917.53 | J18: =I18/'收入--历史经营情况分析'!#REF! -> #REF! | K18: 18561.55 | L18: =K18/'收入--历史经营情况分析'!#REF! -> #REF! | M18: =(H18+J18+L18)/3 -> #REF! | N18: =SUM(N7:N16) -> 0 | O18: =SUM(O7:O16) -> 0 | P18: =SUM(P7:P16) -> 0 | Q18: =SUM(Q7:Q16) -> 0 | R18: =SUM(R7:R16) -> 0

Sheet 租赁费预测
A1: 店铺序号 | B1: 公司 | C1: 单位 | D1: 地区 | E1: 店铺性质 | F1: 店铺业态 | G1: 店铺名称 | H1: 金蝶系统名称 | I1: 承租方 | J1: 出租方 | K1: 地址 | L1: 面积（m2) | M1: 合同期限/年租金 | N1: 租金单价㎡/日 | O1: 2018年租金测算 | P1: 2019年 | Q1: 2020年 | R1: 2021年 | S1: 2022年 | T1: 租金上涨率 | U1: 物业管理费 | V1: 物业费测算 | W1: 关店时间
A2: 1 | B2: 湖北杰之行 | C2: 零售 | D2: 武汉 | E2: 直营 | F2: 地铺店 | G2: 江北红房子耐克、匡威 | H2: 江北红房子 | I2: 湖北杰之行 | J2: 武汉市凡荣服饰有限公司 | K2: 武汉市江岸区江汉路14号 | L2: 180 | M2: 2013.08.01-2019.07.31（2300000元/年） | N2: =O2/180/365 -> 35.00761 | O2: 2300000 | T2: 不涨
A3: 2 | B3: 湖北杰之行 | C3: 零售 | D3: 武汉 | E3: 直营 | F3: 运动城 | G3: 江南光谷集合店 | H3: 江南光谷集合店 | I3: 湖北杰之行 | J3: 湖北胜道体育用品有限公司 | K3: 武汉东湖开发区光谷街3号世界城光谷步行街 | L3: 1784.57 | M3: 2015.01.01-2024.12.31(租金:100万元/年) | N3: =O3/L3/365 -> 1.5352304 | O3: 1000000 | T3: 不涨
B4: 湖北杰之行 | C4: 零售 | D4: 武汉 | E4: 直营 | F4: 运动城 | G4: 江南光谷集合店 | H4: 江南光谷集合店 | I4: 湖北杰之行 | J4: 湖北胜道体育用品有限公司 | K4: 武汉东湖开发区光谷街3号世界城光谷步行街 | L4: 2466.43 | M4: 2017.09.10-2021.01.09（固定租金900万/年；抽成租金保底营业额833.33万*5%*12/年)（2017.09.10-2018.01.09免租） | N4: =O4/L4/365 -> 15.551288 | O4: =(9000000+8333333*0.05*12) -> 14000000 | T4: 不涨 | U4: 2017.09.10-2021.01.09（物业管理费100万/年）（2017.09.10-2018.01.09免租） | V4: 10000000
A5: 3 | B5: 湖北杰之行 | C5: 零售 | D5: 武汉 | E5: 直营 | F5: 地铺店 | G5: 江南光谷世界城万斯 | H5: 江南光谷世界城万斯 | I5: 湖北杰之行 | J5: 武汉市世界城广场商业管理有限公司 | K5: 武汉市东湖新技术开发区珞瑜路世界城广场3035# | L5: 71.22 | M5: 2013.09.28-2015.09.27（租金：213660元/年） 2015.09.28-2016.09.27（租金：230748元/年） 2016.09.28-2017.09.27（租金：230748元/年） 2017.09.28-2018.09.27（租金：230748元/年） | N5: =O5/L5/365 -> 8.8765277 | O5: 230748 | T5: =(230748-213660)/213660/3 -> 0.026659178 | U5: 2013.09.28-2015.09.27（物业管理费：42732元/年） 2015.09.28-2016.09.27（物业管理费：42732元/年） 2016.09.28-2017.09.27（物业管理费：51278元/年） 2017.09.28-2018.09.27（物业管理费：51278元/年） | V5: 51278
A6: 4 | B6: 湖北杰之行 | C6: 零售 | D6: 武汉 | E6: 直营 | F6: 集合店 | G6: 武汉宜家集合店 | H6: 江北宜家集合店 | I6: 湖北杰之行 | J6: 武汉英特宜家置业有限公司 | K6: 武汉市桥口区长宜路1号购物中心L12层4-12-23-SU和4-12-24-SU号的物业 | L6: 425 | M6: 2015.01.12-2016.01.11(提成租金:为13%,基本租金:无;两者取其高) 2016.01.12-2017.01.11(基本租金:121.67元/平米/月,提成租金:14%,两者取其高) 2017.01.12-2018.01.11(基本租金:182.5元/平米/月,提成租金:15%,两者取其高) 免租期:首二个月的免租期,不付租金,但需付物业管理费\推广费\公共事业费等 | N6: 182.5 | O6: =L6*N6*12 -> 930750 | T6: =(182.5-121.67)/121.67 -> 0.49995891 | U6: 2015.01.12-2016.01.11物业费:70元/平米/月,推广费;12元/平米/月 2016.01.12-2017.01.11物业费:70元/平米/月,推广费:12.6元/平米/月 2017.01.12-2018.01.11物业费:70元/平米/月,推广费:13.23元/平米/月 | V6: =(70+13.23)*12*L6 -> 424473
A7: 5 | B7: 湖北杰之行 | C7: 零售 | D7: 武汉 | E7: 直营 | F7: 地铺店 | G7: 武汉宜家安德玛 | H7: 江北宜家安德玛 | I7: 湖北杰之行 | J7: 武汉英特宜家置业有限公司 | K7: 武汉市桥口区长宜路1号购物中心L11层4-11-26-SU单元号 | L7: 197 | M7: 2015.03.23-2016.03.22(基本租金:无 提成租金:比例为12%,) 2016.03.23-2017.03.22(基本租金:106.46元/平米/月,提成租金:13%,) 2017.03.23-2018.03.22(基本租金:182.5元/平米/月,提成比例:14%,) 免租期:指开业日起的首三个月 | U7: 2015.03.23-2016.03.22(物业费:70元/平米/月,推广费;12元/平米/月) 2016.03.23-2017.03.22(物业费:70元/平米/月,推广费:12.6元/平米/月) 2017.03.23-2018.03.22(物业费:70元/平米/月,推广费:13.23元/平米/月) | W7: 2017.06.15
A8: 6 | B8: 湖北杰之行 | C8: 零售 | D8: 武汉 | E8: 直营 | F8: 集合店 | G8: 中百唐家墩集合店 | H8: 武汉唐家墩集合店 | I8: 湖北杰之行 | J8: 中百仓储超市有限公司 | K8: 湖北省武汉市中百仓储购物广场唐家墩店二层 | L8: 270 | M8: 2015.05.01-2016.12.31(租金:31700元/月, 2017.01.01-2017.12.31(租金:34236元/月) 2018.01.01-2018.12.31(租金:36975元/月) 2019.01.01-2019.12.31(租金:39933元/月) | W8: 42826
A9: 7 | B9: 湖北杰之行 | C9: 零售 | D9: 武汉 | E9: 直营 | F9: 地铺店 | G9: 江南光谷世界城阿迪SH | H9: 江南光谷世界城阿迪SH | I9: 湖北杰之行 | J9: 武汉市世界城广场商业管理有限公司 | K9: 武汉市东湖新技术开发区珞瑜路世界城广场(149号) | L9: 150 | M9: 2014.12.20-2015.12.19(租金:684000元/年) 2015.12.20-2016.12.19(租金:752400元/年) 2016.12.20-2017.12.19(租金:828000元/年) | U9: 物业管理费:按3个月为一期结算,50元/月/平方米 营销推广费用:10元/月/平方米, | W9: 合同到期
B10: 湖北杰之行 | C10: 零售 | D10: 武汉 | E10: 直营 | F10: 地铺店 | G10: 江南光谷世界城阿迪SH | H10: 江南光谷世界城阿迪SH | I10: 湖北杰之行 | J10: 武汉市世界城广场商业管理有限公司 | K10: 武汉市东湖新技术开发区珞瑜路世界城广场(149号) | L10: 150 | M10: 2017.12.20-2018.03.31（租金：69000元/月） | N10: =O10/L10/365 -> 15.123288 | O10: =69000*12 -> 828000 | T10: =(828000-752400)/752400 -> 0.10047847 | U10: 物业管理费:,50元/月/平方米营销推广费用:10元/月/平方米,，按3个月为一期结算 | V10: =60*L10*12 -> 108000
A11: 8 | B11: 湖北杰之行 | C11: 零售 | D11: 武汉 | E11: 直营 | F11: 运动城 | G11: 江北菱角湖万达集合店 | H11: 江北菱角湖万达集合店 | I11: 湖北杰之行 | J11: 武汉万达广场投资有限公司 | K11: 武汉市江汉区新华下路63号菱角湖万达购物中心 | L11: 1605.88 | M11: 2015.08.01-2015.09.17（租金：232370.84元/月） 2015.09.17-2016.09.16（租金：2927968.89元/年） | U11: 2015.08.01-2015.09.17（物业：297922.8元/年） 2015.08.01-2015.09.17（物业：301006.15元/年） | W11: 合同到期
B12: 湖北杰之行 | C12: 零售 | D12: 武汉 | E12: 直营 | F12: 运动城 | G12: 江北菱角湖万达集合店 | H12: 江北菱角湖万达集合店 | I12: 湖北杰之行 | J12: 武汉万达广场投资有限公司 | K12: 武汉市江汉区新华下路63号菱角湖万达购物中心 | L12: 1605.88 | M12: 2016.12.18-2017.12.17(租金：3468700.80元/年） 2017.12.18-2018.12.17(租金：3468700.80元/年） 2018.12.18-2019.12.17(租金：3607448.88元/年） 2019.12.18-2020.12.17(租金：3751785.36元/年） 2020.12.18-2021.12.17(租金：3901902.96元/年） 2021.12.18-2022.12.17(租金：4057994.52元/年） | N12: =O12/L12/365 -> 5.9178082 | O12: 3468700.8 | T12: =(3607448.88-3468700.8)/3468700.8 -> 0.040000014 | U12: 2016.12.18-2017.12.17(物业：16元/平米） 2017.12.18-2018.12.17(物业：16元/平米） 2018.12.18-2019.12.17(物业：16.24元/平米） 2019.12.18-2020.12.17(物业：16.49元/平米） 2020.12.18-2021.12.17(物业：16.75元/平米） 2021.12.18-2022.12.17(物业：17.02元/平米） | V12: =16*L12*12 -> 308328.96
A13: 9 | B13: 湖北杰之行 | C13: 零售 | D13: 武汉 | E13: 直营 | F13: 运动城 | G13: 江北经开万达运动城 | H13: 江北经开万达集合店 | I13: 湖北杰之行 | J13: 武汉经开万达广场投资有限公司 | K13: 武汉市经开万达广场综合楼1F-A铺位, | L13: 2848.15 | M13: 2011.8.26-2012.8.25(租金:110元/月/平米) 2012.8.26-2013.8.25(租金:110元/月/平米) 2013.8.26-2014.8.25(租金:113.3元/月/平米) 2014.8.26-2015.8.25(租金:116.7元/月/平米) 2015.8.26-2016.8.25(租金:120.2元/月/平米) 2016.8.26-2017.8.25(租金:123.81元/月/平米) | U13: 2011.8.26-2012.8.25(物业费:6元/月/平米) 2012.8.26-2013.8.25(物业费:6元/月/平米) 2013.8.26-2014.8.25(物业费:6.24元/月/平米) 2014.8.26-2015.8.25(物业费:6.49元/月/平米) 2015.8.26-2016.8.25(物业费:6.75元/月/平米) 2016.8.26-2017.8.25(物业费:7.02元/月/平米) 2011.8.26-2017.8.25(空调费:10元/月/平米) | W13: 合同到期
B14: 湖北杰之行 | C14: 零售 | D14: 武汉 | E14: 直营 | F14: 运动城 | G14: 江北经开万达运动城 | H14: 江北经开万达集合店 | I14: 湖北杰之行 | J14: 武汉经开万达广场投资有限公司 | K14: 武汉市经开万达广场综合楼1F-A铺位, | L14: 2601 | M14: 2017.8.26-2019.8.25(租金:123.81元/月/平米) 2019.8.26-2020.8.25(租金:127.52元/月/平米) 2020.8.26-2021.8.25(租金:131.35元/月/平米) 2021.8.26-2022.8.25(租金:135.29元/月/平米) 2022.8.26-2023.8.25(租金:139.35元/月/平米) | N14: =O14/L14/365 -> 4.0704658 | O14: =123.81*L14*12 -> 3864357.7 | T14: =(127.52-123.81)/123.81 -> 0.029965269 | U14: 2017.8.26-2019.8.25(物业:17.02元/月/平米) 2019.8.26-2020.8.25(物业:17.30元/月/平米) 2020.8.26-2021.8.25(物业:17.59元/月/平米) 2021.8.26-2022.8.25(物业:17.89元/月/平米) 2022.8.26-2023.8.25(物业:18.21元/月/平米) | V14: =17.02*L14*12 -> 531228.24
A15: 10 | B15: 湖北杰之行 | D15: 武汉 | E15: 直营 | F15: 运动城 | G15: 江北经开跑步店 | H15: 江北经开万达集合店 | I15: 湖北杰之行 | J15: 湖北万达广场商业管理有限公司经济开发区分公司 | K15: 经开万达0008点位一 | L15: 30 | O15: 租金？ | U15: 2017.8.15-2018.8.15（物业：8800元/月）
A16: 11 | B16: 湖北杰之行 | C16: 零售 | D16: 武汉 | E16: 直营 | F16: 地铺店 | G16: 江南体院集合店 | H16: 江南体院集合店 | I16: 湖北杰之行 | J16: 湖北胜道体育用品有限公司 | K16: 武汉市洪山区珞南街珞瑜路476号 | L16: 1057 | M16: 2015.05.01-2018.04.30(租金:30万元/年) | N16: =O16/L16/365 -> 0.7775949 | O16: 300000 | T16: 不涨
A17: 12 | B17: 湖北杰之行 | C17: 零售 | D17: 武汉 | E17: 直营 | F17: 运动城 | G17: 江南麦当劳运动城 | H17: 江南麦当劳运动城 | I17: 湖北杰之行 | J17: 湖北胜道体育用品有限公司 | K17: 武汉市武昌区解放路338号(原340号)2栋杰之行运动城 | L17: 1126.65 | M17: 2015.08.01-2020.12.31(租金:100万元/年) | N17: =O17/L17/365 -> 2.4317455 | O17: 1000000 | T17: 不涨
A18: 13 | B18: 武汉杰锐 | C18: 零售 | D18: 武汉 | E18: 直营 | F18: 运动城 | G18: 江南光谷天地运动城 | H18: 江南光谷天地集合店 | I18: 武汉杰锐 | J18: 湖北长城建设实业有限公司 | K18: 武汉市东湖高新技术开发区关山大道591号光谷天地 | L18: 1800 | M18: 2011.07.01-2012.06.30（1944000元/年） 2012.07.01-2013.06.30（2052000元/年） 2013.07.01-2014.06.30（2160000元/年） 2014.07.01-2015.06.30（2268000元/年） 2015.07.01-2016.06.30（2376000元/年） | W18: 2016.07.05
A19: 14 | B19: 湖北杰之行 | C19: 零售 | D19: 武汉 | E19: 直营 | F19: 地铺店 | G19: 武汉凯德广场1818集合店 | H19: 江南凯德广场1818集合店 | I19: 湖北杰之行 | J19: 武汉凯辉中北商用置业有限公司 | K19: 凯德广场.1818,武汉"04层16*19号" | L19: 410.04 | M19: 2015.09.17-2017.09.16(月保底租金32803.2元/月) (提成租金月营业额的10%) 2017.09.17-2018.09.16(月保底租金36903.6元/月) (提成租金月营业额的11%) 2018.09.17-2019.09.16(月保底租金41004元/月) (提成租金月营业额的12%) 2019.09.17-2020.09.16(月保底租金45104.4元/月) (提成租金月营业额的13%) | N19: =O19/L19/365 -> 2.9589041 | O19: =36903.6*12 -> 442843.2 | T19: =(41004-36903.6)/36903.6 -> 0.11111111 | U19: 2015.09.17-2017.09.16(物业管理费24602.4元/月) 2017.09.17-2018.09.16 (物业管理费24602.4元/月) 2018.09.17-2019.09.16 (物业管理费24602.4元/月) 2019.09.17-2020.09.16 (物业管理费24602.4元/月) | V19: =24602.4*12 -> 295228.8 | W19: 原合同终止
B20: 湖北杰之行 | C20: 零售 | D20: 武汉 | E20: 直营 | F20: 地铺店 | G20: 武汉凯德广场1818集合店 | H20: 江南凯德广场1818集合店 | I20: 湖北杰之行 | J20: 武汉凯辉中北商用置业有限公司 | K20: 凯德广场.1818,武汉"04层16*19号" | L20: 260.87 | M20: 2016.12.10-2017.09.16（月保底租金19930.47元） 2017.09.17-2018.09.16（月保底租金22539.17元） 2018.09.17-2019.09.16（月保底租金25147.87元） 2019.09.17-2020.09.16（月保底租金27756.57元） | N20: =O20/L20/365 -> 61.751151 | O20: =22539.17*L20 -> 5879793.3 | T20: =(25147.87-22539.17)/22539.17 -> 0.11574073 | U20: 2016.12.10-2020.09.16（物业管理费16591.33元/月） | V20: 16591.33
A21: 15 | B21: 湖北杰之行 | C21: 零售 | D21: 武汉 | E21: 直营 | F21: 地铺店 | G21: 武汉摩尔城集合店 | H21: 江北王家湾摩尔城集合店 | I21: 湖北杰之行 | J21: 湖北恒信德龙实业有限公司武汉摩尔在管理分公司 | K21: 武汉市汉阳区龙阳大道特6号武汉摩尔城二层22-008号商铺(A区) | L21: 1080 | M21: 2015.10.01-2017.09.30(租金:61200元/月) 2017.10.01-2019.09.30(租金:72720元/月) 2019.10.01-2020.09.30(租金:85680元/月)或月营业额的15% | U21: 物业管理费:54000元/月,店庆费:5000元/年,年度促销费:10000元/年, | W21: 42916
A22: 16 | B22: 湖北杰之行 | C22: 零售 | D22: 黄石 | E22: 直营 | F22: 地铺店 | G22: 黄石新百集合店 | H22: 黄石新百集合店 | I22: 湖北杰之行 | J22: 大金新百百货股份有限公司黄石分公司 | K22: 湖北省黄石市黄石大道678号大金百货黄石新百商场一楼 | L22: 880 | M22: 2015.09.30-2020.06.30(租金:1056000元/年) 营业管理费:3000元/年;店庆费:5000元;刷卡金额1%外卡手续费,刷卡金额2.5%内卡手续费, 第4年起租金递增8% | U22: 销售年超过1000万元/年加提3%作为物业管理费 | W22: 2016.5.31
A23: 17 | B23: 湖北杰之行 | C23: 零售 | D23: 武汉 | E23: 直营 | F23: 集合店 | G23: 武汉壹方集合店 | H23: 江北武汉天地集合店 | I23: 湖北杰之行 | J23: 武汉瑞安天地房地产发展有限公司 | K23: 武汉市江岸区中山大道1515号壹方购物中心3层商1A\1B\44室 | L23: 920.66 | M23: 2016.09.17-2017.09.16(保底租金:0元/年) 2017.09.17-2018.09.16(保底租金:为第一年平均提成租金的80%) 2018.09.17-2019.09.16(保底租金:为第二年平均提成租金的80%) 2019.09.17-2020.09.16(保底租金:为第三年平均提成租金的80%) 2020.09.17-2021.09.16(保底租金:为第四年平均提成租金的80%) 2021.09.17-2022.09.16(保底租金:为第五年平均提成租金的80%) 2016.09.17-2019.09.16(抽成租金:销售额的9%) 2019.09.17-2022.09.16(抽成租金:销售额的10%) 两者取其高者 | O23: 营业额？ | U23: 推广费:10元/月/平米,物业管理费:30元/月/平米 | V23: =40*12*L23 -> 441916.8
A24: 18 | B24: 湖北杰之行 | C24: 零售 | D24: 武汉 | E24: 直营 | F24: 地铺店 | G24: 武汉壹方万斯店 | H24: 江北武汉天地万斯 | I24: 湖北杰之行 | J24: 武汉瑞安天地房地产发展有限公司 | K24: 武汉市江岸区中山大道1515号壹方购物中心3层商38室 | L24: 119.63 | M24: 2016.09.17-2017.09.16(租金:6.58元/天/平米或当月营业额16%提取,两者取其高者) 2017.09.17-2018.09.16(租金:7.23元/天/平米或当月营业额16%提取,两者取其高者) 2018.09.17-2019.09.30(租金:7.96元/天/平米或当月营业额17%提取,两者取其高者) | N24: =O24/L24/365 -> 7.3309589 | O24: =7.23*L24*260+7.96*L24*100 -> 320105.95 | T24: =(7.96-7.23)/7.23 -> 0.10096819 | U24: 推广费:10元/月/平米,物业管理费:55元/月/平米 | V24: =65*L24*12 -> 93311.4
A25: 19 | B25: 湖北杰之行 | C25: 零售 | D25: 武汉 | E25: 直营 | F25: 地铺店 | G25: 武汉壹方阿迪生活店 | H25: 江北武汉天地阿迪NEO | I25: 湖北杰之行 | J25: 武汉瑞安天地房地产发展有限公司 | K25: 武汉市江岸区中山大道1515号壹方购物中心3层商41室 | L25: 122.05 | M25: 2017.11.1-2018.09.30(租金:10.85元/天/平米) 2018.10.1-2019.09.30(租金:11.93元/天/平米) 2019.10.1-2020.09.30(租金:13.12元/天/平米) 租金=租金*（1+5%） 2017.4.28-2018.4.27（当月营业额16%提取） 2018.4.28-2019.4.27（当月营业额17%提取） 2019.4.28-2020.4.27（当月营业额18%提取） 两者取其高者 | N25: =O25/L25/365 -> 10.952877 | O25: =10.85*L25*275+11.93*L25*85 -> 487931.49 | T25: =(13.12-11.93)/11.93 -> 0.099748533 | U25: 物业管理费：63.6元/月/平米，18451.63元/月 | V25: =18451.63*12 -> 221419.56
A26: 20 | B26: 湖北杰之行 | C26: 零售 | D26: 黄石 | E26: 直营 | F26: 地铺店 | G26: 黄石万达广场耐克360店 | H26: 黄石万达耐克360 | I26: 湖北杰之行 | J26: 黄石万达广场投资有限公司 | K26: 黄石市黄石万达广场购物中心室内步行街一层1015号商铺 | L26: 91 | M26: 2016.02.25-2018.02.24(租金:25480元/月) 2018.02.25-2018.04.02(租金:27263.60元/月) | N26: =O26/L26/365 -> 9.849863 | O26: =27263.6*12 -> 327163.2 | T26: =(27263.6-25480)/25480 -> 0.07 | U26: 2016.02.25-2018.02.24(物业管理费:5005元/月) | V26: =5005*12 -> 60060
A27: 21 | B27: 湖北杰之行 | C27: 零售 | D27: 武汉 | E27: 直营 | F27: 集合店 | G27: 同学广场集合店 | H27: 同学广场集合店 | I27: 湖北杰之行 | J27: 武汉圣淘沙实业有限公司 | K27: 武汉市洪山区民族大道219号“同学广场”1层及2层1F-056/2F-050 | L27: 1545 | M27: 201612.31-2017.12.30（租金：97980元/月） 2017.12.31-2018.12.30（租金：117150元/月） 2018.12.31-2019.12.30（租金：127800元/月） 2019.12.31-2022.12.30（租金：141666.67） 2022.12.31-2026.12.30（租金：155000元/月） 抽成租金：年销售1200万，超出部分按照15%收取抽成租金） | N27: =O27/L27/365 -> 0.99715388 | O27: =117150*12*0.4 -> 562320 | T27: =(127800-117150)/117150 -> 0.090909091 | U27: 月度租赁费中：60%为物业管理费 40%为店铺租金 | V27: =O27/0.4*0.6 -> 843480 | W27: 未开
A28: 22 | B28: 湖北杰之行 | C28: 零售 | D28: 武汉 | E28: 直营 | F28: 地铺店 | G28: 古田凯德 | H28: 江北古田凯德 | I28: 湖北杰之行 | J28: 武汉凯德古田商业职业有限公司 | K28: 武汉市硚口区解放大道18号1层06/07号 | L28: 290.12 | M28: 第一年固定租金:236.40元/月/平米，抽成租金:月营业额的16%， 第二年固定租金:260.40元/月/平米，抽成租金:月营业额的17% 第三年固定租金:286.40元/月/平米，抽成租金:月营业额的18% | N28: =O28/L28/365 -> 7.7720548 | O28: =236.4*290.12*12 -> 823012.42 | T28: =(286.4-260.4)/260.4 -> 0.09984639 | U28: 63.6元/月/平米 | V28: =63.6*L28 -> 18451.632
A29: 23 | B29: 湖北杰之行 | C29: 零售 | D29: 武汉 | E29: 直营 | F29: 地铺店 | G29: 江南光谷世界城集合店 | H29: 江南光谷世界城集合店 | I29: 湖北杰之行 | J29: 武汉市世界城广场商业管理有限公司 | K29: 武汉市东湖新技术开发区珞瑜路世界城广场341-343# | L29: 212.7 | M29: 2014.10.01-2015.09.30 租金：765720/年 物业及推广：153144/年 2015.10.01-2016.09.30 租金：826980/年 物业及推广：153144/年 2016.10.01-2017.09.30 租金：908652/年 物业及推广：153144/年 | W29: 关店
A30: 24 | B30: 湖北杰之行 | C30: 零售 | D30: 孝感 | E30: 直营 | F30: 地铺店 | G30: 孝感城站路李宁 | H30: 孝感城站路李宁 | I30: 湖北杰之行 | J30: 孝感市勤奋服务中心 | K30: 孝感市城站路26号（孝感市城站路小天桥南门面两间及二楼） | L30: 120 | M30: 2015.05.01-2016.02.14(租金:9.8万元/年) 2016.02.15-2019.02.14(租金:9.8万元/年) | W30: 合同到期
B31: 湖北杰之行 | C31: 零售 | D31: 孝感 | E31: 直营 | F31: 地铺店 | G31: 孝感城站路李宁 | H31: 孝感城站路李宁 | I31: 湖北杰之行 | J31: 湖北孝城控股集团安华资产管理有限公司 | K31: 孝感市城站路26号（孝感市城站路小天桥南门面两间及二楼） | L31: 120 | M31: 2017.9.18-2019.2.14(租金:9.8万元/年) | N31: =O31/L31/365 -> 2.2374429 | O31: 98000 | T31: 不涨
A32: 25 | B32: 湖北杰之行 | C32: 零售 | D32: 孝感 | E32: 直营 | F32: 运动城 | G32: 孝感新概念运动城 | H32: 孝感新概念集合店 | I32: 湖北杰之行 | J32: 孝感市文昌中学 | K32: 孝感市文化路166号（孝感市文昌中学文化路街面门面） | L32: 622.6 | M32: 2015.05.01-2023.08.17（1400000元/年） 分三次提前支付600万，每季度支付20万房租 | N32: =O32/L32/365 -> 6.1606432 | O32: 1400000 | T32: 不涨
A33: 26 | B33: 湖北杰之行 | C33: 零售 | D33: 孝感 | E33: 直营 | F33: 地铺店 | G33: 孝感文化广场运动城 | H33: 孝感文化广场阿迪 | I33: 湖北杰之行 | J33: 杨少平,李萍 | K33: 孝感市文化路2号宇济文化广场的商用房102#\202#\302#\103#\203#\303# | L33: 4137 | M33: 2015.05.01-2017.12.30(租金:50万元/年)合同签订时,租金已支付到2015.09.30,2015.09.01前支付2015.10.01-2016.09.30的房租50万元,2016.09.01前支付2016.10.01-2017.12.30的房租62.5万元, | T33: 是否续租？续租租金
A34: 27 | B34: 湖北杰之行 | C34: 零售 | D34: 孝感 | E34: 直营 | F34: 运动城 | G34: 孝感宇济文化广场 | H34: 孝感宇济文化广场运动城 | I34: 湖北杰之行 | J34: 严雄武 | K34: 孝感文化路2号宇济广场一楼104.105号房屋 | L34: 910 | M34: 2017.10.1-2020.9.30（2000000元/年）三年一次性付清 | N34: =O34/L34/365 -> 6.0213759 | O34: 2000000 | T34: 不涨
A35: 28 | B35: 湖北杰之行 | C35: 零售 | D35: 荆州 | E35: 直营 | F35: 地铺店 | G35: 荆州旗舰李宁 | H35: 荆州旗舰李宁 | I35: 湖北杰之行 | J35: 陈刚 | K35: 沙市区北京路沙市饭店235-1号北面临街门店1-2楼 | L35: 100 | M35: 2015.07.01-2019.12.31(租金:65万元/年) | N35: =O35/L35/365 -> 17.808219 | O35: 650000 | T35: 不涨
A36: 29 | B36: 湖北杰之行 | C36: 零售 | D36: 荆州 | E36: 直营 | F36: 地铺店 | G36: 荆州广源大厦耐克360 | H36: 荆州广源耐克 | I36: 湖北杰之行 | J36: 王东林 | K36: 荆州市广源商城物业共二层，（一层177平方米，二层380平方米） | L36: 557 | M36: 2015.05.01-2019.08.14(租金:50万元/年) | N36: =O36/L36/365 -> 2.4593591 | O36: 500000 | T36: 不涨
B37: 湖北杰之行 | C37: 零售 | D37: 荆州 | E37: 直营 | F37: 地铺店 | G37: 荆州广源大厦耐克360 | H37: 荆州广源耐克 | I37: 张勇 | J37: 王东林 | K37: 荆州市广源商城物业共二层，（一层177平方米，二层380平方米） | L37: 557 | M37: 2015.05.01-2019.08.14(租金:90万元/年) | N37: =O37/L37/365 -> 4.4268464 | O37: 900000
B38: 湖北杰之行 | C38: 零售 | D38: 荆州 | E38: 直营 | F38: 地铺店 | G38: 荆州广源大厦李宁 | H38: 荆州广源大厦李宁 | I38: 湖北杰之行 | J38: 荆州市杰之行 | K38: 荆州市沙市区北京中路广源大厦一楼 | L38: 518 | M38: 2015.07.01-2016.12.31(租金:100万元/年) 2017.01.01-2017.12.31(租金:150万元/年) | N38: =O38/L38/365 -> 5.2890464 | O38: 1000000 | T38: 是否续租
A39: 30 | B39: 湖北杰之行 | C39: 零售 | D39: 荆州 | E39: 直营 | F39: 地铺店 | G39: 荆州金石耐克店 | H39: 荆州金石耐克鞋店 | I39: 湖北杰之行 | J39: 金毅 | K39: 沙市北京中路219号店堂(金石商场西边第一间) | L39: 57 | M39: 2015.08.16-2016.08.15(租金:15万元/年) 2016.08.16-2019.08.15(租金:15万元/年) | N39: =O39/L39/365 -> 7.2098053 | O39: 150000 | T39: 不涨
A40: 31 | B40: 湖北杰之行 | C40: 零售 | D40: 荆州 | E40: 直营 | F40: 地铺店 | G40: 荆州小南洋耐克、阿迪 | H40: 荆州小南洋耐克店 | I40: 万四平 | J40: 陈源信 | K40: 沙市北京路207号一、二楼 | L40: 1065.73 | M40: 2015.07.19-2016.03.18(租金:666667元,本期间房租已支付) 2016.03.19-2019.03.18(租金:110万元/年) | N40: =O40/L40/365 -> 2.8278257 | O40: 1100000 | T40: =(1100000-666667)/666667/4 -> 0.16249979
B41: 湖北杰之行 | C41: 零售 | D41: 荆州 | E41: 直营 | F41: 地铺店 | G41: 荆州小南洋耐克、阿迪 | H41: 荆州小南洋耐克店 | I41: 湖北杰之行 | J41: 陈源信 | K41: 沙市北京路207号一、二楼 | L41: 1065.73 | M41: 2015.07.19-2016.03.18(租金:1466667元,本期间房租已支付) 2016.03.19-2019.03.18(租金:242万元/年) | N41: =O41/L41/365 -> 6.2212164 | O41: 2420000 | T41: =(2420000-1466667)/1466667/4 -> 0.16249991
A42: 32 | B42: 湖北杰之行 | C42: 零售 | D42: 荆州 | E42: 直营 | F42: 地铺店 | G42: 荆州北京路地下商城综合折扣店 | H42: 荆州地下商城集合店 | I42: 湖北杰之行 | J42: 万四平 | K42: 沙市区北京路中央大道B区B35、B36、B37、B38、B39、B40商铺 | L42: 331 | M42: 2016.01.01-2016.12.31(租金:25万元/年) 2017.01.01-2017.12.30(租金:30万元/年) | N42: =O42/L42/365 -> 2.4831354 | O42: 300000 | T42: =(30-25)/25 -> 0.2
A43: 33 | B43: 湖北杰之行 | C43: 零售 | D43: 荆州 | E43: 直营 | F43: 地铺店 | G43: 荆州城中城阿迪\耐克店 | H43: 荆州荆中路城中城 | I43: 万四平 | J43: 李卫 | K43: 荆中路46号1-2楼 | L43: 400 | M43: 2015.07.01-2016.03.31(租金235950元,其中:2015.07.01-2015.09.30租金78650元已支付) 2016.04.01-2018.03.31(租金:314600元/年) 2018.04.01-2021.03.31(租金:410180元/年) | N43: =O43/L43/365 -> 2.6457877 | O43: =314600/12*3+410180/12*9 -> 386285 | T43: =(410180-314600)/314600 -> 0.30381437
B44: 湖北杰之行 | C44: 零售 | D44: 荆州 | E44: 直营 | F44: 地铺店 | G44: 荆州城中城阿迪\耐克店 | H44: 荆州荆中路城中城 | I44: 湖北杰之行 | J44: 李卫 | K44: 荆中路46号1-2楼 | L44: 400 | M44: 2015.07.01-2016.03.31(租金481140元,其中:2015.07.01-2015.09.30租金160380元已支付) 2016.04.01-2018.03.31(租金:641520元/年) 2018.04.01-2021.03.31(租金:641520元/年) | N44: =O44/L44/365 -> 4.3939726 | O44: =641520 -> 641520 | T44: 不涨
A45: 34 | B45: 湖北杰之行 | C45: 零售 | D45: 荆州 | E45: 直营 | F45: 地铺店 | G45: 荆州万达广场(二楼) | H45: 荆州万达集合店 | I45: 湖北杰之行 | J45: 荆州万达广场投资有限公司 | K45: 荆州万达广场室内步行街2楼2002AA-2002AB-2002B | L45: 396.05 | M45: 2015.08.01-2016.09.19（665364/年） 2016.09.20-2017.06.19（711939.48/年） | W45: 2016.04.30
A46: 35 | B46: 湖北杰之行 | C46: 零售 | D46: 荆州 | E46: 直营 | F46: 地铺店 | G46: 荆州万达广场(三楼) | H46: 荆州万达百货集合店 | I46: 湖北杰之行 | J46: 荆州万达广场投资有限公司 | K46: 荆州市荆州万达广场内购物中心三层的部分区域 | L46: 2046.88 | M46: 2016.03.01-2017.02.28(租金:50元/平米/月) 2017.03.01-2018.02.28(租金:60元/平米/月) 2018.03.01-2019.02.28(租金:62.4元/平米/月) 2019.03.01-2020.02.28(租金:64.9元/平米/月) 2020.03.01-2021.02.28(租金:67.5元/平米/月) 2021.03.01-2022.02.28(租金:70.2元/平米/月) | N46: =O46/L46/365 -> 2.0515068 | O46: =62.4*12*L46 -> 1532703.7 | T46: =(64.9-62.4)/62.4 -> 0.040064103 | U46: 2016.03.01-2017.02.28(物业管理费:6元/平米/月) 2017.03.01-2018.02.28(物业管理费:6元/平米/月) 2018.03.01-2019.02.28(物业管理费:6.24元/平米/月) 2019.03.01-2020.02.28(物业管理费:6.49元/平米/月) 2020.03.01-2021.02.28(物业管理费:6.75元/平米/月) 2021.03.01-2022.02.28(物业管理费:7.02元/平米/月) 空调使用费为:10元/月/平米,超时空调服务费标准为0.08元/小时/平米 | V46: =6.24*12*L46 -> 153270.37
A47: 36 | B47: 湖北杰之行 | C47: 零售 | D47: 荆州 | E47: 直营 | F47: 地铺店 | G47: 荆州新概念运动城 | H47: 荆州新概念运动城 | I47: 湖北杰之行 | J47: 荆州市杰之行 | K47: 荆州市荆州区球场路商业步行街D栋1层106-108室 | L47: 423 | M47: 2015.07.01-2016.12.31(租金:100万元/年) 2017.01.01-2017.12.31(租金:65万元/年) | N47: =O47/L47/365 -> 4.2099809 | O47: 650000
A48: 37 | B48: 湖北杰之行 | C48: 零售 | D48: 宜昌 | E48: 直营 | F48: 地铺店 | G48: 宜昌西陵李宁 | H48: 宜昌西陵李宁 | I48: 湖北杰之行 | J48: 邱小杰 | K48: 宜昌西陵一路67号 | M48: 2015.05.01-2018.04.30(租金:50万元/年) | O48: 500000
A49: 38 | B49: 湖北杰之行 | C49: 零售 | D49: 宜昌 | E49: 直营 | F49: 运动城 | G49: 宜昌CBD集合店 | H49: 宜昌CBD集合店 | I49: 湖北杰之行 | J49: 湖北胜道体育用品有限公司 | K49: 宜昌市夷陵大道58号南一层0001374室一\二楼 | L49: 900 | M49: 2015.07.01-2025.08.31(租金:300万元/年) | N49: =O49/L49/365 -> 9.1324201 | O49: 3000000
B50: 湖北杰之行 | D50: 宜昌 | E50: 直营 | F50: 运动城 | G50: 宜昌CBD集合店 | H50: 宜昌CBD集合店 | I50: 湖北杰之行 | J50: 湖北胜道体育用品有限公司 | K50: 宜昌市夷陵大道58号南一层0001374室一\二楼 | L50: 900 | M50: 2017.01.01-2018.12.31(租金:312万元/年） 2019.01.01-2020.12.31(租金:330万元/年） 2021.01.01-2022.12.31(租金:348万元/年） 2023.01.01-2024.08.31(租金:372万元/年） | N50: =O50/L50/365 -> 9.4977169 | O50: 3120000 | T50: =(330-312)/312 -> 0.057692308
A51: 39 | B51: 湖北杰之行 | C51: 零售 | D51: 宜昌 | E51: 直营 | F51: 集合店 | G51: 宜昌万达集合二店 | H51: 宜昌万达集合二店 | I51: 湖北杰之行 | J51: 宜昌万达广场投资有限公司 | K51: 宜昌伍家岗区沿江大道特168号 | L51: 1902.91 | M51: 2016.10.25-2017.10.24（租金：90元/平方米） 2017.10.25-2018.10.24（租金：90元/平方米） 2018.10.25-2019.10.24（租金：93.6元/平方米） 2019.10.25-2020.10.24（租金：97.34元/平方米） 2020.10.25-2021.10.24（租金：101.23元/平方米） 2021.10.25-2024.10.24（租金：105.28元/平方米） | N51: =O51/L51/365 -> 6.36 | O51: =90*L51/12*10+93.6*12*2*L51 -> 4417415.3 | T51: =(97.34-93.6)/93.6 -> 0.039957265 | U51: 2016.10.25-2017.10.24（物业：16元/平方米） 2017.10.25-2018.10.24（物业：16元/平方米） 2018.10.25-2019.10.24（物业：16.24元/平方米） 2019.10.25-2020.10.24（物业：16.48元/平方米） 2020.10.25-2021.10.24（物业：16.73元/平方米） 2021.10.25-2024.10.24（物业：16.98元/平方米） | V51: =16*L51*12 -> 365358.72
B52: 湖北杰之行 | C52: 零售 | D52: 宜昌 | E52: 直营 | F52: 集合店 | G52: 宜昌万达集合二店 | H52: 宜昌万达集合二店 | I52: 湖北杰之行 | J52: 宜昌万达广场投资有限公司 | K52: 宜昌伍家岗区沿江大道特168号 | L52: 40.47 | M52: 2016.11.26-2017.11.25（租金：360元/平方米） 2017.11.26-2018.11.25（租金：388.8元/平方米） 2017.11.26-2019.11.25（租金：419.9元/平方米） | N52: =O52/L52/365 -> 12.782466 | O52: =388.8*L52*12 -> 188816.83 | T52: =(388.8-360)/360 -> 0.08 | U52: 2016.11.26-2019.11.25（物业：60元/平方米） | V52: =60*L52*12 -> 29138.4
A53: 40 | B53: 湖北杰之行 | C53: 零售 | D53: 宜昌 | E53: 直营 | F53: 运动城 | G53: 宜昌万达运动城 | H53: 宜昌万达集合店 | I53: 湖北杰之行 | J53: 宜昌万达广场投资有限公司 | K53: 宜昌市沿江大道特166号万达广场综合楼一楼杰之行运动城 | L53: 1592 | M53: 2015.08.01-2017.08.25(起租日为2010.08.26),租金:95元/平米/元,租金第三年起,每个年度按按上一年度标准递增3% | U53: 2015.08.01-2017.08.25(起租日为2010.08.26),物业管理费:5元/平米/元,空调使用费:10元/平米/月,物业管理费第三年起,每个年度按按上一年度标准递增3% | W53: 42794
A54: 41 | B54: 湖北杰之行 | C54: 零售 | D54: 襄阳 | E54: 直营 | F54: 地铺店 | G54: 襄樊长虹李宁/襄樊长虹耐克 | H54: 襄阳长虹集合店 | I54: 湖北杰之行 | J54: 襄阳市汇誉商业管理有限公司 | K54: 襄樊市长虹路民发商业广场 | L54: 590.55 | M54: 2016.01.01-2016.12.31(租金：160275*3=480825元/季）2017.01.01-2017.12.31(租金：173090*3=519270元/季） | U54: 2016.01.01-2016.12.31(物业：97440元/季，公摊：26574元/季） 2017.01.01-2017.12.31(物业：102756元/季，公摊：31182元/季） | W54: 2016年9月30日终止
B55: 湖北杰之行 | C55: 零售 | D55: 襄阳 | E55: 直营 | F55: 地铺店 | G55: 襄樊长虹李宁/襄樊长虹耐克 | H55: 襄阳长虹集合店 | I55: 湖北杰之行 | J55: 襄阳市汇誉商业管理有限公司 | K55: 襄樊市长虹路民发商业广场 | L55: 416.15 | M55: 2016.10.1-2016.12.31（租金：75290元/月) 2017.1.1-2019.12.31（租金：121973元/月) 2020.1.1-2021.12.31（租金：131711元/月) | N55: =O55/L55/365 -> 9.6361197 | O55: =121973*12 -> 1463676 | T55: =(131711-121973)/121973 -> 0.079837341 | U55: 2016.10.1-2016.12.31（物业：29130元/月) 2017.1.1-2019.12.31（租金：31461元/月) 2020.1.1-2021.12.31（租金：33958元/月)
A56: 42 | B56: 湖北杰之行 | C56: 零售 | D56: 襄阳 | E56: 直营 | F56: 地铺店 | G56: 襄樊长虹李宁/襄樊长虹耐克（仓库） | H56: 襄阳长虹集合店 | I56: 湖北杰之行 | J56: 襄阳市汇誉商业管理有限公司 | K56: 民发商业广场时尚名店-1F1# | L56: 67.18 | M56: 2015.01.01-2017.12.31（450*12=5400元/年） | N56: =O56/L56/365 -> 0.2202221 | O56: =5400 -> 5400
A57: 43 | B57: 襄阳杰丽 | C57: 零售 | D57: 襄阳 | E57: 直营 | F57: 运动城 | G57: 襄樊新概念运动城 | H57: 襄樊新概念运动城 | I57: 襄阳杰丽 | J57: 襄樊璐萌物业服务有限公司 | K57: 襄樊市樊城区解放路228号 | L57: 1747.11 | M57: 2009.06.01-2016.09.30（960000元/年） | W57: 合同到期
B58: 湖北杰之行 | C58: 零售 | D58: 襄阳 | E58: 直营 | F58: 运动城 | G58: 襄樊新概念运动城 | H58: 襄樊新概念运动城 | I58: 湖北杰之行 | J58: 湖北美亚置业集团有限公司 | K58: 襄樊市樊城区解放路228号 | L58: 1747.11 | M58: 2016.10.01-2022.09.30（1630000元/年） | N58: =O58/L58/365 -> 2.5560803 | O58: 1630000 | T58: 不涨
A59: 44 | B59: 湖北杰之行 | C59: 零售 | D59: 襄阳 | E59: 直营 | F59: 运动城 | G59: 襄樊绅士广场运动城 | H59: 襄樊绅士运动城 | I59: 湖北杰之行 | J59: 襄樊市鹰翔摩托车有限公司 | K59: 襄樊市樊城区长征路125号 | L59: 300 | M59: 2015.08.01-2018.12.31(40万元/年) | N59: =O59/L59/365 -> 3.652968 | O59: 400000
A60: 45 | B60: 湖北杰之行 | C60: 零售 | D60: 襄阳 | E60: 直营 | F60: 运动城 | G60: 襄樊万达运动城 | H60: 襄樊万达运动城 | I60: 湖北杰之行 | J60: 襄樊万达广场投资有限公司 | K60: 襄樊市高新区紫贞路8号 | L60: 3112.81 | M60: 2010.11.26-2012.11.25(85/元/平方） 2012.11.26-2013.11.25(87.55/元/平方） 2013.11.26-2014.11.25(90.18/元/平方） 2014.11.26-2015.11.25(92.88/元/平方） 2015.11.26-2016.11.25(95.67/元/平方） 2016.11.26-2017.11.25(98.54/元/平方） | U60: 2010.11.26-2012.11.25(5/元/平方） 2012.11.26-2013.11.25(5.15/元/平方） 2013.11.26-2015.11.25(5.46/元/平方） 2015.11.26-2016.11.25(5.63/元/平方） 2016.11.26-2017.11.25(5.80/元/平方） 2010.11.26-2017.11.25(10元/平方) | W60: 合同到期
B61: 湖北杰之行 | D61: 襄阳 | E61: 直营 | F61: 运动城 | G61: 襄樊万达运动城 | H61: 襄樊万达运动城 | I61: 湖北杰之行 | J61: 襄樊万达广场投资有限公司 | K61: 襄樊市高新区紫贞路8号 | L61: 3934.9 | M61: 2017.8.1-2019.7.31（103/元/平方） 2019.8.1-2020.7.31（106.09元/平方） 2020.8.1-2021.3.31（109.27/元/平方） | N61: =O61/L61/365 -> 3.3863014 | O61: =103*L61*12 -> 4863536.4 | T61: =(106.09-103)/103 -> 0.03 | U61: 2017.8.1-2019.7.31（17元/平方） 2019.8.1-2020.7.31（17.21元/平方） 2020.8.1-2021.3.31（117.43/元/平方） | V61: =17*12*L61 -> 802719.6
A62: 46 | B62: 湖北杰之行 | C62: 零售 | D62: 荆门 | E62: 直营 | F62: 地铺店 | G62: 荆门万达广场集合店 | H62: 荆门万达集合店 | I62: 湖北杰之行 | J62: 荆门万达广场投资有限公司 | K62: 湖北省荆州市荆门万达广场购物中心二楼二层的商铺 | L62: 2153.55 | M62: 2016.06.03-2018.06.02(租金:80元/月/平米) 2018.06.03-2019.06.02(租金:83.2元/月/平米) 2019.06.03-2020.06.02(租金:86.53元/月/平米) 2020.06.03-2021.06.02(租金:89.99元/月/平米) 2021.06.03-2022.06.02(租金:93.59元/月/平米) 或:月租金=月销售额*8%,两者取其高 | N62: =O62/L62/365 -> 2.630137 | O62: =80*12*L62 -> 2067408 | U62: 2016.06.03-2018.06.02(物业管理费:6元/月/平米) 2018.06.03-2019.06.02(物业管理费:6.24元/月/平米) 2019.06.03-2020.06.02(物业管理费:6.49元/月/平米) 2020.06.03-2021.06.02(物业管理费:6.75元/月/平米) 2021.06.03-2022.06.02(物业管理费:7.02元/月/平米) 空调使用费:10元/月/平米 | V62: =(6.13+10)*12*L62 -> 416841.14
A63: 47 | B63: 湖北杰之行 | C63: 零售 | D63: 十堰 | E63: 直营 | F63: 运动城 | G63: 十堰新概念运动城 | H63: 十堰新概念集合店 | I63: 湖北杰之行 | J63: 十堰市堰丰酒店管理有限公司 | K63: 十堰市人民北路堰丰宾馆一楼 | L63: 1076 | M63: 2015.12.01-2018.11.30(租金:190万元/年) 2018.12.01-2020.11.30(租金:208万元/年) | N63: =O63/L63/365 -> 4.8378062 | O63: 1900000 | T63: =(208-190)/190/5 -> 0.018947368
A64: 48 | B64: 湖北杰之行 | C64: 零售 | D64: 十堰 | E64: 直营 | F64: 运动城 | G64: 十堰京堰运动城 | H64: 十堰京堰集合店 | I64: 湖北杰之行 | J64: 熊六波 | K64: 十堰市五堰香港街4号武当商城三号楼 | L64: 1060 | M64: 2015.05.01-2018.09.10(租金:60万元/年) | N64: =O64/L64/365 -> 1.5507883 | O64: 600000
A65: 49 | B65: 湖北杰之行 | C65: 零售 | D65: 十堰 | E65: 直营 | F65: 集合店 | G65: 十堰万达集合店 | H65: 十堰万达广场集合店 | I65: 湖北杰之行 | J65: 十堰万达置业有限公司 | K65: 十堰万达购物广场娱乐楼1B层 | L65: 1694.27 | M65: 2016.08.05-2018.08.04(租金:75元/平米*月) 2018.08.05-2019.08.04(固定租金:78元/平米*月) 2019.08.05-2020.08.04(固定租金:81.12元/平米*月) 2020.08.05-2021.08.04(固定租金:84.36元/平米*月) 2021.08.05-2022.08.04(固定租金:87.74元/平米*月) 2016.08.05-2022.08.04(抽成租金:销售额的8%,\两者取其高者 | N65: =O65/L65/365 -> 2.4986301 | O65: =75*L65*12/12*8+78*L65*12/12*4 -> 1545174.2 | T65: =(78-75)/75 -> 0.04 | U65: 2016.08.05-2018.08.04(物业管理费:6元/平米*月) 2018.08.05-2019.08.04(物业管理费:6.24元/平米*月) 2019.08.05-2020.08.04(物业管理费:6.49元/平米*月) 2020.08.05-2021.08.04(物业管理费:6.75元/平米*月) 2021.08.05-2022.08.04(物业管理费:7.02元/平米*月) 空调使用费:10元/平米*月 | V65: =6.24*8*L65+6.49*4*L65 -> 128561.21
B66: 湖北杰之行 | C66: 零售 | D66: 十堰 | E66: 直营 | F66: 集合店 | G66: 十堰万达李宁店 | H66: 十堰万达李宁店 | I66: 湖北杰之行 | J66: 十堰万达广场置业有限公司 | K66: 十堰万达广场内购物中心室内步行街1BF层1B61号商铺 | L66: 248.62 | M66: 2016.08.05-2016.11.30(租金:110843.08元) 2016.12.01-2017.02.28(租金:62155元) 2017.03.01-2017.05.31(租金:62155元) 2017.06.01-2017.08.31(租金:74472.05元) 2017.09.01-2018.08.04(租金:33252.93元/月) 2018.08.05-2019.08.04(租金:35580.64元/月) | N66: =O66/L66/365 -> 4.5255146 | O66: =33252.93*7+35580.64*5 -> 410673.71 | T66: =(35580.64-33252.93)/33252.93 -> 0.070000147 | U66: 2016.08.05-2019.08.04(物业管理费:13674.10元/月) | V66: =13674.1*12 -> 164089.2
A67: 50 | B67: 湖北杰之行 | C67: 零售 | D67: 武汉 | E67: 直营 | F67: 集合店 | G67: 应城城市广场 | H67: 应城中央广场集合店 | I67: 湖北杰之行 | J67: 应城市泓诚商业管理有限公司（房租+商业） 应城市泓信商业管理有限公司（物业） | K67: 应城市全洲盛世城5号1层127-141铺 | L67: 641.52 | M67: 2016.12.18-2017.12.17(租金:50万元/年) 2017.12.18-2018.12.17(租金:58万元/年) 2018.12.18-2019.12.17(租金:66万元/年) 2019.12.18-2020.12.17(租金:74万元/年) 2020.12.18-2021.12.17(租金:82万元/年) | N67: =O67/L67/365 -> 2.4769939 | O67: 580000 | T67: =(66-58)/58 -> 0.13793103 | U67: 2016.12.18-2017.12.17(商业管理费:10万元/年;物业管理费:10万元/年) 2017.12.18-2018.12.17(商业管理费:10万元/年;物业管理费:12万元/年) 2018.12.18-2019.12.17(商业管理费:10万元/年;物业管理费:14万元/年) 2019.12.18-2020.12.17(商业管理费:10万元/年;物业管理费:11万元/年) 2020.12.18-2021.12.17(商业管理费:10万元/年;物业管理费:8万元/年) | V67: 220000
A68: 51 | B68: 湖北杰之行 | C68: 零售 | D68: 黄冈 | E68: 直营 | F68: 集合店 | G68: 黄冈奥康步行街集合店 | H68: 黄冈奥康步行街集合店 | I68: 湖北杰之行 | J68: 黄冈工贸家电商贸有限公司 | K68: 黄冈市黄州区奥康商业步行街1号D幢一楼 | L68: 1000 | M68: 2017.1.1-2017.12.31（租金：868219元/年,217055元/季） | W68: 合同终止
B69: 湖北杰之行 | C69: 零售 | D69: 黄冈 | E69: 直营 | F69: 集合店 | G69: 黄冈奥康步行街集合店 | H69: 黄冈奥康步行街集合店 | I69: 湖北杰之行 | J69: 黄冈工贸家电商贸有限公司 | K69: 黄冈市黄州区奥康商业步行街1号D幢一楼 | L69: 1330 | M69: 2018.1.1-2020.12.31（租金：274500元/季，1098000元/年） 2021.1.1-2022.12.31（租金：288225元/季，1152900元/年） | N69: =O69/L69/365 -> 2.2618189 | O69: 1098000 | T69: =(1152900-1098000)/1098000/4 -> 0.0125
A70: 52 | B70: 湖北杰之行 | C70: 零售 | D70: 随州 | E70: 直营 | F70: 集合店 | G70: 随州大润发集合店 | H70: 随州大润发运动城 | I70: 湖北杰之行 | J70: 随州大润发商业有限公司 | K70: 随州店商店街1060号柜面 | L70: 700 | M70: 2017.1.1-2017.12.31（租金：59240元/月），2018.1.1-2018.12.31（租金：65160元/月） | N70: =O70/L70/365 -> 3.0603523 | O70: =65160*12 -> 781920 | T70: =(65160-59240)/59240 -> 0.099932478 | U70: POP架租金费用50元/月
A71: 53 | B71: 湖北杰之行 | C71: 零售 | D71: 孝感 | E71: 直营 | F71: 地铺店 | G71: 孝感银泰百货李宁 | H71: 孝感银泰百货李宁 | I71: 湖北杰之行 | J71: 孝感银泰商贸有限公司 | K71: 孝感银泰百货3F301-2 | L71: 153 | M71: 2017.5.26-2019.5.25(抽成租金10%）2019.5.26-2020.5.25（抽成租金11%） | O71: 营业额？
B72: 湖北杰之行 | C72: 零售 | D72: 孝感 | E72: 直营 | F72: 地铺店 | G72: 孝感银泰百货阿迪 | H72: 孝感银泰百货阿迪 | I72: 湖北杰之行 | J72: 孝感银泰商贸有限公司 | K72: 孝感银泰百货3F302-1 | L72: 273 | M72: 2017.5.26-2019.5.25(抽成租金10%）2019.5.26-2020.5.25（抽成租金11%）
B73: 湖北杰之行 | C73: 零售 | D73: 孝感 | E73: 直营 | F73: 地铺店 | G73: 孝感银泰百货阿迪生活 | H73: 孝感银泰百货阿迪生活 | I73: 湖北杰之行 | J73: 孝感银泰商贸有限公司 | K73: 孝感银泰百货1F108 | L73: 82 | M73: 2017.5.26-2019.5.25(抽成租金10%）2019.5.26-2020.5.25（抽成租金11%）
B74: 湖北杰之行 | C74: 零售 | D74: 孝感 | E74: 直营 | F74: 地铺店 | G74: 孝感银泰百货耐克 | H74: 孝感银泰百货耐克 | I74: 湖北杰之行 | J74: 孝感银泰商贸有限公司 | K74: 孝感银泰百货3F302-2 | L74: 252 | M74: 2017.5.26-2019.5.25(抽成租金10%）2019.5.26-2020.5.25（抽成租金11%）
B75: 湖北杰之行 | C75: 零售 | D75: 孝感 | E75: 直营 | F75: 地铺店 | G75: 孝感银泰百货耐克360 | H75: 孝感银泰百货耐克360 | I75: 湖北杰之行 | J75: 孝感银泰商贸有限公司 | K75: 孝感银泰百货1F107 | L75: 82 | M75: 2017.5.26-2019.5.25(抽成租金10%）2019.5.26-2020.5.25（抽成租金11%）
A76: 54 | B76: 湖北杰之行 | D76: 武汉 | E76: 直营 | F76: 地铺店 | G76: 江北交通路 | H76: 江北交通路 | I76: 湖北杰之行 | J76: 邓奎 | K76: 武汉轻轨2号线江汉路站还建楼项目1-58 | L76: 670.62 | M76: 2017.9.1-2020.8.31（租金：5890726元/年） 2020.9.1-2021.8.31 (租金：6185262元/年） 2021.9.1-2022.8.31（租金：6494526元/年） | N76: =O76/L76/365 -> 24.065753 | O76: 5890726
A77: 55 | B77: 湖北杰之行 | C77: 零售 | D77: 襄阳 | E77: 直营 | F77: 地铺店 | G77: 襄阳民发广场运动城 | H77: 襄阳民发广场运动城 | I77: 湖北杰之行 | J77: 襄阳市汇誉商业管理有限公司 | K77: 襄阳市襄州区张湾街道办事处西湾村1组（交警一大队旁） | L77: 1860 | M77: 租金或扣点两者取其高 2017.9.15-2018.9.14（租金:31164元/月） 2018.9.15-2020.9.14（租金:62328元/月) 2020.9.15-2023.9.14 (租金:68560元/月) 2023.9.15-2027.9.14 (租金:76855元/月) 2017.9.15-2020.9.14（提成:8.5折10%,6-8.4折8%,5.9折以下6%） 2020.9.15-2023.9.14（提成:8.5折11%,6-8.4折9%,5.9折以下7%） 2023.9.15-2027.9.14（提成:8.5折12%,6-8.4折10%,5.9折以下8%） | N77: =O77/L77/365 -> 0.55084401 | O77: =31164*12 -> 373968 | T77: =(68560-62328)/62328 -> 0.099987165
A78: 56 | B78: 湖北杰之行 | C78: 零售 | D78: 武汉 | E78: 直营 | F78: 地铺店 | G78: 武汉K11耐克店 | H78: 江南光谷K11耐克店 | I78: 59 | J78: 新世界嘉业（武汉）有限公司 | K78: 武汉东湖新技术开发区关山大道353号I座 | L78: 453 | M78: 第一年租金：0元/月/平米 第二年租金：第一年实收/（天数*面积）*100% 第三年租金：9元/月/平米 第四年租金：10元/月/平米 第五年租金：11元/月/平米 第一年租金：抽成租金：12% 第二年租金：抽成租金：12% 第三年租金：抽成租金：13% 第四年租金：抽成租金：14% 第五年租金：抽成租金：15% 两者取其高者 | N78: =O78/L78/365 -> 0.29589041 | O78: =9*453*12 -> 48924 | T78: 0.1 | U78: 物业：80元/平方/月（36240元/月） | V78: 36240
A79: 57 | B79: 湖北杰之行 | C79: 零售 | D79: 孝感 | E79: 直营 | F79: 地铺店 | G79: 孝感文化路 | H79: 孝感文化广场美邦 | I79: 湖北杰之行 | J79: 孝感杰丽 | K79: 孝感文化路52号门面 | L79: 94 | M79: 2017.06.1-2017.12.31（租金共计300000元） | N79: =O79/L79/365 -> 8.7438065 | O79: 300000 | T79: 不涨
A80: 58 | B80: 湖北杰之行 | C80: 零售 | D80: 武汉 | E80: 直营 | F80: 集合店 | G80: 青山印象城 | H80: 武汉青山印象城集合店 | I80: 湖北杰之行 | J80: 湖北胜道体育用品有限公司 | K80: 武汉市青山区和平大道1278号01-14商铺 | L80: 1808.76 | M80: 2017.8.28-2020.8.27（租金：150万元/年） | N80: =O80/L80/365 -> 2.2720477 | O80: 1500000 | T80: 不涨
A81: =COUNT(A$2:A80)+1 -> 59 | B81: 湖北杰之行 | C81: 零售 | D81: 武汉 | E81: 直营 | F81: 地铺店 | G81: 江北宜家万斯 | H81: 江北宜家万斯 | I81: 湖北杰之行 | J81: 武汉英特宜家置业有限公司 | K81: 武汉市桥口区长宜路1号购物中心L12层1-12-08-SU单元号 | L81: 88 | M81: 2017.11.15-2018.11.14（基本租金：304.17元/平方/月） 2018.11.15-2019.11.14（基本租金：334.58元/平方/月） 2017.11.15-2019.11.14（提成比例：15%） | N81: =O81/L81/365 -> 10.00011 | O81: =304.17*88*12 -> 321203.52 | T81: =(334.58-304.17)/304.17 -> 0.099976987 | U81: 2017.11.15-2018.11.14物业费:70元/平米/月,推广费;13.89元/平米/月 2018.11.15-2019.11.14物业费:70元/平米/月,推广费;14.58元/平米/月 （推广费从第二年度每年向上调整5%） | V81: =(70+13.89)*12*L81 -> 88587.84
A82: =COUNT(A$2:A81)+1 -> 60 | B82: 武汉杰锐 | C82: 零售 | D82: 武汉 | E82: 直营 | F82: 地铺店 | G82: 江北江汉路李宁一店/耐克、匡威 | H82: 江北江汉路 | I82: 武汉杰锐 | J82: 武汉鑫隆经贸有限责任公司 | K82: 武汉市江岸区江汉路184号3-4栋1楼2号房 | L82: 110 | M82: 2015.01.01-2017.12.31(租金:20万元/年) 2018.01.01-2018.12.31(租金:22万元/年) | N82: =O82/L82/365 -> 5.4794521 | O82: 220000 | T82: 0.1
B83: 湖北杰之行 | C83: 零售 | D83: 武汉 | E83: 直营 | F83: 地铺店 | G83: 江北江汉路李宁一店(外仓) | H83: 江北江汉路 | I83: 湖北杰之行 | J83: 罗群 | K83: 武汉市江汉区江汉路福新里4号一楼 | L83: 40 | M83: 2012.10.16-2015.10.15（13200元/年） 2015.12.01-2017.12.31(13200元/年) | N83: =O83/L83/365 -> 0.90410959 | O83: 13200 | T83: 不涨
A84: =COUNT(A$2:A83)+1 -> 61 | B84: 湖北杰之行 | C84: 零售 | D84: 襄阳 | E84: 直营 | F84: 办公室 | G84: 襄阳办公室 | H84: 襄阳办公室 | I84: 湖北杰之行 | J84: 湖北小白象商贸有限公司 | K84: 襄阳市长征路都市花园2#－2房 | L84: 300 | M84: 2012.09.05-2013.09.04（48000元/年） 2013.09.05-2014.09.04（50000元/年） 2014.09.05-2016.09.04（60000元/年） 2016.09.05-2017.09.04（63000元/年） 2017.09.05-2020.09.04（62000元/年） | N84: =O84/L84/365 -> 0.56621005 | O84: 62000 | T84: 不涨
A85: =COUNT(A$2:A84)+1 -> 62 | B85: 湖北杰之行 | C85: 零售 | D85: 荆门 | E85: 直营 | F85: 办公室 | G85: 荆门办公室 | H85: 荆门办公室 | I85: 湖北杰之行 | J85: 周仙桃 | K85: 荆门长宁大道68号金地广场24楼2401号 | M85: 2014.03.01-2019.02.28（29000元/年） | O85: 29000 | T85: 不涨
A86: =COUNT(A$2:A85)+1 -> 63 | B86: 湖北杰之行 | C86: 零售 | D86: 十堰 | E86: 直营 | F86: 办公室 | G86: 十堰办公室 | H86: 十堰办公室 | I86: 湖北杰之行 | J86: 茅箭区五堰诗阳广告部 | K86: 十堰市人民路三号六楼南边 | L86: 100 | M86: 2014.06.20-2016.06.19（28000元/年） 2016.06.20-2018.06.19（28000元/年） | N86: =O86/L86/365 -> 0.76712329 | O86: 28000 | T86: 不涨
A87: =COUNT(A$2:A86)+1 -> 64 | B87: 湖北杰之行 | C87: 零售 | D87: 仙桃 | E87: 直营 | F87: 办公室 | G87: 仙桃办公室 | H87: 仙桃办公室 | I87: 邱永新 | J87: 谢红韬 | K87: 宏运名居2号楼1单元101 | M87: 2014.07.08-2019.07.09(租金:22000元/年) | O87: 22000 | T87: 不涨
A88: =COUNT(A$2:A87)+1 -> 65 | B88: 湖北杰之行 | C88: 零售 | D88: 宜昌 | E88: 直营 | F88: 办公室 | G88: 宜昌办公室 | H88: 宜昌办公室 | I88: 湖北杰之行 | J88: 刘远杏 | K88: 在宜昌市西陵一路10号墨池苑⒊13⒁ | L88: 133 | M88: 2016.1.12-2019.1.11(租金:35000元/年) | N88: =O88/L88/365 -> 0.72098053 | O88: 35000 | T88: 不涨 | U88: 年物业费为:2075元/年。价格如后期有变动,按物业管理方给出价格为准 | V88: 2075
A89: =COUNT(A$2:A88)+1 -> 66 | B89: 湖北杰之行淮南分公司 | C89: 零售 | D89: 安徽 | E89: 直营 | F89: 地铺店 | G89: 淮南大金新百集合店 | H89: 淮南大金新百集合店 | I89: 湖北杰之行淮南分公司 | J89: 大金新百淮南百货有限公司 | K89: 安徽大金新百淮南百货有限公司第一层 | L89: 652 | M89: 2015.09.01-2017.09.01(租金:70.42万元/年) 2017.09.01-2020.09.01(租金:77.46万元/年)－－欢乐一卡通,各商户按一卡通的刷卡消费金额进行月结, 1-60000元 2% 60001-120000元 3% 120001元以上 4%封顶 | W89: 关店
A90: =COUNT(A$2:A89)+1 -> 67 | B90: 湖北杰之行马鞍山分公司 | C90: 零售 | D90: 安徽 | E90: 直营 | F90: 地铺店 | G90: 马鞍山万达集合店 | H90: 马鞍山万达集合店 | I90: 湖北杰之行马鞍山分公司 | J90: 马鞍山万达广场商业管理有限公司 | K90: 马鞍山万达广场购物中心娱乐楼二层 | L90: 1849.26 | M90: 2015.11.20-2016.01.31(租金:32.88元/月/平米) 2016.02.01-2016.08.31(租金:80元/月/平米) 2016.09.01-2016.12.31(租金:36985.2元/月)减租协议 2017.01.01-2017.11.19(租金:80元/月/平米) 2017.11.20-2018.11.19(租金:83.2元/月/平米) 2018.12.20-2019.11.19(租金:86.53元/月/平米) 2019.11.20-2020.11.19(租金:89.99元/月/平米) 2020.11.20-2021.11.19(租金:93.59元/月/平米) | N90: =O90/L90/365 -> 2.7353425 | O90: =83.2*L90*12 -> 1846301.2 | T90: =(83.2-80)/80 -> 0.04 | U90: 2015.11.20-2016.01.31(物业费:2.47元/月/平米) 2016.02.01-2017.11.19(物业费:6.24元/月/平米) 2017.11.20-2018.11.19(物业费:6.49元/月/平米) 2018.12.20-2019.11.19(物业费:6.75元/月/平米) 2019.11.20-2020.11.19(物业费:7.02元/月/平米) 2020.11.20-2021.11.19(物业费:7.30元/月/平米) 空调使用费为:10元/月/平米,POS机费用:300元/月 | V90: =6.49*12*L90 -> 144020.37
A91: =COUNT(A$2:A90)+1 -> 68 | B91: 湖北杰之行芜湖分公司 | C91: 零售 | D91: 安徽 | E91: 直营 | F91: 地铺店 | G91: 芜湖镜湖万达广场集合店(百货区) | H91: 芜湖镜湖万达集合店 | I91: 湖北杰之行芜湖分公司 | J91: 芜湖万达广场有限公司 | K91: 芜湖万达广场内购物中心百货区域一层 | L91: 1546.34 | M91: 2016.01.01-2016.03.31(租金:26.67元/月/平米) 2016.04.01-2017.12.31(租金:80.00元/月/平米) 2018.01.01-2018.12.31(租金:83.20元/月/平米) 2019.01.01-2019.12.31(租金:86.53元/月/平米) 2020.01.01-2020.12.31(租金:89.99元/月/平米) 2021.01.01-2021.12.31(租金:93.59元/月/平米) | U91: 2016.01.01-2017.12.31(物业费:6.00元/月/平米) 2018.01.01-2018.12.31(物业费:6.18元/月/平米) 2019.01.01-2019.12.31(物业费:6.37元/月/平米) 2020.01.01-2020.12.31(物业费:6.56元/月/平米) 2021.01.01-2021.12.31(物业费:6.76元/月/平米) 空调使用费:10元/月/平米,POS机使用费:300元/月 | W91: 42977
B92: 湖北杰之行芜湖分公司 | C92: 零售 | D92: 安徽 | E92: 直营 | F92: 地铺店 | G92: 芜湖镜湖万达广场集合店(步行街区) | H92: 芜湖镜湖万达集合店 | I92: 湖北杰之行芜湖分公司 | J92: 芜湖万达广场有限公司 | K92: 芜湖市镜湖万达广场内购物中心步行街一层01-50号商铺 | L92: 89.64 | M92: 2016.01.01-2017.12.31(租金:25099.20元/月) 2018.01.01-2018.12.31(租金:26856.14元/月) 2019.01.01-2019.12.31(租金:28736.07元/月) 2020.01.01-2020.12.31(租金:30747.59元/月) 2021.01.01-2021.12.31(租金:32899.92元/月) | U92: 2016.01.01-2016.12.31(物业费:55元/月/平米) 以后租约年物业费以书面通知执行,若无,按上一租约年执行 POS机使用费:300元/月 | W92: 42977
A93: =COUNT(A$2:A92)+1 -> 69 | B93: 湖北杰之行合肥一分公司 | C93: 零售 | D93: 安徽 | E93: 直营 | F93: 集合店 | G93: 合肥瑶海万达集合店 | H93: 合肥瑶海万达集合店 | I93: 湖北杰之行合肥一分公司 | J93: 合肥瑶海万达投资有限公司 | K93: 安徽省合肥市合肥瑶海万达城万达购物中心娱乐综合楼二楼 | L93: 1842 | M93: 2016.09.09-2018.09.08(租金:80元/月/平米) 2018.09.09-2019.09.08(租金:83.2元/月/平米) 2019.09.09-2020.09.08(租金:86.53元/月/平米) 2020.09.09-2021.09.08(租金:89.99元/月/平米) 2021.09.09-2022.09.08(租金:93.59元/月/平米) 或:月租金=月销售额*8%,两者取其高 | N93: =O93/L93/365 -> 1.8828288 | O93: =83.2*L93*8+86.53*L93/4 -> 1265882.3 | T93: =(86.53-83.2)/83.2 -> 0.040024038 | U93: 2016.09.09-2018.09.08(物业管理费:6元/月/平米) 2018.09.09-2019.09.08(物业管理费:6.24元/月/平米) 2019.09.09-2020.09.08(物业管理费:6.49元/月/平米) 2020.09.09-2021.09.08(物业管理费:6.75元/月/平米) 2021.09.09-2022.09.08(物业管理费:7.02元/月/平米) 空调使用费:10元/月/平米 | V93: =6*12*L93 -> 132624
A94: =COUNT(A$2:A93)+1 -> 70 | B94: 湖北杰之行合肥二分公司 | C94: 零售 | D94: 安徽 | E94: 直营 | F94: 集合店 | G94: 合肥滨湖万达城集合店 | H94: 合肥万达集合店 | I94: 湖北杰之行合肥二分公司 | J94: 合肥万达投资有限公司 | K94: 安徽省合肥市合肥万达城万达购物中心娱乐综合楼一楼 | L94: 2231.64 | M94: 2016.09.24-2018.09.23(租金:80元/月/平米) 2018.09.24-2019.09.23(租金:83.2元/月/平米) 2019.09.24-2020.09.23(租金:86.53元/月/平米) 2020.09.24-2021.09.23(租金:89.99元/月/平米) 2021.09.24-2022.09.23(租金:93.59元/月/平米) 或:月租金=月销售额*8%,两者取其高 | N94: =O94/L94/365 -> 2.700274 | O94: =80*4*L94+83.2*8*L94 -> 2199504.4 | T94: =(86.53-83.2)/83.2 -> 0.040024038 | U94: 2016.09.24-2018.09.23(物业管理费:6元/月/平米) 2018.09.24-2019.09.23(物业管理费:6.24元/月/平米) 2019.09.24-2020.09.23(物业管理费:6.49元/月/平米) 2020.09.24-2021.09.23(物业管理费:6.75元/月/平米) 2021.09.24-2022.09.23(物业管理费:7.02元/月/平米) 空调使用费:10元/月/平米 | V94: =6*12*L94 -> 160678.08
A95: =COUNT(A$2:A94)+1 -> 71 | B95: 湖北杰之行亳州分公司 | C95: 零售 | D95: 安徽 | E95: 直营 | F95: 集合店 | G95: 亳州万达集合店 | H95: 亳州万达集合店 | I95: 湖北杰之行亳州分公司 | J95: 亳州万达广场投资有限公司 | K95: 安徽省亳州市万达广场内购物中心娱乐综合楼二层 | L95: 1920 | M95: 2016.08.12-2018.08.11(租金:65元/月/平米) 2018.08.12-2019.08.11(租金:67.6元/月/平米) 2019.08.12-2020.08.11(租金:70.3元/月/平米) 2020.08.12-2021.08.11(租金:73.12元/月/平米) 2021.08.12-2022.08.11(租金:76.04元/月/平米) 或:月租金=月销售额*8%,两者取其高 | N95: =O95/L95/365 -> 2.1369863 | O95: =65*L95*12 -> 1497600 | T95: =(67.6-65)/65 -> 0.04 | U95: 2016.08.12-2018.08.11(物业管理费:6元/月/平米) 2018.08.12-2019.08.11(物业管理费:6.24元/月/平米) 2019.08.12-2020.08.11(物业管理费:6.49元/月/平米) 2020.08.12-2021.08.11(物业管理费:6.75元/月/平米) 2021.08.12-2022.08.11(物业管理费:7.02元/月/平米) 空调使用费:10元/月/平米 | V95: =6*L95*12 -> 138240
A96: =COUNT(A$2:A95)+1 -> 72 | B96: 湖北杰之行阜阳分公司 | C96: 零售 | D96: 安徽 | E96: 直营 | F96: 集合店 | G96: 阜阳颖泉万达集合店 | H96: 阜阳颖泉万达集合店 | I96: 湖北杰之行阜阳分公司 | J96: 阜阳颖泉万达广场投资有限公司 | K96: 阜阳颖泉万达广场1F | L96: 2212.67 | M96: 2017.06.16-2018.06.15（租金：50元/月/平方米) 2018.06.16-2019.06.15（租金：50元/月/平方米) 2019.06.16-2020.06.15（租金：52元/月/平方米) 2020.06.16-2021.06.15（租金：54.08元/月/平方米) 2021.06.16-2022.06.15（租金：56.24元/月/平方米) 2022.06.16-2023.06.15（租金：58.49元/月/平方米) 2023.06.16-2024.06.15（租金：60.83元/月/平方米) 2024.06.16-2025.06.15（租金：63.87元/月/平方米) | N96: =O96/L96/365 -> 1.6438356 | O96: =50*12*L96 -> 1327602 | T96: =(54.08-52)/52 -> 0.04 | U96: 2017.06.16-2018.06.15（租金：16/月/平方米) 2018.06.16-2019.06.15（租金：16元/月/平方米) 2019.06.16-2020.06.15（租金：16.24元/月/平方米) 2020.06.16-2021.06.15（租金：16.49元/月/平方米) 2021.06.16-2022.06.15（租金：16.75元/月/平方米) 2022.06.16-2023.06.15（租金：17.02元/月/平方米) 2023.06.16-2024.06.15（租金：17.30元/月/平方米) 2024.06.16-2025.06.15（租金：17.59元/月/平方米) | V96: =16*L96*12 -> 424832.64
A97: =COUNT(A$2:A96)+1 -> 73 | B97: 湖北杰之行南昌分公司 | C97: 零售 | D97: 江西 | E97: 直营 | F97: 集合店 | G97: 南昌九龙湖万达集合店(1210平米区域2075) | H97: 南昌万达城集合店 | I97: 湖北杰之行南昌分公司 | J97: 南昌万达城投资有限公司 | K97: 南昌市万达城内购物中心步行街二层2075号商铺 | L97: 1210 | M97: 2016.05.28-2016.08.31(租金:227480元) 2016.09.01-2016.11.30(租金:145200元) 2016.12.01-2017.02.28(租金:145200元) 2017.03.01-2017.05.27(租金:135520元) 2017.05.28-2018.05.27(租金:77682元/月) 2018.05.28-2019.05.27(租金:83119.74元/月) 2019.05.28-2020.05.27(租金:88938.12元/月) 2020.05.28-2021.05.27(租金:95163.79元/月) | U97: 物业管理费:50元/平米/月(即60500元/月) | W97: 43014
B98: 湖北杰之行南昌分公司 | C98: 零售 | D98: 江西 | E98: 直营 | F98: 集合店 | G98: 南昌九龙湖万达集合店(321平米区域2077) | H98: 南昌万达城集合店 | I98: 湖北杰之行南昌分公司 | J98: 南昌万达城投资有限公司 | K98: 南昌市万达城内购物中心步行街二层2077号商铺 | L98: 321 | M98: 2016.05.28-2016.08.31(租金:80464元) 2016.09.01-2016.11.30(租金:51360元) 2016.12.01-2017.02.28(租金:51360元) 2017.03.01-2017.05.27(租金:47936元) 2017.05.28-2018.05.27(租金:27477.6元/月) 2018.05.28-2019.05.27(租金:29401.03元/月) 2019.05.28-2020.05.27(租金:31459.10元/月) 2020.05.28-2021.05.27(租金:33661.24元/月) | U98: 物业管理费:50元/平米/月(即16050元/月) | W98: 43014
A99: =COUNT(A$2:A98)+1 -> 74 | B99: 湖北杰之行上饶分公司 | C99: 零售 | D99: 江西 | E99: 直营 | F99: 集合店 | G99: 上饶万达集合店 | H99: 上饶万达集合店 | I99: 湖北杰之行上饶分公司 | J99: 上饶万达广场投资有限公司 | K99: 上饶市万达广场2F-次主3 | L99: 1990.27 | M99: 2016.11.25-2018.11.24(租金:75元/月/平米) 2018.11.25-2019.11.24(租金:78元/月/平米) 2019.11.25-2020.11.24(租金:81.12元/月/平米) 2020.11.25-2021.11.24(租金:84.36元/月/平米) 2021.11.25-2022.11.24(租金:87.74元/月/平米) 或:月租金=月销售额*8%,两者取其高 | N99: =O99/L99/365 -> 2.4657534 | O99: =75*L99*12 -> 1791243 | T99: =(78-75)/75 -> 0.04 | U99: 2016.11.25-2018.11.24(物业管理费:6元/月/平米) 2018.11.25-2019.11.24(物业管理费:6.24元/月/平米) 2019.11.25-2020.11.24(物业管理费:6.49元/月/平米) 2020.11.25-2021.11.24(物业管理费:6.75元/月/平米) 2021.11.25-2022.11.24(物业管理费:7.02元/月/平米) 空调使用费:10元/月/平米 | V99: =6*L99*12 -> 143299.44
A100: =COUNT(A$2:A99)+1 -> 75 | B100: 湖北杰之行九江分公司 | C100: 零售 | D100: 九江 | E100: 直营 | F100: 集合店 | G100: 九江天禧城市广场集合店 | H100: 九江天禧城市广场集合店 | I100: 湖北杰之行九江分公司 | J100: 九江智禧实业有限公司 | K100: 江西省九江市庐山区浔南大道的天禧广场-购物中心2层S11-220、221、222号 | L100: 1037 | M100: 2016.12.28-2018.12.27（租金：销售收入*8%） 2018.12.28-2020.12.27（租金：销售收入*9%） 2020.12.28-2022.12.27（租金：销售收入*10%） 2022.12.28-2023.12.27（租金：销售收入*11%） 2023.12.28-2024.12.27（租金：销售收入*12%） 租赁期前两年每季度收取2个月的经营场地使用费（减免8个月费用）
...

Sheet 财务费用预测表
A1: 财务费用预测表
I2: =[35]封面!A11 -> 评估基准日:2017年12月31日
J3: 人民币元
H4: 0.02 | I4: 0.02 | J4: 0.02 | K4: 0.02 | L4: 0.02
C5: 历史费用情况 | H5: 未来费用预测
A6: 项目 | C6: =[35]未来收入预测表!C6 -> 2013年 | D6: =[35]未来收入预测表!D6 -> 2014年 | E6: =[35]未来收入预测表!E6 -> 2015年 | F6: =[35]未来收入预测表!F6 -> 2016年 | G6: =[35]未来收入预测表!G6 -> 2017年 | H6: =[35]未来收入预测表!H6 -> 2018年 | I6: =[35]未来收入预测表!I6 -> 2019年 | J6: =[35]未来收入预测表!J6 -> 2020年 | ... L6: =[35]未来收入预测表!L6 -> 2022年
A7: 财务费用 | B7: 手续及工本费 | C7: 3298242.6 | D7: 5484942 | E7: =ROUND(2419161.36/10000,2) -> 241.92 | F7: =ROUND(2254389.78/10000,2) -> 225.44 | G7: =ROUND(2588053.93/10000,2) -> 258.81 | H7: =G7 -> 258.81 | I7: =H7 -> 258.81 | J7: =I7 -> 258.81 | K7: =J7 -> 258.81 | L7: =K7 -> 258.81
B8: 利息支出 | E8: =ROUND(39035980.82/10000,2) -> 3903.6 | F8: =ROUND(44910429.17/10000,2) -> 4491.04 | G8: =3204.46-258.81 -> 2945.65
B9: 合计 | C9: =SUM(C7:C8) -> 3298242.6 | D9: =SUM(D7:D8) -> 5484942 | E9: =SUM(E7:E8) -> 4145.52 | F9: =SUM(F7:F8) -> 4716.48 | G9: =3204.46 -> 3204.46
H11: =H9/0.055 -> 0
H12: =50000*0.055 -> 2750
H13: =400/0.05 -> 8000

Sheet 项目投资情况表
B3: 主体工程建设
B5: A | C5: 序号 | D5: 建筑物名称 | E5: 规模 | F5: 占地面积 | G5: 备注
C6: 1 | D6: 污水处理土建三期 | E6: 10000m3/d | F6: 7.125 | G6: 土地划拨
C7: 2 | D7: 污水处理土建四期 | E7: 10000m3/d | F7: 7.125 | G7: 土地划拨
C15: 合 计 | F15: =SUM(F6:F14) -> 14.25 | G15: =SUM(G6:G14) -> 0
C18: 设备投放计划
C19: 设备投放计划 | D19: 投放期间 | E19: 设备投放数量 | F19: 比例 | G19: 投资额
C20: 三期100% | D20: 2019年 | E20: =[36]主要设备生产情况!C6*[36]项目投资情况表!F20 -> 0 | F20: 1 | G20: 837.5
C21: 四期100% | D21: 2022年 | E21: =[36]主要设备生产情况!C6*[36]项目投资情况表!F21 -> 0 | F21: 1 | G21: 837.5
C23: 合计 | E23: =SUM(E20:E22) -> 0 | F23: =SUM(F20:F22) -> 2 | G23: =SUM(G20:G22) -> 1675

Sheet 利息测算
A1: 融资项目 | B1: 会计科目 | C1: 公司名称 | D1: 融资银行 | E1: 担保方式 | F1: 融资金额 | G1: 年利率/贴现率 | H1: 起息日 | I1: 到期日 | J1: 保证金 | K1: 票据号码 | L1: 备注 | O1: 利息
A2: 借款 | B2: 短期借款 | C2: 杰之行 | D2: 包商银行文化支行 | E2: 担保 | F2: 25000000 | G2: 0.0616 | M2: 预计 | N2: 一年期 | O2: =F2*$G$2 -> 1540000
A3: 借款 | B3: 短期借款 | C3: 杰之行 | D3: 包商银行文化支行 | E3: 担保 | F3: 25000000 | M3: 预计 | N3: 一年期 | O3: =F3*$G$2 -> 1540000
A4: 借款 | B4: 短期借款 | C4: 杰之行 | D4: 包商银行文化支行 | E4: 担保 | F4: 25000000 | M4: 预计 | N4: 一年期 | O4: =F4*$G$2 -> 1540000
A5: 借款 | B5: 短期借款 | C5: 杰之行 | D5: 包商银行文化支行 | E5: 担保 | F5: 25000000 | M5: 预计 | N5: 一年期 | O5: =F5*$G$2 -> 1540000
A6: 借款 | B6: 短期借款 | C6: 杰之行 | D6: 包商银行文化支行 | E6: 担保 | F6: 20000000 | M6: 预计 | N6: 一年期 | O6: =F6*$G$2 -> 1232000
A7: 借款 | B7: 短期借款 | C7: 杰之行 | D7: 包商银行文化支行 | E7: 担保 | F7: 20000000 | M7: 预计 | N7: 一年期 | O7: =F7*$G$2 -> 1232000
A8: 借款 | B8: 短期借款 | C8: 杰之行 | D8: 包商银行文化支行 | E8: 担保 | F8: 10000000 | M8: 预计 | N8: 一年期 | O8: =F8*$G$2 -> 616000
A9: 借款 | B9: 短期借款 | C9: 杰之行 | D9: 华夏银行 | E9: 担保 | F9: 30000000 | G9: =4.35%*1.5 -> 0.06525 | M9: 预计 | N9: 一年期 | O9: =F9*G9 -> 1957500
A10: 借款 | B10: 短期借款 | C10: 杰之行 | D10: 浙商银行 | E10: 抵押 | F10: 60000000 | G10: =G11 -> 0.0544 | M10: 预计 | N10: 一年期 | O10: =F10*G10 -> 3264000
A11: 借款 | B11: 短期借款 | C11: 杰之行 | D11: 招行硚口支行 | E11: 担保+抵押 | F11: 50000000 | G11: 0.0544 | M11: 预计 | N11: 一年期 | O11: =F11*G11 -> 2720000
A12: 借款 | B12: 短期借款 | C12: 杰之行 | D12: 招行硚口支行 | E12: 担保+抵押 | F12: 20000000 | G12: 0.0435 | H12: 43137 | I12: 43502 | O12: =F12*G12/360*324 -> 783000
A13: 借款 | B13: 短期借款 | C13: 杰之行 | D13: 招行硚口支行 | E13: 担保+抵押 | F13: 5000000 | G13: 0.0522 | H13: 43154 | I13: 43518 | O13: =F13*G13/360*307 -> 222575
A14: 借款 | B14: 短期借款 | C14: 杰之行 | D14: 招行硚口支行 | E14: 担保+抵押 | F14: 14000000 | G14: =4.35%*1.31 -> 0.056985 | H14: 43159 | I14: 43524 | O14: =F14*G14/360*300 -> 664825
A15: 借款 | B15: 短期借款 | C15: 杰之行 | D15: 招行硚口支行 | E15: 担保+抵押 | F15: 11000000 | G15: =4.35%*1.8 -> 0.0783 | H15: 43175 | I15: 43539 | O15: =F15*G15/360*285 -> 681862.5
A16: 借款 | B16: 短期借款 | C16: 杰之行 | D16: 民生银行武汉分行 | E16: 担保 | F16: 39999999 | G16: 0.0566 | M16: 预计 | N16: 一年期 | O16: =F16*G16 -> 2263999.9
A17: 票据 | B17: 应付票据 | C17: 杰之行 | D17: 华夏银行 | E17: 1 | F17: 30000000 | J17: 30000000 | M17: 预计 | O17: =F17*G17 -> 0
O20: =SUM(O2:O17) -> 21797762
O21: =165*12 -> 1980
F22: =SUBTOTAL(9,F2:F20) -> 409999999 | J22: =SUBTOTAL(9,J2:J17) -> 30000000 | K22: =F22-J22 -> 379999999 | O22: =O21*1.1 -> 2178
S75: 6494526

Sheet 成本--构成分析
A1: 生产成本明细表
A2: 项目 | B2: 2015年 | C2: 2016年 | D2: 2017年
A3: 一、生产成本总计 | B3: =B4+B7 -> 2418428.9 | C3: =C4+C7 -> 8839205.2 | D3: =D4+D7 -> 9843943.6 | I3: 剔除17年平均值
A4: 1、变动成本合计 | B4: =SUM(B5:B6) -> 1918734 | C4: =SUM(C5:C6) -> 7495734.2 | D4: =SUM(D5:D6) -> 5598972.5 | F4: =SUM(B5:B6) -> 1918734 | G4: =SUM(C5:C6) -> 7495734.2 | H4: =SUM(D5:D6) -> 5598972.5 | I4: 变动成本
A5: 1-1 基本材料 | B5: 1690390 | C5: 6760221.1 | D5: 4747712 | F5: =F4/B3 -> 0.79338037 | G5: =G4/C3 -> 0.84800997 | H5: =H4/D3 -> 0.56877332 | I5: =(F5+G5)/2 -> 0.82069517
A6: 1-2 基本人工 | B6: 228344 | C6: 735513.04 | D6: 851260.49
A7: 2、固定成本合计 | B7: =SUM(B8:B10) -> 499694.88 | C7: =SUM(C8:C10) -> 1343471 | D7: =SUM(D8:D10) -> 4244971.1 | F7: =SUM(B8:B10) -> 499694.88 | G7: =SUM(C8:C10) -> 1343471 | H7: =SUM(D8:D10) -> 4244971.1 | I7: 固定成本
A8: 2-1 基本折旧 | B8: 182684.58 | C8: 506832.65 | D8: 1262869.2 | F8: =F7/B3 -> 0.20661963 | G8: =G7/C3 -> 0.15199003 | H8: =H7/D3 -> 0.43122668 | I8: =(F8+G8)/2 -> 0.17930483
A9: 2-2 基本电费 | C9: 9802.32 | D9: 3523.64
A10: 2-3 基本制造费用 | B10: 317010.3 | C10: 826836.06 | D10: 2978578.3
A11: 其中：工资 | B11: 87087 | C11: 176361 | D11: 1415385
A12: 折旧 | B12: 13501.84 | C12: 20729.76 | D12: 420726.38
A13: 物料消耗 | B13: 24299.33 | C13: 65379.04 | D13: 166451.73
A14: 租赁费 | B14: 172694.72 | C14: 492413.34 | D14: 894589.83
A15: 电费 | B15: 19427.41 | C15: 20670.87 | D15: 81425.34
A16: 营业收入 | B16: 2935047.1 | C16: 10473622 | D16: 3114175.7

Sheet 成本预测表
E1: 成本预测表
B3: 项目内容 | C3: 2018年 | D3: 2019年 | E3: 2020年 | F3: 2021年 | G3: 2022年 | H3: 2023年及以后
B4: 收入情况表 | C4: =收入预测表!C9 -> 2751.17 | D4: =收入预测表!D9 -> 3301.404 | E4: =收入预测表!E9 -> 3895.6567 | F4: =收入预测表!F9 -> 4480.0052 | G4: =收入预测表!G9 -> 4928.0058 | H4: =收入预测表!H9 -> 4928.0058
B5: 总成本 | C5: =SUM(C6:C7) -> 2279.7316 | D5: =SUM(D6:D7) -> 2610.4137 | E5: =SUM(E6:E7) -> 2967.1129 | F5: =SUM(F6:F7) -> 3318.8878 | G5: =SUM(G6:G7) -> 3593.1362 | H5: =SUM(H6:H7) -> 3593.1362 | I5: ='成本--成本比例分析'!G29 -> 0.7
B6: 其中：变动成本 | C6: =C4*$I$5*$I$6 -> 1580.5104 | D6: =D4*$I$5*$I$6 -> 1896.6124 | E6: =E4*$I$5*$I$6 -> 2238.0027 | F6: =F4*$I$5*$I$6 -> 2573.7031 | G6: =G4*$I$5*$I$6 -> 2831.0734 | H6: =H4*$I$5*$I$6 -> 2831.0734 | I6: ='成本--构成分析'!I5 -> 0.82069517
B7: 固定成本 | C7: =SUM(C8:C10) -> 699.22125 | D7: =SUM(D8:D10) -> 713.80125 | E7: =SUM(E8:E10) -> 729.11025 | F7: =SUM(F8:F10) -> 745.1847 | G7: =SUM(G8:G10) -> 762.06287 | H7: =SUM(H8:H10) -> 762.06287 | J7: 预测期内产能尚有足够的空间，因此固定成本在预测期内保持不变
B8: 其中：折旧费 | C8: =折旧和资本化支出!D56 -> 137.74125 | D8: =折旧和资本化支出!E56 -> 137.74125 | E8: =折旧和资本化支出!F56 -> 137.74125 | F8: =折旧和资本化支出!G56 -> 137.74125 | G8: =折旧和资本化支出!H56 -> 137.74125 | H8: =折旧和资本化支出!I56 -> 137.74125
B9: 人员工资 | C9: =人员费用表!B21 -> 291.6 | D9: =人员费用表!C21 -> 306.18 | E9: =人员费用表!D21 -> 321.489 | F9: =人员费用表!E21 -> 337.56345 | G9: =人员费用表!F21 -> 354.44162 | H9: =人员费用表!G21 -> 354.44162
B10: 租赁费 | C10: =22.49*12 -> 269.88 | D10: =22.49*12 -> 269.88 | E10: =22.49*12 -> 269.88 | F10: =22.49*12 -> 269.88 | G10: =22.49*12 -> 269.88 | H10: =22.49*12 -> 269.88 | I10: 租赁费224948.52元*12月
B11: 总成本占主营业务收入比列 | C11: =C5/C4 -> 0.82864076 | D11: =D5/D4 -> 0.79069804 | E11: =E5/E4 -> 0.7616464 | F11: =F5/F4 -> 0.7408223 | G11: =G5/G4 -> 0.72912582 | H11: =H5/H4 -> 0.72912582
C13: =1-C11 -> 0.17135924 | D13: =1-D11 -> 0.20930196 | E13: =1-E11 -> 0.2383536 | F13: =1-F11 -> 0.2591777 | G13: =1-G11 -> 0.27087418 | H13: =1-H11 -> 0.27087418
C15: =C4*70% -> 1925.819

Sheet 税金及附加预测表
A2: 营业税金及附加申报表-预测表
I3: 表11
A4: =封面!B2 -> 被评估单位：福建卫东新能源股份有限公司 | D4: =-2708268.12/10000 -> -270.82681 | E4: =D7+D4-D8 -> -138.34868 | I4: 单位：万元
A5: 序号 | B5: 项目 | C5: 税率 | D5: 预测年度
D6: 2018年 | E6: 2019年 | F6: 2020年 | G6: 2021年 | H6: 2022年 | I6: 2023年及之后
A7: 1 | B7: 增值税销项 | C7: 0.17 | D7: =收入预测表!C9*税金及附加预测表!$C$7 -> 467.6989 | E7: =收入预测表!D9*税金及附加预测表!$C$7 -> 561.23868 | F7: =收入预测表!E9*税金及附加预测表!$C$7 -> 662.26164 | G7: =收入预测表!F9*税金及附加预测表!$C$7 -> 761.60089 | H7: =收入预测表!G9*税金及附加预测表!$C$7 -> 837.76098 | I7: =收入预测表!H9*税金及附加预测表!$C$7 -> 837.76098
B8: 增值税进项 | D8: =D36 -> 335.22077 | E8: =E36 -> 389.12319 | F8: =F36 -> 447.33781 | G8: =G36 -> 504.58218 | H8: =H36 -> 548.46953 | I8: =I36 -> 548.46953
B9: 应交增值税 | D9: 0 | E9: =E7-E8+E4 -> 33.766808 | F9: =F7-F8 -> 214.92384 | G9: =G7-G8 -> 257.01871 | H9: =H7-H8 -> 289.29145 | I9: =I7-I8 -> 289.29145
A10: 2 | B10: 营业税
A11: 3 | B11: 资源税
A12: 4 | B12: 城建税 | C12: 0.07 | D12: =D$9*$C12 -> 0 | E12: =E9*$C$12 -> 2.3636765 | F12: =F9*$C$12 -> 15.044668 | G12: =G9*$C$12 -> 17.99131 | H12: =H9*$C$12 -> 20.250401 | I12: =I9*$C$12 -> 20.250401
A13: 5 | B13: 教育费附加 | C13: 0.03 | D13: =D$9*$C13 -> 0 | E13: =E$9*$C13 -> 1.0130042 | F13: =F$9*$C13 -> 6.4477151 | G13: =G$9*$C13 -> 7.7105613 | H13: =H$9*$C13 -> 8.6787434 | I13: =I$9*$C13 -> 8.6787434
A14: 6 | B14: 地方教育附加 | C14: 0.02 | D14: =D$9*$C14 -> 0 | E14: =E$9*$C14 -> 0.67533616 | F14: =F$9*$C14 -> 4.2984767 | G14: =G$9*$C14 -> 5.1403742 | H14: =H$9*$C14 -> 5.7858289 | I14: =I$9*$C14 -> 5.7858289
A15: 7 | B15: 个人所得税
B16: 水利建设基金
B17: 印花税 | C17: 0.0003 | D17: =收入预测表!C9*税金及附加预测表!$C$17 -> 0.825351 | E17: =收入预测表!D9*税金及附加预测表!$C$17 -> 0.9904212 | F17: =收入预测表!E9*税金及附加预测表!$C$17 -> 1.168697 | G17: =收入预测表!F9*税金及附加预测表!$C$17 -> 1.3440016 | H17: =收入预测表!G9*税金及附加预测表!$C$17 -> 1.4784017 | I17: =收入预测表!H9*税金及附加预测表!$C$17 -> 1.4784017
B18: 车船税
B19: 城镇土地使用税
B20: 房产税
B21: 耕地占用税
B22: 车船税
A23: 8 | B23: 主营业务税金及附加 | D23: =D12+D13+D14+D17 -> 0.825351 | E23: =E12+E13+E14+E17 -> 5.0424381 | F23: =F12+F13+F14+F17 -> 26.959557 | G23: =G12+G13+G14+G17 -> 32.186247 | H23: =H12+H13+H14+H17 -> 36.193375 | I23: =I12+I13+I14+I17 -> 36.193375
B26: 增值税的进项抵扣项
B27: 进项内容 | C27: 项目 | D27: 2018年 | E27: 2019年 | F27: 2020年 | G27: 2021年 | H27: 2022年 | I27: 2023年及之后
B28: 变动成本 | C28: 基数 | D28: =成本预测表!C6 -> 1580.5104 | E28: =成本预测表!D6 -> 1896.6124 | F28: =成本预测表!E6 -> 2238.0027 | G28: =成本预测表!F6 -> 2573.7031 | H28: =成本预测表!G6 -> 2831.0734 | I28: =成本预测表!H6 -> 2831.0734
C29: 0.17 | D29: =D28*$C$29 -> 268.68676 | E29: =E28*$C$29 -> 322.42411 | F29: =F28*$C$29 -> 380.46045 | G29: =G28*$C$29 -> 437.52952 | H29: =H28*$C$29 -> 481.28247 | I29: =I28*$C$29 -> 481.28247
B30: 租赁费 | C30: 基数 | D30: =成本预测表!C10 -> 269.88 | E30: =成本预测表!D10 -> 269.88 | F30: =成本预测表!E10 -> 269.88 | G30: =成本预测表!F10 -> 269.88 | H30: =成本预测表!G10 -> 269.88 | I30: =成本预测表!H10 -> 269.88
C31: 0.11 | D31: =D30*$C$31 -> 29.6868 | E31: =E30*$C$31 -> 29.6868 | F31: =F30*$C$31 -> 29.6868 | G31: =G30*$C$31 -> 29.6868 | H31: =H30*$C$31 -> 29.6868 | I31: =I30*$C$31 -> 29.6868
B32: 宣传费用 | C32: 基数 | D32: =销售费用!O9 -> 13.75585 | E32: =销售费用!P9 -> 16.50702 | F32: =销售费用!Q9 -> 19.478284 | G32: =销售费用!R9 -> 22.400026 | H32: =销售费用!S9 -> 24.640029 | I32: =销售费用!T9 -> 24.640029
C33: 0.06 | D33: =D32*$C$33 -> 0.825351 | E33: =E32*$C$33 -> 0.9904212 | F33: =F32*$C$33 -> 1.168697 | G33: =G32*$C$33 -> 1.3440016 | H33: =H32*$C$33 -> 1.4784017 | I33: =I32*$C$33 -> 1.4784017
B34: 资本性支出 | C34: 基数 | D34: =折旧和资本化支出!D60 -> 211.89328 | E34: =折旧和资本化支出!E60 -> 211.89328 | F34: =折旧和资本化支出!F60 -> 211.89328 | G34: =折旧和资本化支出!G60 -> 211.89328 | H34: =折旧和资本化支出!H60 -> 211.89328 | I34: =折旧和资本化支出!I60 -> 211.89328
C35: 0.17 | D35: =D34*$C$35 -> 36.021858 | E35: =E34*$C$35 -> 36.021858 | F35: =F34*$C$35 -> 36.021858 | G35: =G34*$C$35 -> 36.021858 | H35: =H34*$C$35 -> 36.021858 | I35: =I34*$C$35 -> 36.021858
B36: 合计 | D36: =D29+D31+D33+D35 -> 335.22077 | E36: =E29+E31+E33+E35 -> 389.12319 | F36: =F29+F31+F33+F35 -> 447.33781 | G36: =G29+G31+G33+G35 -> 504.58218 | H36: =H29+H31+H33+H35 -> 548.46953 | I36: =I29+I31+I33+I35 -> 548.46953

Sheet 工资表
A1: 福建卫东新能源股份有限公司工资汇总表 2017年12月
A2: 部门 | B2: 人数 | C2: 应发小计 | D2: 已发 | E2: 应发合计 | F2: 养老保险 | G2: 医疗保险 | H2: 个所税 | I2: 住宿费 | J2: 水费 | K2: 电费 | L2: 其它 | M2: 代扣合计 | N2: 实发工资 | O2: 平均工资
A3: 高管 | B3: 5 | C3: =VLOOKUP(A3,'[37]2017年12月份'!B:N,13,FALSE) -> 35000 | D3: 0 | E3: =C3+D3 -> 35000 | F3: =VLOOKUP(A3,'[37]2017年12月份'!B:O,14,FALSE) -> 561 | G3: =VLOOKUP(A3,'[37]2017年12月份'!B:P,15,FALSE) -> 177.96 | H3: =VLOOKUP(A3,'[37]2017年12月份'!B:R,17,FALSE) -> 1151.11 | I3: =VLOOKUP(A3,'[37]2017年12月份'!B:S,18,FALSE) -> 0 | J3: =VLOOKUP(A3,'[37]2017年12月份'!B:T,19,FALSE) -> 0 | K3: =VLOOKUP(A3,'[37]2017年12月份'!B:U,20,FALSE) -> 0 | L3: =VLOOKUP(A3,'[37]2017年12月份'!B:V,21,FALSE) -> 0 | M3: =SUM(F3:L3) -> 1890.07 | N3: =VLOOKUP(A3,'[37]2017年12月份'!B2:Y132,23,FALSE) -> 33109.93 | O3: =E3/B3 -> 7000
A4: 综合部 | B4: 3 | C4: =IF(ISERROR(VLOOKUP(A4,'[37]2017年12月份'!B:N,13,FALSE)),0,VLOOKUP(A4,'[37]2017年12月份'!B:N,13,FALSE)) -> 12500 | D4: 0 | E4: =C4+D4 -> 12500 | F4: =IF(ISERROR(VLOOKUP(A4,'[37]2017年12月份'!B:V,14,FALSE)),0,VLOOKUP(A4,'[37]2017年12月份'!B:V,14,FALSE)) -> 0 | G4: =IF(ISERROR(VLOOKUP(A4,'[37]2017年12月份'!B:V,15,FALSE)),0,VLOOKUP(A4,'[37]2017年12月份'!B:V,15,FALSE)) -> 0 | H4: =IF(ISERROR(VLOOKUP(A4,'[37]2017年12月份'!B:V,17,FALSE)),0,VLOOKUP(A4,'[37]2017年12月份'!B:V,17,FALSE)) -> 60 | I4: =IF(ISERROR(VLOOKUP(A4,'[37]2017年12月份'!B:V,18,FALSE)),0,VLOOKUP(A4,'[37]2017年12月份'!B:V,18,FALSE)) -> 0 | J4: =IF(ISERROR(VLOOKUP(A4,'[37]2017年12月份'!B:V,19,FALSE)),0,VLOOKUP(A4,'[37]2017年12月份'!B:V,19,FALSE)) -> 0 | K4: =IF(ISERROR(VLOOKUP(A4,'[37]2017年12月份'!B:V,20,FALSE)),0,VLOOKUP(A4,'[37]2017年12月份'!B:V,20,FALSE)) -> 0 | L4: =IF(ISERROR(VLOOKUP(A4,'[37]2017年12月份'!B:V,21,FALSE)),0,VLOOKUP(A4,'[37]2017年12月份'!B:V,21,FALSE)) -> 0 | M4: =SUM(F4:L4) -> 60 | N4: =E4-M4 -> 12440 | O4: =E4/B4 -> 4166.6667
A5: 行政人事部 | B5: 7 | C5: =VLOOKUP(A5,'[37]2017年12月份'!B:N,13,FALSE) -> 20323 | D5: 0 | E5: =C5+D5 -> 20323 | F5: =VLOOKUP(A5,'[37]2017年12月份'!B:O,14,FALSE) -> 756.5 | G5: =VLOOKUP(A5,'[37]2017年12月份'!B:P,15,FALSE) -> 296.6 | H5: =VLOOKUP(A5,'[37]2017年12月份'!B:R,17,FALSE) -> 23.89 | I5: =VLOOKUP(A5,'[37]2017年12月份'!B:S,18,FALSE) -> 5 | J5: =VLOOKUP(A5,'[37]2017年12月份'!B:T,19,FALSE) -> 0.68 | K5: =VLOOKUP(A5,'[37]2017年12月份'!B:U,20,FALSE) -> 9.77 | L5: =VLOOKUP(A5,'[37]2017年12月份'!B:V,21,FALSE) -> 0 | M5: =SUM(F5:L5) -> 1092.44 | N5: =VLOOKUP(A5,'[37]2017年12月份'!B2:Y133,23,FALSE) -> 19230.56 | O5: =E5/B5 -> 2903.2857
A6: 总工办 | B6: 2 | C6: =VLOOKUP(A6,'[37]2017年12月份'!B:N,13,FALSE) -> 7700 | D6: 0 | E6: =C6+D6 -> 7700 | F6: =VLOOKUP(A6,'[37]2017年12月份'!B:O,14,FALSE) -> 312.8 | G6: =VLOOKUP(A6,'[37]2017年12月份'!B:P,15,FALSE) -> 118.64 | H6: =VLOOKUP(A6,'[37]2017年12月份'!B:R,17,FALSE) -> 62.92 | I6: =VLOOKUP(A6,'[37]2017年12月份'!B:S,18,FALSE) -> 10 | J6: =VLOOKUP(A6,'[37]2017年12月份'!B:T,19,FALSE) -> 0 | K6: =VLOOKUP(A6,'[37]2017年12月份'!B:U,20,FALSE) -> 0 | L6: =VLOOKUP(A6,'[37]2017年12月份'!B:V,21,FALSE) -> 0 | M6: =SUM(F6:L6) -> 504.36 | N6: =VLOOKUP(A6,'[37]2017年12月份'!B3:Y133,23,FALSE) -> 7195.64 | O6: =E6/B6 -> 3850
A7: 小计 | B7: =SUM(B3:B6) -> 17 | C7: =SUM(C3:C6) -> 75523 | D7: =SUM(D3:D6) -> 0 | E7: =SUM(E3:E6) -> 75523 | O7: =E7/B7 -> 4442.5294 | P7: 4500
A8: 市场营销部 | B8: 3 | C8: =VLOOKUP(A8,'[37]2017年12月份'!B:N,13,FALSE) -> 6756 | D8: 0 | E8: =C8+D8 -> 6756 | F8: =VLOOKUP(A8,'[37]2017年12月份'!B:O,14,FALSE) -> 151.3 | G8: =VLOOKUP(A8,'[37]2017年12月份'!B:P,15,FALSE) -> 59.32 | H8: =VLOOKUP(A8,'[37]2017年12月份'!B:R,17,FALSE) -> 0 | I8: =VLOOKUP(A8,'[37]2017年12月份'!B:S,18,FALSE) -> 5 | J8: =VLOOKUP(A8,'[37]2017年12月份'!B:T,19,FALSE) -> 0 | K8: =VLOOKUP(A8,'[37]2017年12月份'!B:U,20,FALSE) -> 0 | L8: =VLOOKUP(A8,'[37]2017年12月份'!B:V,21,FALSE) -> 0 | M8: =SUM(F8:L8) -> 215.62 | N8: =VLOOKUP(A8,'[37]2017年12月份'!B2:Y133,23,FALSE) -> 6540.38 | O8: =E8/B8 -> 2252
A9: 采购部 | B9: 3 | C9: =VLOOKUP(A9,'[37]2017年12月份'!B:N,13,FALSE) -> 8327 | D9: 0 | E9: =C9+D9 -> 8327 | F9: =VLOOKUP(A9,'[37]2017年12月份'!B:O,14,FALSE) -> 464.1 | G9: =VLOOKUP(A9,'[37]2017年12月份'!B:P,15,FALSE) -> 177.96 | H9: =VLOOKUP(A9,'[37]2017年12月份'!B:R,17,FALSE) -> 0 | I9: =VLOOKUP(A9,'[37]2017年12月份'!B:S,18,FALSE) -> 70 | J9: =VLOOKUP(A9,'[37]2017年12月份'!B:T,19,FALSE) -> 0.23 | K9: =VLOOKUP(A9,'[37]2017年12月份'!B:U,20,FALSE) -> 3.58 | L9: =VLOOKUP(A9,'[37]2017年12月份'!B:V,21,FALSE) -> 0 | M9: =SUM(F9:L9) -> 715.87 | N9: =VLOOKUP(A9,'[37]2017年12月份'!B9:Y139,23,FALSE) -> 7611.13 | O9: =E9/B9 -> 2775.6667
A10: 小计 | B10: =SUM(B8:B9) -> 6 | E10: =SUM(E8:E9) -> 15083 | O10: =E10/B10 -> 2513.8333 | P10: 2500
A11: 质量部 | B11: 9 | C11: =VLOOKUP(A11,'[37]2017年12月份'!B:N,13,FALSE) -> 25645 | D11: 0 | E11: =C11+D11 -> 25645 | F11: =VLOOKUP(A11,'[37]2017年12月份'!B:O,14,FALSE) -> 1220.6 | G11: =VLOOKUP(A11,'[37]2017年12月份'!B:P,15,FALSE) -> 474.56 | H11: =VLOOKUP(A11,'[37]2017年12月份'!B:R,17,FALSE) -> 400.84 | I11: =VLOOKUP(A11,'[37]2017年12月份'!B:S,18,FALSE) -> 105 | J11: =VLOOKUP(A11,'[37]2017年12月份'!B:T,19,FALSE) -> 5.1 | K11: =VLOOKUP(A11,'[37]2017年12月份'!B:U,20,FALSE) -> 56.12 | L11: =VLOOKUP(A11,'[37]2017年12月份'!B:V,21,FALSE) -> 78 | M11: =SUM(F11:L11) -> 2340.22 | N11: =VLOOKUP(A11,'[37]2017年12月份'!B3:Y135,23,FALSE) -> 23304.78 | O11: =E11/B11 -> 2849.4444
A12: 技术中心 | B12: 22 | C12: =VLOOKUP(A12,'[37]2017年12月份'!B:N,13,FALSE) -> 87234 | D12: 0 | E12: =C12+D12 -> 87234 | F12: =VLOOKUP(A12,'[37]2017年12月份'!B:O,14,FALSE) -> 2441.2 | G12: =VLOOKUP(A12,'[37]2017年12月份'!B:P,15,FALSE) -> 949.12 | H12: =VLOOKUP(A12,'[37]2017年12月份'!B:R,17,FALSE) -> 846.88 | I12: =VLOOKUP(A12,'[37]2017年12月份'!B:S,18,FALSE) -> 463.33 | J12: =VLOOKUP(A12,'[37]2017年12月份'!B:T,19,FALSE) -> 36.99 | K12: =VLOOKUP(A12,'[37]2017年12月份'!B:U,20,FALSE) -> 363.06 | L12: =VLOOKUP(A12,'[37]2017年12月份'!B:V,21,FALSE) -> 182 | M12: =SUM(F12:L12) -> 5282.58 | N12: =VLOOKUP(A12,'[37]2017年12月份'!B4:Y135,23,FALSE) -> 81951.42 | O12: =E12/B12 -> 3965.1818
A13: 设备工程部 | B13: 7 | C13: =VLOOKUP(A13,'[37]2017年12月份'!B:N,13,FALSE) -> 29428 | D13: 0 | E13: =C13+D13 -> 29428 | F13: =VLOOKUP(A13,'[37]2017年12月份'!B:O,14,FALSE) -> 918 | G13: =VLOOKUP(A13,'[37]2017年12月份'!B:P,15,FALSE) -> 355.92 | H13: =VLOOKUP(A13,'[37]2017年12月份'!B:R,17,FALSE) -> 486.6 | I13: =VLOOKUP(A13,'[37]2017年12月份'!B:S,18,FALSE) -> 240 | J13: =VLOOKUP(A13,'[37]2017年12月份'!B:T,19,FALSE) -> 12.45 | K13: =VLOOKUP(A13,'[37]2017年12月份'!B:U,20,FALSE) -> 116.31 | L13: =VLOOKUP(A13,'[37]2017年12月份'!B:V,21,FALSE) -> 275 | M13: =SUM(F13:L13) -> 2404.28 | N13: =VLOOKUP(A13,'[37]2017年12月份'!B5:Y136,23,FALSE) -> 27023.72 | O13: =E13/B13 -> 4204
A14: 生产部 | B14: 43 | C14: =VLOOKUP(A14,'[37]2017年12月份'!B:N,13,FALSE) -> 95275 | D14: 0 | E14: =C14+D14 -> 95275 | F14: =VLOOKUP(A14,'[37]2017年12月份'!B:O,14,FALSE) -> 5910.9 | G14: =VLOOKUP(A14,'[37]2017年12月份'!B:P,15,FALSE) -> 2313.48 | H14: =VLOOKUP(A14,'[37]2017年12月份'!B:R,17,FALSE) -> 439.28 | I14: =VLOOKUP(A14,'[37]2017年12月份'!B:S,18,FALSE) -> 310 | J14: =VLOOKUP(A14,'[37]2017年12月份'!B:T,19,FALSE) -> 39.24 | K14: =VLOOKUP(A14,'[37]2017年12月份'!B:U,20,FALSE) -> 306.05 | L14: =VLOOKUP(A14,'[37]2017年12月份'!B:V,21,FALSE) -> 234 | M14: =SUM(F14:L14) -> 9552.95 | N14: =VLOOKUP(A14,'[37]2017年12月份'!B7:Y137,23,FALSE) -> 85722.05 | O14: =E14/B14 -> 2215.6977
A15: 小计 | B15: =SUM(B11:B14) -> 81 | E15: =SUM(E11:E14) -> 237582 | O15: =E15/B15 -> 2933.1111 | P15: 3000
A16: 财务部 | B16: 4 | C16: =VLOOKUP(A16,'[37]2017年12月份'!B:N,13,FALSE) -> 13058 | D16: 0 | E16: =C16+D16 -> 13058 | F16: =VLOOKUP(A16,'[37]2017年12月份'!B:O,14,FALSE) -> 615.4 | G16: =VLOOKUP(A16,'[37]2017年12月份'!B:P,15,FALSE) -> 237.28 | H16: =VLOOKUP(A16,'[37]2017年12月份'!B:R,17,FALSE) -> 1.18 | I16: =VLOOKUP(A16,'[37]2017年12月份'!B:S,18,FALSE) -> 50 | J16: =VLOOKUP(A16,'[37]2017年12月份'!B:T,19,FALSE) -> 2.7 | K16: =VLOOKUP(A16,'[37]2017年12月份'!B:U,20,FALSE) -> 24.4 | L16: =VLOOKUP(A16,'[37]2017年12月份'!B:V,21,FALSE) -> 39 | M16: =SUM(F16:L16) -> 969.96 | N16: =VLOOKUP(A16,'[37]2017年12月份'!B8:Y138,23,FALSE) -> 12088.04 | O16: =E16/B16 -> 3264.5 | P16: 3300 | S16: =E17*12 -> 8033208
A17: 合计 | B17: =SUM(B3:B16) -> 212 | C17: =SUM(C3:C16) -> 416769 | D17: =SUM(D3:D16) -> 0 | E17: =SUM(E3:E16) -> 669434 | F17: =SUM(F3:F16) -> 13351.8 | G17: =SUM(G3:G16) -> 5160.84 | H17: =SUM(H3:H16) -> 3472.7 | I17: =SUM(I3:I16) -> 1258.33 | ... N17: =SUM(N3:N16) -> 316217.65 | O17: =E17/B17 -> 3157.7075
B20: 审批： | G20: 审核： | L20: 核算员：滕直黠

Sheet 人员费用表
A1: 人员费用预测
A3: 年度 | B3: 2018年 | C3: 2019年 | D3: 2020年 | E3: 2021年 | F3: 2022年 | G3: 2023年 | H3: 2025年
A4: 职工人数 | B4: =B6+B5+B7+B8 -> 108 | C4: =B4 -> 108 | D4: =C4 -> 108 | E4: =D4 -> 108 | F4: =E4 -> 108 | G4: =F4 -> 108 | H4: =H6+H5+H7+H8 -> #REF!
A5: 管理部门 | B5: =工资表!B3+工资表!B5+工资表!B6+工资表!B4 -> 17 | C5: =B5 -> 17 | D5: =C5 -> 17 | E5: =D5 -> 17 | F5: =E5 -> 17 | G5: =F5 -> 17 | H5: =#REF!+#REF! -> #REF!
A6: 销售部门 | B6: =工资表!B8+工资表!B9 -> 6 | C6: =B6 -> 6 | D6: =C6 -> 6 | E6: =D6 -> 6 | F6: =E6 -> 6 | G6: =F6 -> 6 | H6: =#REF!+#REF!+#REF! -> #REF!
A7: 生产部门 | B7: =工资表!B11++工资表!B12+工资表!B13+工资表!B14 -> 81 | C7: =B7 -> 81 | D7: =C7 -> 81 | E7: =D7 -> 81 | F7: =E7 -> 81 | G7: =F7 -> 81 | H7: =#REF!+#REF! -> #REF!
A8: 财务部 | B8: =工资表!B16 -> 4 | C8: =B8 -> 4 | D8: =C8 -> 4 | E8: =D8 -> 4 | F8: =E8 -> 4 | G8: =F8 -> 4 | H8: =#REF!+#REF!+#REF! -> #REF!
A9: 员工平均薪酬(单位: 元/人*月) | B9: 2018年 | C9: 2019年 | D9: 2020年 | E9: 2021年 | F9: 2022年 | G9: 2023年 | H9: 2025年
A10: 管理部门 | B10: =工资表!P7 -> 4500 | C10: =B10*(1+$I$10) -> 4725 | D10: =C10*(1+$I$10) -> 4961.25 | E10: =D10*(1+$I$10) -> 5209.3125 | F10: =E10*(1+$I$10) -> 5469.7781 | G10: =F10 -> 5469.7781 | H10: =H11+H12+H13 -> #REF! | I10: 0.05 | J10: 薪酬增幅
A11: 销售部门 | B11: =工资表!P10 -> 2500 | C11: =B11*(1+$I$10) -> 2625 | D11: =C11*(1+$I$10) -> 2756.25 | E11: =D11*(1+$I$10) -> 2894.0625 | F11: =E11*(1+$I$10) -> 3038.7656 | G11: =F11 -> 3038.7656 | H11: =#REF!*(1+$I$10) -> #REF!
A12: 生产部门 | B12: =工资表!P15 -> 3000 | C12: =B12*(1+$I$10) -> 3150 | D12: =C12*(1+$I$10) -> 3307.5 | E12: =D12*(1+$I$10) -> 3472.875 | F12: =E12*(1+$I$10) -> 3646.5188 | G12: =F12 -> 3646.5188 | H12: =#REF!*(1+$I$10) -> #REF!
A13: 财务部 | B13: =工资表!P16 -> 3300 | C13: =B13*(1+$I$10) -> 3465 | D13: =C13*(1+$I$10) -> 3638.25 | E13: =D13*(1+$I$10) -> 3820.1625 | F13: =E13*(1+$I$10) -> 4011.1706 | G13: =F13 -> 4011.1706 | H13: =#REF!*(1+$I$10) -> #REF!
A14: 薪酬汇总（金额单位：万元） | B14: =SUM(B15:B18) -> 417.24 | C14: =SUM(C15:C18) -> 438.102 | D14: =SUM(D15:D18) -> 460.0071 | E14: =SUM(E15:E18) -> 483.00745 | F14: =SUM(F15:F18) -> 507.15783 | G14: =SUM(G15:G18) -> 507.15783 | H14: =H15+#REF!+#REF!+#REF! -> #REF!
A15: 管理部门 | B15: =B10*12*B5/10000 -> 91.8 | C15: =C10*12*C5/10000 -> 96.39 | D15: =D10*12*D5/10000 -> 101.2095 | E15: =E10*12*E5/10000 -> 106.26998 | F15: =F10*12*F5/10000 -> 111.58347 | G15: =G10*12*G5/10000 -> 111.58347 | H15: =H16+H17+H18 -> #REF!
A16: 销售部门 | B16: =B11*12*B6/10000 -> 18 | C16: =C11*12*C6/10000 -> 18.9 | D16: =D11*12*D6/10000 -> 19.845 | E16: =E11*12*E6/10000 -> 20.83725 | F16: =F11*12*F6/10000 -> 21.879113 | G16: =G11*12*G6/10000 -> 21.879113 | H16: =#REF!*H11*12/10000 -> #REF!
A17: 生产部门 | B17: =B12*12*B7/10000 -> 291.6 | C17: =C12*12*C7/10000 -> 306.18 | D17: =D12*12*D7/10000 -> 321.489 | E17: =E12*12*E7/10000 -> 337.56345 | F17: =F12*12*F7/10000 -> 354.44162 | G17: =G12*12*G7/10000 -> 354.44162 | H17: =#REF!*H12*12/10000 -> #REF!
A18: 财务部 | B18: =B13*12*B8/10000 -> 15.84 | C18: =C13*12*C8/10000 -> 16.632 | D18: =D13*12*D8/10000 -> 17.4636 | E18: =E13*12*E8/10000 -> 18.33678 | F18: =F13*12*F8/10000 -> 19.253619 | G18: =G13*12*G8/10000 -> 19.253619 | H18: =#REF!*H13*12/10000 -> #REF!
A21: 其中：生产成本 | B21: =B17 -> 291.6 | C21: =C17 -> 306.18 | D21: =D17 -> 321.489 | E21: =E17 -> 337.56345 | F21: =F17 -> 354.44162 | G21: =G17 -> 354.44162 | H21: =#REF! -> #REF!
A22: 管理费用 | B22: =B15+B18 -> 107.64 | C22: =C15+C18 -> 113.022 | D22: =D15+D18 -> 118.6731 | E22: =E15+E18 -> 124.60676 | F22: =F15+F18 -> 130.83709 | G22: =G15+G18 -> 130.83709 | H22: =#REF!+#REF! -> #REF!
A23: 销售费用 | B23: =B16 -> 18 | C23: =C16 -> 18.9 | D23: =D16 -> 19.845 | E23: =E16 -> 20.83725 | F23: =F16 -> 21.879113 | G23: =G16 -> 21.879113 | H23: =H15 -> #REF!
A24: 合计 | B24: =SUM(B21:B23) -> 417.24 | C24: =SUM(C21:C23) -> 438.102 | D24: =SUM(D21:D23) -> 460.0071 | E24: =SUM(E21:E23) -> 483.00745 | F24: =SUM(F21:F23) -> 507.15783 | G24: =SUM(G21:G23) -> 507.15783 | H24: =SUM(H21:H23) -> #REF!

Sheet 销售费用
M1: 索引号：SY-11 | O1: 销售费用预测表
A3: 被评估单位： | J3: 金额单位：人民币元
A4: 序号 | B4: 项目 | C4: 年 | E4: 年 | G4: 年 | I4: 年 | K4: 年 | M4: 交叉索引号 | N4: 备注 | O4: 2018年 | P4: 2019年 | Q4: 2020年 | R4: 2021年 | S4: 2022年 | T4: 2023年 | U4: 标准
C5: 金额 | D5: 年度变动比例（％） | E5: 金额 | F5: 年度变动比例（％） | G5: 金额 | H5: 年度变动比例（％） | I5: 金额 | J5: 年度变动比例（％） | K5: 金额 | L5: 年度变动比例（％） | O5: 金额 | P5: 金额 | Q5: 金额 | R5: 金额 | S5: 金额 | T5: 金额
A7: 1 | B7: 人员费用 | O7: =人员费用表!B23 -> 18 | P7: =人员费用表!C23 -> 18.9 | Q7: =人员费用表!D23 -> 19.845 | R7: =人员费用表!E23 -> 20.83725 | S7: =人员费用表!F23 -> 21.879113 | T7: =人员费用表!G23 -> 21.879113
A8: 2 | B8: 办公、差旅费等 | O8: =人员费用表!B6*$V$8 -> 12 | P8: =人员费用表!C6*$V$8 -> 12 | Q8: =人员费用表!D6*$V$8 -> 12 | R8: =人员费用表!E6*$V$8 -> 12 | S8: =人员费用表!F6*$V$8 -> 12 | T8: =人员费用表!G6*$V$8 -> 12 | U8: 按照人均2万元/年 | V8: 2
A9: 3 | B9: 宣传费 | O9: =收入预测表!C9*销售费用!$V$9 -> 13.75585 | P9: =收入预测表!D9*销售费用!$V$9 -> 16.50702 | Q9: =收入预测表!E9*销售费用!$V$9 -> 19.478284 | R9: =收入预测表!F9*销售费用!$V$9 -> 22.400026 | S9: =收入预测表!G9*销售费用!$V$9 -> 24.640029 | T9: =收入预测表!H9*销售费用!$V$9 -> 24.640029 | U9: 按照年收入的0.5% | V9: 0.005
A10: 4 | B10: 其他费用 | O10: =收入预测表!C9*销售费用!$V$10 -> 5.50234 | P10: =收入预测表!D9*销售费用!$V$10 -> 6.602808 | Q10: =收入预测表!E9*销售费用!$V$10 -> 7.7913134 | R10: =收入预测表!F9*销售费用!$V$10 -> 8.9600105 | S10: =收入预测表!G9*销售费用!$V$10 -> 9.8560115 | T10: =收入预测表!H9*销售费用!$V$10 -> 9.8560115 | U10: 按照年收入的0.2% | V10: 0.002
O11: =收入预测表!C12*销售费用!$V$8 -> 0
O12: =收入预测表!C13*销售费用!$V$8 -> 0
O13: =收入预测表!C14*销售费用!$V$8 -> 0
O14: =收入预测表!C15*销售费用!$V$8 -> 0
B15: 合计 | O15: =SUM(O7:O14) -> 49.25819 | P15: =SUM(P7:P14) -> 54.009828 | Q15: =SUM(Q7:Q14) -> 59.114597 | R15: =SUM(R7:R14) -> 64.197287 | S15: =SUM(S7:S14) -> 68.375153 | T15: =SUM(T7:T14) -> 68.375153
F16: 评估人员：
O17: =O15/收入预测表!C9 -> 0.017904452 | P17: =P15/收入预测表!D9 -> 0.016359654 | Q17: =Q15/收入预测表!E9 -> 0.015174488 | R17: =R15/收入预测表!F9 -> 0.014329735 | S17: =S15/收入预测表!G9 -> 0.013874812 | T17: =T15/收入预测表!H9 -> 0.013874812
S22: 住宅 | T22: 0.3
S23: 商业 、车位
B25: 住宅合同金额 | P25: 预售合同 | R25: 首付款 | T25: 按揭款(2019年预售的可收回按揭)
P26: 比例 | Q26: 金额 | R26: 比例 | S26: 金额 | T26: 比例
B27: 2019年 | O27: 108758.89 | P27: 0.3 | Q27: 32627.666 | R27: 0.3 | S27: 9788.2997
B28: 2020年 | P28: 0.5 | Q28: 54379.443 | R28: 0.3 | S28: 16313.833 | T28: 0.7
B29: 2021年 | P29: 0.2 | Q29: 21751.777 | R29: 0.3 | S29: 6525.5331 | T29: 0.3
B30: 2022年
B31: 2023年
B32: 商业、车位合同金额 | P32: 预售合同 | R32: 首付款 | T32: 按揭款(2021年预售的可收回按揭)
P33: 比例 | Q33: 金额 | R33: 比例 | S33: 金额 | T33: 比例
B34: 2021年 | O34: 43968.005 | P34: 0.6 | Q34: 26380.803 | R34: 0.5 | S34: 13190.401 | T34: 0.5
B35: 2022年 | P35: 0.3 | Q35: 13190.401 | R35: 0.5 | S35: 6595.2007 | T35: 0.5
B36: 2023年 | P36: 0.1 | Q36: 4396.8005 | R36: 0.5 | S36: 2198.4002
B37: 2024年
O39: =O27+O34 -> 152726.89

Sheet 折旧和资本化支出
A1: 固定资产评估汇总表
A2: 评估基准日：2017年12月31日
A3: 编号 | B3: 科目名称 | C3: 帐面价值 | E3: 购买日期 | F3: 年折旧额
C4: 原值 | D4: 净值
B5: 设备类合计
B6: 自用的投资性房地产
A7: 4-6-1 | B7: 固定资产-房屋建筑物 | F7: =C7/G7 -> 0 | G7: 20
A8: 4-6-4 | B8: 固定资产-机器设备 | C8: 1565.07 | D8: 1101.93 | E8: 2015 | F8: =D8/G8 -> 137.74125 | G8: 8
A9: 4-6-5 | B9: 固定资产-车辆 | C9: 75.4075 | D9: 65.1396 | F9: =D9/G9 -> 6.51396 | G9: 10 | H9: =D9/G9 -> 6.51396
A10: 4-6-6 | B10: 固定资产-电子设备 | C10: 27.055 | D10: 8.781 | F10: =D10/G10 -> 2.927 | G10: 3 | H10: =D10/G10 -> 2.927
B11: 固定资产合计 | C11: =SUM(C7:C10) -> 1667.5325 | D11: =SUM(D7:D10) -> 1175.8506
A15: A1—折旧
C16: 项目\预测期 | D16: 2018年 | E16: 2019年 | F16: 2020年 | G16: 2021年 | H16: 2022年 | I16: 2023年
B18: 折旧 | C18: 机器设备
C19: 期初余额 | D19: =D8 -> 1101.93 | E19: =D23 -> 1101.93 | F19: =E23 -> 1101.93 | G19: =F23 -> 1101.93 | H19: =G23 -> 1101.93 | I19: =H23 -> 1101.93
C20: 本期新增 | D20: =D22 -> 137.74125 | E20: =E22 -> 137.74125 | F20: =F22 -> 137.74125 | G20: =G22 -> 137.74125 | H20: =H22 -> 137.74125 | I20: =I22 -> 137.74125
C22: 本期折旧 | D22: =F8 -> 137.74125 | E22: =D22 -> 137.74125 | F22: =E22 -> 137.74125 | G22: =F22 -> 137.74125 | H22: =G22 -> 137.74125 | I22: =H22 -> 137.74125
C23: 期末余额 | D23: =D19+D20-D22 -> 1101.93 | E23: =E19+E20-E22 -> 1101.93 | F23: =F19+F20-F22 -> 1101.93 | G23: =G19+G20-G22 -> 1101.93 | H23: =H19+H20-H22 -> 1101.93 | I23: =I19+I20-I22 -> 1101.93
B24: 机器设备
C25: 期初余额 | E25: =D29 -> 0 | F25: =E29 -> 0 | G25: =F29 -> 0 | H25: =G29 -> 0 | I25: =H29 -> 0
C26: 本期新增 | E26: =E28 -> 0 | F26: =F28 -> 0 | G26: =G28 -> 0 | H26: =H28 -> 0 | I26: =I28 -> 0
D27: 0 | E27: 1000 | F27: 1001 | G27: 1002 | H27: 1003 | I27: 1004
C28: 本期折旧 | D28: =D25 -> 0 | E28: 0 | F28: 0 | G28: 0 | H28: 0 | I28: 0
C29: 期末余额 | D29: =D25+D26-D28 -> 0 | E29: =E25+E26-E28 -> 0 | F29: =F25+F26-F28 -> 0 | G29: =G25+G26-G28 -> 0 | H29: =H25+H26-H28 -> 0 | I29: =I25+I26-I28 -> 0
C30: 办公电子设备
C31: 期初余额 | D31: =D10 -> 8.781 | E31: =D36 -> 8.781 | F31: =E36 -> 8.781 | G31: =F36 -> 8.781 | H31: =G36 -> 8.781 | I31: =H36 -> 8.781
C32: 本期新增 | D32: =D35 -> 2.927 | E32: =D32 -> 2.927 | F32: =E32 -> 2.927 | G32: =F32 -> 2.927 | H32: =G32 -> 2.927 | I32: =I35+I33 -> #REF!
I33: =#REF! -> #REF!
C34: 本期新增 | D34: =D35 -> 2.927 | E34: =E35 -> 2.927 | F34: =F35 -> 2.927 | G34: =G35 -> 2.927 | H34: =H35 -> 2.927 | I34: =I35 -> 2.927
C35: 本期折旧 | D35: =F10 -> 2.927 | E35: =D35 -> 2.927 | F35: =E35 -> 2.927 | G35: =F35 -> 2.927 | H35: =G35 -> 2.927 | I35: =H35 -> 2.927
C36: 期末余额 | D36: =D31+D34-D35 -> 8.781 | E36: =E31+E34-E35 -> 8.781 | F36: =F31+F34-F35 -> 8.781 | G36: =G31+G34-G35 -> 8.781 | H36: =H31+H34-H35 -> 8.781 | I36: =I31+I34-I35 -> 8.781
C37: 运输设备
C38: 期初余额 | D38: =D9 -> 65.1396 | E38: =D43 -> 65.1396 | F38: =E43 -> 65.1396 | G38: =F43 -> 65.1396 | H38: =G43 -> 65.1396 | I38: =H43 -> 65.1396
C39: 本期新增 | D39: =D42 -> 6.51396 | E39: =E42 -> 6.51396 | F39: =F42 -> 6.51396 | G39: =G42 -> 6.51396 | H39: =H42 -> 6.51396 | I39: =I42 -> 6.51396
D40: 0 | E40: 0 | F40: 0 | G40: 0 | H40: 0 | I40: 0
C41: 本期新增 | D41: =D42 -> 6.51396 | E41: =E42 -> 6.51396 | F41: =F42 -> 6.51396 | G41: =G42 -> 6.51396 | H41: =H42 -> 6.51396 | I41: =I42 -> 6.51396
C42: 本期折旧 | D42: =F9 -> 6.51396 | E42: =D42 -> 6.51396 | F42: =E42 -> 6.51396 | G42: =F42 -> 6.51396 | H42: =G42 -> 6.51396 | I42: =H42 -> 6.51396
C43: 期末余额 | D43: =D38+D41-D42 -> 65.1396 | E43: =E38+E41-E42 -> 65.1396 | F43: =F38+F41-F42 -> 65.1396 | G43: =G38+G41-G42 -> 65.1396 | H43: =H38+H41-H42 -> 65.1396 | I43: =I38+I41-I42 -> 65.1396
C44: 折旧合计 | D44: =D22+D35+D42 -> 147.18221 | E44: =E22+E35+E42 -> 147.18221 | F44: =F22+F35+F42 -> 147.18221 | G44: =G22+G35+G42 -> 147.18221 | H44: =H22+H35+H42 -> 147.18221 | I44: =I22+I35+I42 -> 147.18221
B45: 无形资产摊销
B46: ——软件 | C46: 期初余额 | D46: =3.1607 -> 3.1607 | E46: =D49 -> 3.1607 | F46: =E49 -> 3.1607 | G46: =F49 -> 3.1607 | H46: =G49 -> 3.1607 | I46: =H49 -> 3.1607
B47: 10 | C47: 本期新增 | D47: =D48 -> 0.31607 | E47: =E48 -> 0.31607 | F47: =F48 -> 0.31607 | G47: =G48 -> 0.31607 | H47: =H48 -> 0.31607 | I47: =I48 -> 0.31607
C48: 本期摊销 | D48: =D46/B47 -> 0.31607 | E48: =D48 -> 0.31607 | F48: =E48 -> 0.31607 | G48: =F48 -> 0.31607 | H48: =G48 -> 0.31607 | I48: =H48 -> 0.31607
C49: 期末余额 | D49: =D46+D47-D48 -> 3.1607 | E49: =E46+E47-E48 -> 3.1607 | F49: =F46+F47-F48 -> 3.1607 | G49: =G46+G47-G48 -> 3.1607 | H49: =H46+H47-H48 -> 3.1607 | I49: =I46+I47-I48 -> 3.1607
B50: ——专利 | C50: 期初余额 | D50: =515.16 -> 515.16 | E50: =D53 -> 515.16 | F50: =E53 -> 515.16 | G50: =F53 -> 515.16 | H50: =G53 -> 515.16 | I50: =H53 -> 515.16
B51: 8 | C51: 本期新增 | D51: =D52 -> 64.395 | E51: =E52 -> 64.395 | F51: =F52 -> 64.395 | G51: =G52 -> 64.395 | H51: =H52 -> 64.395 | I51: =I52 -> 64.395
C52: 本期摊销 | D52: =D50/B51 -> 64.395 | E52: =D52 -> 64.395 | F52: =E52 -> 64.395 | G52: =F52 -> 64.395 | H52: =G52 -> 64.395 | I52: =H52 -> 64.395
C53: 期末余额 | D53: =D50+D51-D52 -> 515.16 | E53: =E50+E51-E52 -> 515.16 | F53: =F50+F51-F52 -> 515.16 | G53: =G50+G51-G52 -> 515.16 | H53: =H50+H51-H52 -> 515.16 | I53: =I50+I51-I52 -> 515.16
C54: 摊销合计 | D54: =D48+D52 -> 64.71107 | E54: =E48+E52 -> 64.71107 | F54: =F48+F52 -> 64.71107 | G54: =G48+G52 -> 64.71107 | H54: =H48+H52 -> 64.71107 | I54: =I48+I52 -> 64.71107
A55: A2—资本性支出
B56: 折旧和摊销 | C56: 生产成本 | D56: =D22 -> 137.74125 | E56: =E22 -> 137.74125 | F56: =F22 -> 137.74125 | G56: =G22 -> 137.74125 | H56: =H22 -> 137.74125 | I56: =I22 -> 137.74125
C57: 管理费用-折旧 | D57: =D35+D42 -> 9.44096 | E57: =E35+E42 -> 9.44096 | F57: =F35+F42 -> 9.44096 | G57: =G35+G42 -> 9.44096 | H57: =H35+H42 -> 9.44096 | I57: =I35+I42 -> 9.44096
C58: 管理费用-摊销 | D58: =D54 -> 64.71107 | E58: =E54 -> 64.71107 | F58: =F54 -> 64.71107 | G58: =G54 -> 64.71107 | H58: =H54 -> 64.71107 | I58: =I54 -> 64.71107
C59: 合计 | D59: =SUM(D56:D58) -> 211.89328 | E59: =SUM(E56:E58) -> 211.89328 | F59: =SUM(F56:F58) -> 211.89328 | G59: =SUM(G56:G58) -> 211.89328 | H59: =SUM(H56:H58) -> 211.89328 | I59: =SUM(I56:I58) -> 211.89328
B60: 资本性支出合计 | D60: =D59 -> 211.89328 | E60: =E59 -> 211.89328 | F60: =F59 -> 211.89328 | G60: =G59 -> 211.89328 | H60: =H59 -> 211.89328 | I60: =I59 -> 211.89328

Sheet 管理费用
C1: 管理费用预测表
A3: 被评估单位：
A4: 序号 | B4: 项目 | C4: 2018年 | D4: 2019年 | E4: 2020年 | F4: 2021年 | G4: 2022年 | H4: 2023年 | I4: 标准
C5: 金额 | D5: 金额 | E5: 金额 | F5: 金额 | G5: 金额 | H5: 金额
A7: 1 | B7: 人员费用 | C7: =人员费用表!B22 -> 107.64 | D7: =人员费用表!C22 -> 113.022 | E7: =人员费用表!D22 -> 118.6731 | F7: =人员费用表!E22 -> 124.60676 | G7: =人员费用表!F22 -> 130.83709 | H7: =人员费用表!G22 -> 130.83709
A8: 2 | B8: 办公等费用 | C8: =收入预测表!C9*管理费用!$J$8 -> 41.26755 | D8: =收入预测表!D9*管理费用!$J$8 -> 49.52106 | E8: =收入预测表!E9*管理费用!$J$8 -> 58.434851 | F8: =收入预测表!F9*管理费用!$J$8 -> 67.200078 | G8: =收入预测表!G9*管理费用!$J$8 -> 73.920086 | H8: =收入预测表!H9*管理费用!$J$8 -> 73.920086 | I8: 按照收入的1.5% | J8: 0.015
A9: 3 | B9: 折旧和摊销费 | C9: =折旧和资本化支出!D57+折旧和资本化支出!D58 -> 74.15203 | D9: =折旧和资本化支出!E57+折旧和资本化支出!E58 -> 74.15203 | E9: =折旧和资本化支出!F57+折旧和资本化支出!F58 -> 74.15203 | F9: =折旧和资本化支出!G57+折旧和资本化支出!G58 -> 74.15203 | G9: =折旧和资本化支出!H57+折旧和资本化支出!H58 -> 74.15203 | H9: =折旧和资本化支出!I57+折旧和资本化支出!I58 -> 74.15203
B14: 合计 | C14: =SUM(C7:C13) -> 223.05958 | D14: =SUM(D7:D13) -> 236.69509 | E14: =SUM(E7:E13) -> 251.25998 | F14: =SUM(F7:F13) -> 265.95886 | G14: =SUM(G7:G13) -> 278.90921 | H14: =SUM(H7:H13) -> 278.90921

Sheet 营运资金测算
B4: 项目 | C4: 2016年7-12 | D4: 2017年 | E4: 2018年 | F4: 2019年 | G4: 2020年 | H4: 2021年 | I4: 2022年 | J4: 2023年 | K4: 2024年 | L4: 2025年 | M4: 2026-2039 | N4: 2040 | O4: 2041-2043 | P4: 2044 | Q4: 2045-2048 | R4: 2049-2051
B5: 主要费用项目 | C5: =C6+C8+C9+C11+C7+C10 -> #REF! | D5: =D6+D8+D9+D11+D7+D10 -> #REF! | E5: =E6+E8+E9+E11+E7+E10 -> #REF! | F5: =F6+F8+F9+F11+F7+F10 -> #REF! | G5: =G6+G8+G9+G11+G7+G10 -> #REF! | H5: =H6+H8+H9+H11+H7+H10 -> #REF! | I5: =I6+I8+I9+I11+I7+I10 -> #REF! | J5: =J6+J8+J9+J11+J7 -> #REF! | K5: =K6+K8+K9+K11+K7 -> #REF! | L5: =L6+L8+L9+L11+L7 -> #REF! | M5: =M6+M8+M9+M11+M7 -> #REF! | N5: =N6+N8+N9+N11+N7 -> #REF! | O5: =O6+O8+O9+O11+O7 -> #REF! | P5: =P6+P8+P9+P11+P7 -> #REF! | Q5: =Q6+Q8+Q9+Q11+Q7 -> #REF! | R5: =R6+R8+R9+R11+R7 -> #REF!
B6: 其中：营业成本 | C6: =#REF! -> #REF! | D6: =#REF!+#REF! -> #REF! | E6: =ROUND(#REF!/10000,2) -> #REF! | F6: =ROUND(#REF!/10000,2) -> #REF! | G6: =ROUND(#REF!/10000,2) -> #REF! | H6: =ROUND(#REF!/10000,2) -> #REF! | I6: =ROUND(#REF!/10000,2) -> #REF! | J6: =#REF! -> #REF! | K6: =#REF! -> #REF! | L6: =#REF! -> #REF! | M6: =#REF! -> #REF! | N6: =#REF! -> #REF! | O6: =#REF! -> #REF! | P6: =#REF! -> #REF! | Q6: =#REF! -> #REF! | R6: =#REF! -> #REF!
B7: 营业税金及附加 | C7: =#REF! -> #REF! | D7: =#REF! -> #REF! | E7: =#REF! -> #REF! | F7: =#REF! -> #REF! | G7: =#REF! -> #REF! | H7: =#REF! -> #REF! | I7: =#REF! -> #REF! | J7: =#REF! -> #REF! | ... R7: =#REF! -> #REF!
B8: 营业费用 | C8: =#REF! -> #REF! | D8: =#REF! -> #REF! | E8: =#REF! -> #REF! | F8: =#REF! -> #REF! | G8: =#REF! -> #REF! | H8: =#REF! -> #REF! | I8: =#REF! -> #REF! | J8: =#REF! -> #REF! | ... R8: =#REF! -> #REF!
B9: 管理费用 | C9: =#REF! -> #REF! | D9: =#REF! -> #REF! | E9: =#REF! -> #REF! | F9: =#REF! -> #REF! | G9: =#REF! -> #REF! | H9: =#REF! -> #REF! | I9: =#REF! -> #REF! | J9: =#REF! -> #REF! | ... R9: =#REF! -> #REF!
B10: 财务费用 | C10: =#REF! -> #REF! | D10: =#REF! -> #REF! | E10: =#REF! -> #REF! | F10: =#REF! -> #REF! | G10: =#REF! -> #REF! | H10: =#REF! -> #REF!
B11: 所得税 | C11: =#REF! -> #REF! | D11: =#REF! -> #REF! | E11: =#REF! -> #REF! | F11: =#REF! -> #REF! | G11: =#REF! -> #REF! | H11: =#REF! -> #REF! | I11: =#REF! -> #REF! | J11: =#REF! -> #REF! | ... R11: =#REF! -> #REF!
B12: 减：无需现金支付的费用 | C12: =C13 -> #REF! | D12: =D13 -> #REF! | E12: =E13 -> #REF! | F12: =F13 -> #REF! | G12: =G13 -> #REF! | H12: =H13 -> #REF! | I12: =I13 -> #REF! | J12: =J13 -> #REF! | ... R12: =R13 -> #REF!
B13: 其中：折旧及摊销 | C13: =#REF! -> #REF! | D13: =ROUND((管理费用预测表!#REF!+销售费用预测表!K10),2) -> #REF! | E13: =管理费用预测表!#REF!+销售费用预测表!N10 -> #REF! | F13: =管理费用预测表!#REF!+销售费用预测表!O10 -> #REF! | G13: =管理费用预测表!#REF!+销售费用预测表!P10 -> #REF! | H13: =管理费用预测表!#REF!+销售费用预测表!Q10 -> #REF! | I13: =管理费用预测表!#REF!+销售费用预测表!R10 -> #REF! | J13: =#REF! -> #REF! | K13: =#REF! -> #REF! | L13: =#REF! -> #REF! | M13: =#REF! -> #REF! | N13: =#REF! -> #REF! | O13: =#REF! -> #REF! | P13: =#REF! -> #REF! | Q13: =#REF! -> #REF! | R13: =#REF! -> #REF!
B14: 合计 | C14: =(C5-C12) -> #REF! | D14: =(D5-D12) -> #REF! | E14: =(E5-E12) -> #REF! | F14: =(F5-F12) -> #REF! | G14: =(G5-G12) -> #REF! | H14: =(H5-H12) -> #REF! | I14: =(I5-I12) -> #REF! | J14: =(J5-J12) -> #REF! | ... R14: =(R5-R12) -> #REF!
B15: 每月付现支出 | C15: =ROUND(C14/6,2) -> #REF! | D15: =ROUND(D14/12,2) -> #REF! | E15: =ROUND(E14/12,2) -> #REF! | F15: =ROUND(F14/12,2) -> #REF! | G15: =ROUND(G14/12,2) -> #REF! | H15: =ROUND(H14/12,2) -> #REF! | I15: =ROUND(I14/12,2) -> #REF! | J15: =ROUND(J14/12,2) -> #REF! | K15: =ROUND(K14/12,2) -> #REF! | ... R15: =ROUND(R14/12,2) -> #REF!
B16: 根据企业的财务指标确定安全资金的月数 | C16: 3 | D16: 3 | E16: 3 | F16: 3 | G16: 3 | H16: 3 | I16: 3 | J16: 3 | K16: 3 | L16: 3 | M16: 3 | N16: 3 | O16: 3 | P16: 3 | Q16: 3 | R16: 3
B17: 安全运营现金 | C17: =C15*C16 -> #REF! | D17: =D15*D16 -> #REF! | E17: =E15*E16 -> #REF! | F17: =F15*F16 -> #REF! | G17: =G15*G16 -> #REF! | H17: =H15*H16 -> #REF! | I17: =I15*I16 -> #REF! | J17: =J15*J16 -> #REF! | ... R17: =R15*R16 -> #REF!
B21: 周转率 | C21: 2016年7-12 | D21: 2017年 | E21: 2018年 | F21: 2019年 | G21: 2020年 | H21: 2021年 | I21: 2022年 | J21: 2023年 | K21: 2024年 | L21: 2025年 | M21: 2026-2039 | N21: 2040 | O21: 2041-2043 | P21: 2044 | Q21: 2045-2048 | R21: 2049-2051
A22: 应收账款（工程款、项目款） | B22: 1.36 | C22: =ROUND('收入--历史经营情况分析'!#REF!/$B$22,2) -> #REF! | D22: =ROUND('收入--历史经营情况分析'!#REF!/$B$22,2) -> #REF! | E22: =ROUND('收入--历史经营情况分析'!#REF!/$B$22,2) -> #REF! | F22: =ROUND('收入--历史经营情况分析'!#REF!/$B$22,2) -> #REF! | G22: =ROUND('收入--历史经营情况分析'!#REF!/$B$22,2) -> #REF! | H22: =ROUND('收入--历史经营情况分析'!#REF!/$B$22,2) -> #REF! | I22: =ROUND('收入--历史经营情况分析'!#REF!/$B$22,2) -> #REF! | J22: =ROUND('收入--历史经营情况分析'!#REF!/$B$22,2) -> #REF! | ... R22: =ROUND('收入--历史经营情况分析'!#REF!/$B$22,2) -> #REF!
A23: 预付账款（预付货款，周期为150天） | B23: 11.3 | C23: =ROUND(#REF!/$B$23,2) -> #REF! | D23: =ROUND(#REF!/$B$23,2) -> #REF! | E23: =ROUND(#REF!/$B$23,2) -> #REF! | F23: =ROUND(#REF!/$B$23,2) -> #REF! | G23: =ROUND(#REF!/$B$23,2) -> #REF! | H23: =ROUND(#REF!/$B$23,2) -> #REF! | I23: =ROUND(#REF!/$B$23,2) -> #REF! | J23: =ROUND(#REF!/$B$23,2) -> #REF! | ... R23: =ROUND(#REF!/$B$23,2) -> #REF!
A24: 存货（属于工程材料等）
A25: 应付账款（工程款、货款等，周期163天） | B25: 2.82 | C25: =ROUND(#REF!/$B$25,2) -> #REF! | D25: =ROUND(#REF!/$B$25,2) -> #REF! | E25: =ROUND(#REF!/$B$25,2) -> #REF! | F25: =ROUND(#REF!/$B$25,2) -> #REF! | G25: =ROUND(#REF!/$B$25,2) -> #REF! | H25: =ROUND(#REF!/$B$25,2) -> #REF! | I25: =ROUND(#REF!/$B$25,2) -> #REF! | J25: =ROUND(#REF!/$B$25,2) -> #REF! | ... R25: =ROUND(#REF!/$B$25,2) -> #REF!
A26: 预收账款（预收账款金额小，不予测算）
B31: 项目\预测期 | C31: 2016年7-12 | D31: 2017年 | E31: 2018年 | F31: 2019年 | G31: 2020年 | H31: 2021年 | I31: 2022年 | J31: 2023年 | K31: 2024年 | L31: 2025年 | M31: 2026-2039 | N31: 2040 | O31: 2041-2043 | P31: 2044 | Q31: 2045-2048 | R31: 2049-2051 | S31: 2022
A32: 1 | B32: 期初运营现金 | C32: 59.47 | D32: =T42 -> 7757.58 | E32: =D42 -> #REF! | F32: =E42 -> #REF! | G32: =F42 -> #REF! | H32: =G42 -> #REF! | I32: =H42 -> #REF! | J32: =I42 -> #REF! | K32: =J42 -> #REF! | L32: =K42 -> #REF! | ... R32: =Q42 -> #REF! | T32: 13.49
A33: 2 | B33: 应收账款 | C33: =C22 -> #REF! | D33: =D22 -> #REF! | E33: =E22 -> #REF! | F33: =F22 -> #REF! | G33: =G22 -> #REF! | H33: =H22 -> #REF! | I33: =I22 -> #REF! | J33: =J22 -> #REF! | ... R33: =R22 -> #REF! | T33: 8947.91
A34: 3 | B34: 经营性其他应收款
A35: 4 | B35: 预付账款 | C35: =C23 -> #REF! | D35: =D23 -> #REF! | E35: =E23 -> #REF! | F35: =F23 -> #REF! | G35: =G23 -> #REF! | H35: =H23 -> #REF! | I35: =I23 -> #REF! | J35: =J23 -> #REF! | ... R35: =R23 -> #REF! | T35: 323.47
A36: 5 | B36: 存货 | C36: =C24 -> 0 | D36: =D24 -> 0 | E36: =E24 -> 0 | F36: =F24 -> 0 | G36: =G24 -> 0 | H36: =H24 -> 0 | I36: =I24 -> 0 | J36: =J24 -> 0 | ... R36: =R24 -> 0
A37: 6 | B37: 其他的经营性资产
A38: 7 | B38: 应付账款 | C38: =C25 -> #REF! | D38: =D25 -> #REF! | E38: =E25 -> #REF! | F38: =F25 -> #REF! | G38: =G25 -> #REF! | H38: =H25 -> #REF! | I38: =I25 -> #REF! | J38: =J25 -> #REF! | ... R38: =R25 -> #REF! | T38: 1513.8
A39: 8 | B39: 预收账款 | C39: =C26 -> 0 | D39: =D26 -> 0 | E39: =E26 -> 0 | F39: =F26 -> 0 | G39: =G26 -> 0 | H39: =H26 -> 0 | I39: =I26 -> 0 | J39: =J26 -> 0 | ... R39: =R26 -> 0
A40: 9 | B40: 经营性其他应付款
A41: 10 | B41: 其他付现成本 | C41: =C17 -> #REF! | D41: =D17 -> #REF! | E41: =E17 -> #REF! | F41: =F17 -> #REF! | G41: =G17 -> #REF! | H41: =H17 -> #REF! | I41: =I17 -> #REF! | J41: =J17 -> #REF! | ... R41: =R17 -> #REF!
B42: 全年营运资本 | C42: =(C33+C35+C36-C38-C39)/6*3+C41 -> #REF! | D42: =(D33+D35+D36-D38-D39)+D41 -> #REF! | E42: =(E33+E35+E36-E38-E39)+E41 -> #REF! | F42: =(F33+F35+F36-F38-F39)+F41 -> #REF! | G42: =(G33+G35+G36-G38-G39)+G41 -> #REF! | H42: =(H33+H35+H36-H38-H39)+H41 -> #REF! | I42: =I33+I35+I36-I38-I39+I41 -> #REF! | J42: =J33+J35+J36-J38-J39+J41 -> #REF! | K42: =K33+K35+K36-K38-K39+K41 -> #REF! | L42: =L33+L35+L36-L38-L39+L41 -> #REF! | M42: =M33+M35+M36-M38-M39+M41 -> #REF! | N42: =N33+N35+N36-N38-N39+N41 -> #REF! | O42: =O33+O35+O36-O38-O39+O41 -> #REF! | P42: =P33+P35+P36-P38-P39+P41 -> #REF! | ... R42: =R33+R35+R36-R38-R39+R41 -> #REF! | T42: =(T33+T35+T36-T38-T39)+T41 -> 7757.58
B43: 运营资本增加 | C43: =C42-C32 -> #REF! | D43: 0 | E43: =E42-E32 -> #REF! | F43: =F42-F32 -> #REF! | G43: =G42-G32 -> #REF! | H43: =H42-H32 -> #REF! | I43: =I42-I32 -> #REF! | J43: =J42-J32 -> #REF! | K43: =K42-K32 -> #REF! | L43: =L42-L32 -> #REF! | ... R43: =R42-R32 -> #REF!
D45: 0
B79: =B61*10000 -> 0 | C79: =C61*10000 -> 0 | D79: =D61*10000 -> 0 | E79: =E61*10000 -> 0 | F79: =F61*10000 -> 0 | G79: =G61*10000 -> 0 | H79: =H61*10000 -> 0
B80: =B62*10000 -> 0 | C80: =C62*10000 -> 0 | D80: =D62*10000 -> 0 | E80: =E62*10000 -> 0 | F80: =F62*10000 -> 0 | G80: =G62*10000 -> 0 | H80: =H62*10000 -> 0
B81: =B63*10000 -> 0 | C81: =C63*10000 -> 0 | D81: =D63*10000 -> 0 | E81: =E63*10000 -> 0 | F81: =F63*10000 -> 0 | G81: =G63*10000 -> 0 | H81: =H63*10000 -> 0
B82: =B64*10000 -> 0 | C82: =C64*10000 -> 0 | D82: =D64*10000 -> 0 | E82: =E64*10000 -> 0 | F82: =F64*10000 -> 0 | G82: =G64*10000 -> 0 | H82: =H64*10000 -> 0
B83: =B65*10000 -> 0 | C83: =C65*10000 -> 0 | D83: =D65*10000 -> 0 | E83: =E65*10000 -> 0 | F83: =F65*10000 -> 0 | G83: =G65*10000 -> 0 | H83: =H65*10000 -> 0
B84: =B66*10000 -> 0 | C84: =C66*10000 -> 0 | D84: =D66*10000 -> 0 | E84: =E66*10000 -> 0 | F84: =F66*10000 -> 0 | G84: =G66*10000 -> 0 | H84: =H66*10000 -> 0
B85: =B67*10000 -> 0 | C85: =C67*10000 -> 0 | D85: =D67*10000 -> 0 | E85: =E67*10000 -> 0 | F85: =F67*10000 -> 0 | G85: =G67*10000 -> 0 | H85: =H67*10000 -> 0
B86: =B68*10000 -> 0 | C86: =C68*10000 -> 0 | D86: =D68*10000 -> 0 | E86: =E68*10000 -> 0 | F86: =F68*10000 -> 0 | G86: =G68*10000 -> 0 | H86: =H68*10000 -> 0
B87: =B69*10000 -> 0 | C87: =C69*10000 -> 0 | D87: =D69*10000 -> 0 | E87: =E69*10000 -> 0 | F87: =F69*10000 -> 0 | G87: =G69*10000 -> 0 | H87: =H69*10000 -> 0
B88: =B70*10000 -> 0 | C88: =C70*10000 -> 0 | D88: =D70*10000 -> 0 | E88: =E70*10000 -> 0 | F88: =F70*10000 -> 0 | G88: =G70*10000 -> 0 | H88: =H70*10000 -> 0
B89: =B71*10000 -> 0 | C89: =C71*10000 -> 0 | D89: =D71*10000 -> 0 | E89: =E71*10000 -> 0 | F89: =F71*10000 -> 0 | G89: =G71*10000 -> 0 | H89: =H71*10000 -> 0
B90: =B72*10000 -> 0 | C90: =C72*10000 -> 0 | D90: =D72*10000 -> 0 | E90: =E72*10000 -> 0 | F90: =F72*10000 -> 0 | G90: =G72*10000 -> 0 | H90: =H72*10000 -> 0
B91: =B73*10000 -> 0 | C91: =C73*10000 -> 0 | D91: =D73*10000 -> 0 | E91: =E73*10000 -> 0 | F91: =F73*10000 -> 0 | G91: =G73*10000 -> 0 | H91: =H73*10000 -> 0

Sheet WACC测算
O2: Rf | P2: 0.0418
E3: 序号 | F3: 股票代码 | G3: 可比参考公司 | H3: 付息债务价值Di | I3: 股权价值Ei | J3: Di/Ei | K3: 调整BETA | L3: 税率ti | M3: βUi（整理） | O3: MRP | P3: 0.0719
E4: 1 | M4: =K4/(1+J4*0.75) -> 0 | O4: βL | P4: =ROUND(M7*(1+(1-25%)*J7),4) -> 0
E5: 2 | M5: =K5/(1+J5*0.75) -> 0 | O5: 规模风险 | P5: =ROUND(3.139%-0.2486%*3.806376,4) -> 0.0219
E6: 3 | M6: =K6/(1+J6*0.75) -> 0 | O6: 特有风险 | P6: 0.03
H7: =SUM(H4:H6) -> 0 | I7: =SUM(I4:I6) -> 0 | J7: =ROUND((J4+J5+J6)/3,4) -> 0 | K7: =(K4+K5+K6)/3 -> 0 | M7: =ROUND((M4+M5+M6)/3,4) -> 0 | O7: Rc | P7: =P5+P6 -> 0.0519
O8: Ke= Rf1＋βL×MRP＋Rc
E9: 短期债务 | F9: 长期债务 | H9: 短债 | I9: 长债 | J9: 合计 | O9: Ke | P9: =ROUND(4.18%+P4*7.19%+P7,4) -> 0.0937
L10: 一年期贷款利率4.35% | O10: Kd | P10: =ROUND(H13*4.35%+I13*4.9%,4) -> 0
L11: 中长期贷款(五年以上）利率4.9% | O11: WACC | P11: =38063.76/90644.4*P9+52580.64/90644.4*(1-25%)*P10 -> 0.03934688
H12: =E10+E11+E12 -> 0 | I12: =F10+F11+F12 -> 0 | J12: =H12+I12 -> 0

Sheet 财务费用
B4: 项目\预测期 | C4: 2016年6-12 | D4: 2017年 | E4: 2018年 | F4: 2019年 | G4: 2020年 | H4: 2021年
B5: 期初现金保有量 | C5: =[38]营运资金测算!D33 -> 7576.61 | D5: =[38]营运资金测算!E33 -> 7576.61 | E5: =[38]营运资金测算!F33 -> 13646.92 | F5: =[38]营运资金测算!G33 -> 14458.94 | G5: =[38]营运资金测算!H33 -> 14944.77 | H5: =[38]营运资金测算!I33 -> 15484.75
B6: 需要现金流量 | C6: =[38]营运资金测算!D43 -> 7079.86 | D6: =[38]营运资金测算!E43 -> 13646.92 | E6: =[38]营运资金测算!F43 -> 14458.94 | F6: =[38]营运资金测算!G43 -> 14944.77 | G6: =[38]营运资金测算!H43 -> 15484.75 | H6: =[38]营运资金测算!I43 -> 15484.75
B7: 资金盈缺 | C7: =C5-C6 -> 496.75 | D7: =D5-D6 -> -6070.31 | E7: =E5-E6 -> -812.02 | F7: =F5-F6 -> -485.83 | G7: =G5-G6 -> -539.98 | H7: =H5-H6 -> 0
B8: 资金盈缺 | C8: =C6-C5 -> -496.75 | D8: =D6-D5 -> 6070.31 | E8: =E6-E5 -> 812.02 | F8: =F6-F5 -> 485.83 | G8: =G6-G5 -> 539.98 | H8: =H6-H5 -> 0
B10: 金融机构借款—期初 | C10: =[38]评估值测算!N18 -> 10317.616 | D10: =C13 -> 0 | E10: =D13 -> 0 | F10: =E13 -> 0 | G10: =F13 -> 0 | H10: =G13 -> 0
B11: 经营现金流 | C11: =[38]评估值测算!B8 -> 3604.0331 | D11: =[38]评估值测算!C8 -> 4762.7466 | E11: =[38]评估值测算!D8 -> 11176.036 | F11: =[38]评估值测算!E8 -> 11983.849 | G11: =[38]评估值测算!F8 -> 12463.999 | H11: =[38]评估值测算!G8 -> 13003.979
B12: 金融机构借款—追加（归还） | C12: =-C11 -> -3604.0331 | D12: =-D11 -> -4762.7466 | E12: =-E10 -> 0 | F12: 0 | G12: 0 | H12: 0
B13: 期末借款金额
B15: 利息 | C15: 123.9537 | D15: 201.06089 | E15: 53.60795 | F15: 0 | G15: 0 | H15: 0
B17: 利息 | C17: =ROUND(C13*$J$17/12*6,2) -> 0 | D17: =ROUND(D13*$J$17,2) -> 0 | E17: =ROUND(E13*$J$17,2) -> 0 | F17: =ROUND(F13*$J$17,2) -> 0 | G17: =ROUND(G13*$J$17,2) -> 0 | H17: =ROUND(H13*$J$17,2) -> 0 | J17: =K17+L17 -> 0.0612 | K17: 0.0435 | L17: 0.0177

Sheet Sheet1
A4: 金额单位：万元 | B4: 2016年7-12 | C4: 2017年 | D4: 2018年 | E4: 2019年 | F4: 2020年 | G4: 2021年 | H4: 2022年 | I4: 2023年 | J4: 2024年 | K4: 2025年 | L4: 2026年
A5: 营业收入 | B5: ='收入--历史经营情况分析'!#REF! -> #REF! | C5: ='收入--历史经营情况分析'!#REF! -> #REF! | D5: ='收入--历史经营情况分析'!#REF! -> #REF! | E5: ='收入--历史经营情况分析'!#REF! -> #REF! | F5: ='收入--历史经营情况分析'!#REF! -> #REF! | G5: ='收入--历史经营情况分析'!#REF! -> #REF! | H5: ='收入--历史经营情况分析'!#REF! -> #REF! | I5: ='收入--历史经营情况分析'!#REF! -> #REF! | ... L5: ='收入--历史经营情况分析'!#REF! -> #REF!
A6: 营业成本 | B6: =#REF! -> #REF! | C6: =#REF! -> #REF! | D6: =#REF! -> #REF! | E6: =#REF! -> #REF! | F6: =#REF! -> #REF! | G6: =#REF! -> #REF! | H6: =#REF! -> #REF! | I6: =#REF! -> #REF! | ... L6: =#REF! -> #REF!
A7: 毛利率 | B7: =(B5-B6)/B5 -> #REF! | C7: =(C5-C6)/C5 -> #REF! | D7: =(D5-D6)/D5 -> #REF! | E7: =(E5-E6)/E5 -> #REF! | F7: =(F5-F6)/F5 -> #REF! | G7: =(G5-G6)/G5 -> #REF! | H7: =(H5-H6)/H5 -> #REF! | I7: =(I5-I6)/I5 -> #REF! | ... L7: =(L5-L6)/L5 -> #REF!
A8: 税金及附加 | B8: =#REF! -> #REF! | C8: =#REF! -> #REF! | D8: =#REF! -> #REF! | E8: =#REF! -> #REF! | F8: =#REF! -> #REF! | G8: =#REF! -> #REF! | H8: =#REF! -> #REF! | I8: =#REF! -> #REF! | ... L8: =#REF! -> #REF!
A9: 减：营业费用 | B9: =经营费用!B9 -> #REF! | C9: =经营费用!C9 -> #REF! | D9: =经营费用!D9 -> #REF! | E9: =经营费用!E9 -> #REF! | F9: =经营费用!F9 -> #REF! | G9: =经营费用!G9 -> #REF! | H9: =经营费用!H9 -> #REF! | I9: =经营费用!I9 -> #REF! | ... K9: =经营费用!K9 -> #REF! | L9: =经营费用!P9 -> #REF!
A10: 减：管理费用 | B10: =#REF! -> #REF! | C10: =#REF! -> #REF! | D10: =#REF! -> #REF! | E10: =#REF! -> #REF! | F10: =#REF! -> #REF! | G10: =#REF! -> #REF! | H10: =#REF! -> #REF! | I10: =#REF! -> #REF! | ... L10: =#REF! -> #REF!
A11: 减：财务费用 | B11: 0 | C11: 0 | D11: 0 | E11: 0 | F11: 0 | G11: 0 | H11: 0 | I11: 0 | J11: 0 | K11: 0 | L11: 0
A12: 加：其它业务利润 | B12: 0 | C12: 0 | D12: 0 | E12: 0 | F12: 0 | G12: 0 | H12: 0 | I12: 0 | J12: 0 | K12: 0 | L12: 0
A13: 税前利润 | B13: =B5-B6-B8-B9-B10-B11+B12 -> #REF! | C13: =C5-C6-C8-C9-C10-C11+C12 -> #REF! | D13: =D5-D6-D8-D9-D10-D11+D12 -> #REF! | E13: =E5-E6-E8-E9-E10-E11+E12 -> #REF! | F13: =F5-F6-F8-F9-F10-F11+F12 -> #REF! | G13: =G5-G6-G8-G9-G10-G11+G12 -> #REF! | H13: =H5-H6-H8-H9-H10-H11+H12 -> #REF! | I13: =I5-I6-I8-I9-I10-I11+I12 -> #REF! | ... L13: =L5-L6-L8-L9-L10-L11+L12 -> #REF!
A14: 减: 所得税 | B14: 0 | C14: =C13*$M$14 -> #REF! | D14: =D13*$M$14 -> #REF! | E14: =E13*$M$14 -> #REF! | F14: =F13*$M$14 -> #REF! | G14: =G13*$M$14 -> #REF! | H14: =H13*$M$14 -> #REF! | I14: =I13*$M$14 -> #REF! | J14: =J13*$M$14 -> #REF! | ... L14: =L13*$M$14 -> #REF! | M14: 0.15
A15: 净利润 | B15: =B13-B14 -> #REF! | C15: =C13-C14 -> #REF! | D15: =D13-D14 -> #REF! | E15: =E13-E14 -> #REF! | F15: =F13-F14 -> #REF! | G15: =G13-G14 -> #REF! | H15: =H13-H14 -> #REF! | I15: =I13-I14 -> #REF! | ... L15: =L13-L14 -> #REF!

Sheet Sheet2

Sheet 预测利润表
A2: 序号 | B2: 项目 | C2: 2018年 | D2: 2019年 | E2: 2020年 | F2: 2021年 | G2: 2022年 | H2: 2023年
A3: 1 | B3: 一、主营业务收入 | C3: =收入预测表!C9 -> 2751.17 | D3: =收入预测表!D9 -> 3301.404 | E3: =收入预测表!E9 -> 3895.6567 | F3: =收入预测表!F9 -> 4480.0052 | G3: =收入预测表!G9 -> 4928.0058 | H3: =收入预测表!H9 -> 4928.0058
A4: 2 | B4: 减：主营业务成本 | C4: =成本预测表!C5 -> 2279.7316 | D4: =成本预测表!D5 -> 2610.4137 | E4: =成本预测表!E5 -> 2967.1129 | F4: =成本预测表!F5 -> 3318.8878 | G4: =成本预测表!G5 -> 3593.1362 | H4: =成本预测表!H5 -> 3593.1362
C5: =1-C4/C3 -> 0.17135924 | D5: =1-D4/D3 -> 0.20930196 | E5: =1-E4/E3 -> 0.2383536 | F5: =1-F4/F3 -> 0.2591777 | G5: =1-G4/G3 -> 0.27087418 | H5: =1-H4/H3 -> 0.27087418
A6: 3 | B6: 主营业务税金及附加 | C6: =税金及附加预测表!D23 -> 0.825351 | D6: =税金及附加预测表!E23 -> 5.0424381 | E6: =税金及附加预测表!F23 -> 26.959557 | F6: =税金及附加预测表!G23 -> 32.186247 | G6: =税金及附加预测表!H23 -> 36.193375 | H6: =税金及附加预测表!I23 -> 36.193375
A7: 4 | B7: 二、主营业务利润 | C7: =C3-C4-C6 -> 470.61304 | D7: =D3-D4-D6 -> 685.94789 | E7: =E3-E4-E6 -> 901.58425 | F7: =F3-F4-F6 -> 1128.9312 | G7: =G3-G4-G6 -> 1298.6761 | H7: =H3-H4-H6 -> 1298.6761
A8: 5 | B8: 加：其他业务利润
A9: 6 | B9: 减：销售费用 | C9: =销售费用!O15 -> 49.25819 | D9: =销售费用!P15 -> 54.009828 | E9: =销售费用!Q15 -> 59.114597 | F9: =销售费用!R15 -> 64.197287 | G9: =销售费用!S15 -> 68.375153 | H9: =销售费用!T15 -> 68.375153
A10: 7 | B10: 管理费用 | C10: =管理费用!C14 -> 223.05958 | D10: =管理费用!D14 -> 236.69509 | E10: =管理费用!E14 -> 251.25998 | F10: =管理费用!F14 -> 265.95886 | G10: =管理费用!G14 -> 278.90921 | H10: =管理费用!H14 -> 278.90921
A11: 8 | B11: 财务费用
A12: 9 | B12: 三、营业利润 | C12: =C7+C8-C9-C10-C11 -> 198.29527 | D12: =D7+D8-D9-D10-D11 -> 395.24297 | E12: =E7+E8-E9-E10-E11 -> 591.20967 | F12: =F7+F8-F9-F10-F11 -> 798.77507 | G12: =G7+G8-G9-G10-G11 -> 951.39177 | H12: =H7+H8-H9-H10-H11 -> 951.39177
A13: 10 | B13: 加：投资收益
A14: 11 | B14: 补贴收入
A15: 12 | B15: 营业外收入
A16: 13 | B16: 减：营业外支出
A17: 14 | B17: 四、利润总额 | C17: =C12+C13+C14+C15-C16 -> 198.29527 | D17: =D12+D13+D14+D15-D16 -> 395.24297 | E17: =E12+E13+E14+E15-E16 -> 591.20967 | F17: =F12+F13+F14+F15-F16 -> 798.77507 | G17: =G12+G13+G14+G15-G16 -> 951.39177 | H17: =H12+H13+H14+H15-H16 -> 951.39177
A18: 15 | B18: 减：所得税（25%） | G18: =(C17+D17+E17+F17+G17-2452.67)*25% -> 120.56119 | H18: =H17*25% -> 237.84794 | J18: 根据税审报告，截至17年底，尚余可税前弥补的亏损余额为2452.67万元
A19: 16 | B19: 五、净利润 | C19: =C17-C18 -> 198.29527 | D19: =D17-D18 -> 395.24297 | E19: =E17-E18 -> 591.20967 | F19: =F17-F18 -> 798.77507 | G19: =G17-G18 -> 830.83058 | H19: =H17-H18 -> 713.54383
B23: -6711077.2 | C23: -3158853.1 | D23: -7245584.3
B24: 15 | C24: 16 | D24: 17
B25: 20 | C25: 21 | D25: 22

Sheet 预测 主要资产负债项目
A1: 资产负债项目估算表
A2: 项目 | B2: 2018年 | C2: 2019年 | D2: 2020年 | E2: 2021年 | F2: 2022年 | G2: 2023年
A3: 存 货 | B3: =预测利润表!C4/财务指标分析表!$G$17 -> 189.97763 | C3: =预测利润表!D4/财务指标分析表!$G$17 -> 217.53447 | D3: =预测利润表!E4/财务指标分析表!$G$17 -> 247.25941 | E3: =预测利润表!F4/财务指标分析表!$G$17 -> 276.57398 | F3: =预测利润表!G4/财务指标分析表!$G$17 -> 299.42802 | G3: =预测利润表!H4/财务指标分析表!$G$17 -> 299.42802
A4: 应收账款 | B4: =预测利润表!C3*$H$4/财务指标分析表!$G$18 -> 183.41133 | C4: =预测利润表!D3*$H$4/财务指标分析表!$G$18 -> 220.0936 | D4: =预测利润表!E3*$H$4/财务指标分析表!$G$18 -> 259.71045 | E4: =预测利润表!F3*$H$4/财务指标分析表!$G$18 -> 298.66702 | F4: =预测利润表!G3*$H$4/财务指标分析表!$G$18 -> 328.53372 | G4: =预测利润表!H3*$H$4/财务指标分析表!$G$18 -> 328.53372 | H4: 0.8
A5: 预付账款 | B5: =预测利润表!C4*$H$5/财务指标分析表!$G$19 -> 37.995527 | C5: =预测利润表!D4*$H$5/财务指标分析表!$G$19 -> 43.506895 | D5: =预测利润表!E4*$H$5/财务指标分析表!$G$19 -> 49.451882 | E5: =预测利润表!F4*$H$5/财务指标分析表!$G$19 -> 55.314796 | F5: =预测利润表!G4*$H$5/财务指标分析表!$G$19 -> 59.885604 | G5: =预测利润表!H4*$H$5/财务指标分析表!$G$19 -> 59.885604 | H5: 0.2
A6: 应付账款 | B6: =预测利润表!C4*$H$6/财务指标分析表!$G$22 -> 151.98211 | C6: =预测利润表!D4*$H$6/财务指标分析表!$G$22 -> 174.02758 | D6: =预测利润表!E4*$H$6/财务指标分析表!$G$22 -> 197.80753 | E6: =预测利润表!F4*$H$6/财务指标分析表!$G$22 -> 221.25918 | F6: =预测利润表!G4*$H$6/财务指标分析表!$G$22 -> 239.54242 | G6: =预测利润表!H4*$H$6/财务指标分析表!$G$22 -> 239.54242 | H6: 0.8
A7: 预收款项 | B7: =预测利润表!C3*$H$7/财务指标分析表!$G$23 -> 91.705667 | C7: =预测利润表!D3*$H$7/财务指标分析表!$G$23 -> 110.0468 | D7: =预测利润表!E3*$H$7/财务指标分析表!$G$23 -> 129.85522 | E7: =预测利润表!F3*$H$7/财务指标分析表!$G$23 -> 149.33351 | F7: =预测利润表!G3*$H$7/财务指标分析表!$G$23 -> 164.26686 | G7: =预测利润表!H3*$H$7/财务指标分析表!$G$23 -> 164.26686 | H7: 0.2
A8: =资产负债分析调整表!B50 -> 应付职工薪酬 | B8: =人员费用表!B24 -> 417.24 | C8: =人员费用表!C24 -> 438.102 | D8: =人员费用表!D24 -> 460.0071 | E8: =人员费用表!E24 -> 483.00745 | F8: =人员费用表!F24 -> 507.15783 | G8: =人员费用表!G24 -> 507.15783
A9: =资产负债分析调整表!B52 -> 应交税费 | B9: =税金及附加预测表!D9+税金及附加预测表!D23 -> 0.825351 | C9: =税金及附加预测表!E9+税金及附加预测表!E23 -> 38.809246 | D9: =税金及附加预测表!F9+税金及附加预测表!F23 -> 241.88339 | E9: =税金及附加预测表!G9+税金及附加预测表!G23 -> 289.20496 | F9: =税金及附加预测表!H9+税金及附加预测表!H23 -> 325.48482 | G9: =税金及附加预测表!I9+税金及附加预测表!I23 -> 325.48482

Sheet 营运资金
A1: 营运资金增加额估算表
A2: 项目 | B2: 2017年 | C2: 2018年 | D2: 2019年 | E2: 2020年 | F2: 2021年 | G2: 2022年 | H2: 2023年
A3: 收入 | B3: =利润分析调整表!D7/10000 -> 311.41757 | C3: =预测利润表!C3 -> 2751.17 | D3: =预测利润表!D3 -> 3301.404 | E3: =预测利润表!E3 -> 3895.6567 | F3: =预测利润表!F3 -> 4480.0052 | G3: =预测利润表!G3 -> 4928.0058 | H3: =预测利润表!H3 -> 4928.0058
A4: 成本 | B4: =利润分析调整表!D11/10000 -> 457.74977 | C4: =预测利润表!C4 -> 2279.7316 | D4: =预测利润表!D4 -> 2610.4137 | E4: =预测利润表!E4 -> 2967.1129 | F4: =预测利润表!F4 -> 3318.8878 | G4: =预测利润表!G4 -> 3593.1362 | H4: =预测利润表!H4 -> 3593.1362
A5: 管理费用 | B5: =利润分析调整表!D16/10000 -> 14.237442 | C5: =管理费用!C14 -> 223.05958 | D5: =管理费用!D14 -> 236.69509 | E5: =管理费用!E14 -> 251.25998 | F5: =管理费用!F14 -> 265.95886 | G5: =管理费用!G14 -> 278.90921 | H5: =管理费用!H14 -> 278.90921
A6: 销售费用 | B6: =利润分析调整表!D16/10000 -> 14.237442 | C6: =预测利润表!C9 -> 49.25819 | D6: =预测利润表!D9 -> 54.009828 | E6: =预测利润表!E9 -> 59.114597 | F6: =预测利润表!F9 -> 64.197287 | G6: =预测利润表!G9 -> 68.375153 | H6: =预测利润表!H9 -> 68.375153
A7: 财务费用
A8: 税金及附加 | B8: =利润分析调整表!D15/10000 -> 0.42286 | C8: =预测利润表!C6 -> 0.825351 | D8: =预测利润表!D6 -> 5.0424381 | E8: =预测利润表!E6 -> 26.959557 | F8: =预测利润表!F6 -> 32.186247 | G8: =预测利润表!G6 -> 36.193375 | H8: =预测利润表!H6 -> 36.193375
A9: 所得税 | B9: 0 | C9: =预测利润表!C18 -> 0 | D9: =预测利润表!D18 -> 0 | E9: =预测利润表!E18 -> 0 | F9: =预测利润表!F18 -> 0 | G9: =预测利润表!G18 -> 120.56119 | H9: =预测利润表!H18 -> 237.84794
A10: 折旧摊销 | B10: =SUM(B11:B11) -> 184.6238 | C10: =SUM(C11:C11) -> 211.89328 | D10: =SUM(D11:D11) -> 211.89328 | E10: =SUM(E11:E11) -> 211.89328 | F10: =SUM(F11:F11) -> 211.89328 | G10: =SUM(G11:G11) -> 211.89328 | H10: =SUM(H11:H11) -> 211.89328
A11: 折旧摊销 | B11: =(资产负债分析调整表!E28-资产负债分析调整表!D28)/10000 -> 184.6238 | C11: =折旧和资本化支出!D59 -> 211.89328 | D11: =折旧和资本化支出!E59 -> 211.89328 | E11: =折旧和资本化支出!F59 -> 211.89328 | F11: =折旧和资本化支出!G59 -> 211.89328 | G11: =折旧和资本化支出!H59 -> 211.89328 | H11: =折旧和资本化支出!I59 -> 211.89328
A12: 付现成本 | B12: =B4+B5+B6+B7+B8+B9-B10 -> 302.02371 | C12: =C4+C5+C6+C7+C8+C9-C10 -> 2340.9814 | D12: =D4+D5+D6+D7+D8+D9-D10 -> 2694.2678 | E12: =E4+E5+E6+E7+E8+E9-E10 -> 3092.5538 | F12: =F4+F5+F6+F7+F8+F9-F10 -> 3469.3369 | G12: =G4+G5+G6+G7+G8+G9-G10 -> 3885.2819 | H12: =H4+H5+H6+H7+H8+H9-H10 -> 4002.5686
A13: 最低现金保有量 | B13: =B12/12*3 -> 75.505928 | C13: =C12/12*3 -> 585.24536 | D13: =D12/12*3 -> 673.56694 | E13: =E12/12*3 -> 773.13844 | F13: =F12/12*3 -> 867.33422 | G13: =G12/12*3 -> 971.32047 | H13: =H12/12*3 -> 1000.6422
A14: 存 货 | B14: =资产负债分析调整表!E16/10000 -> 530.39016 | C14: ='预测 主要资产负债项目'!B3 -> 189.97763 | D14: ='预测 主要资产负债项目'!C3 -> 217.53447 | E14: ='预测 主要资产负债项目'!D3 -> 247.25941 | F14: ='预测 主要资产负债项目'!E3 -> 276.57398 | G14: ='预测 主要资产负债项目'!F3 -> 299.42802 | H14: ='预测 主要资产负债项目'!G3 -> 299.42802
A15: 应收账款 | B15: =资产负债分析调整表!E12/10000 -> 325.98318 | C15: ='预测 主要资产负债项目'!B4 -> 183.41133 | D15: ='预测 主要资产负债项目'!C4 -> 220.0936 | E15: ='预测 主要资产负债项目'!D4 -> 259.71045 | F15: ='预测 主要资产负债项目'!E4 -> 298.66702 | G15: ='预测 主要资产负债项目'!F4 -> 328.53372 | H15: ='预测 主要资产负债项目'!G4 -> 328.53372
A16: 预付账款 | B16: =资产负债分析调整表!E14/10000 -> 228.14434 | C16: ='预测 主要资产负债项目'!B5 -> 37.995527 | D16: ='预测 主要资产负债项目'!C5 -> 43.506895 | E16: ='预测 主要资产负债项目'!D5 -> 49.451882 | F16: ='预测 主要资产负债项目'!E5 -> 55.314796 | G16: ='预测 主要资产负债项目'!F5 -> 59.885604 | H16: ='预测 主要资产负债项目'!G5 -> 59.885604
A17: 应付账款 | B17: =资产负债分析调整表!E48/10000 -> 201.43995 | C17: ='预测 主要资产负债项目'!B6 -> 151.98211 | D17: ='预测 主要资产负债项目'!C6 -> 174.02758 | E17: ='预测 主要资产负债项目'!D6 -> 197.80753 | F17: ='预测 主要资产负债项目'!E6 -> 221.25918 | G17: ='预测 主要资产负债项目'!F6 -> 239.54242 | H17: ='预测 主要资产负债项目'!G6 -> 239.54242
A18: 预收款项 | B18: =资产负债分析调整表!E49/10000 -> 24.04556 | C18: ='预测 主要资产负债项目'!B7 -> 91.705667 | D18: ='预测 主要资产负债项目'!C7 -> 110.0468 | E18: ='预测 主要资产负债项目'!D7 -> 129.85522 | F18: ='预测 主要资产负债项目'!E7 -> 149.33351 | G18: ='预测 主要资产负债项目'!F7 -> 164.26686 | H18: ='预测 主要资产负债项目'!G7 -> 164.26686
A19: =资产负债分析调整表!B50 -> 应付职工薪酬 | B19: 464 | C19: ='预测 主要资产负债项目'!B8 -> 417.24 | D19: ='预测 主要资产负债项目'!C8 -> 438.102 | E19: ='预测 主要资产负债项目'!D8 -> 460.0071 | F19: ='预测 主要资产负债项目'!E8 -> 483.00745 | G19: ='预测 主要资产负债项目'!F8 -> 507.15783 | H19: ='预测 主要资产负债项目'!G8 -> 507.15783
A20: =资产负债分析调整表!B52 -> 应交税费 | B20: =资产负债分析调整表!G52/10000 -> -270.82681 | C20: ='预测 主要资产负债项目'!B9 -> 0.825351 | D20: ='预测 主要资产负债项目'!C9 -> 38.809246 | E20: ='预测 主要资产负债项目'!D9 -> 241.88339 | F20: ='预测 主要资产负债项目'!E9 -> 289.20496 | G20: ='预测 主要资产负债项目'!F9 -> 325.48482 | H20: ='预测 主要资产负债项目'!G9 -> 325.48482
A21: 营运资本 | B21: =B13+B14+B15+B16-B17-B18-B19-B20 -> 741.36491 | C21: =C13+C14+C15+C16-C17-C18-C19-C20 -> 334.87673 | D21: =D13+D14+D15+D16-D17-D18-D19-D20 -> 393.71628 | E21: =E13+E14+E15+E16-E17-E18-E19-E20 -> 300.00694 | F21: =F13+F14+F15+F16-F17-F18-F19-F20 -> 355.08491 | G21: =G13+G14+G15+G16-G17-G18-G19-G20 -> 422.71589 | H21: =H13+H14+H15+H16-H17-H18-H19-H20 -> 452.03758
A22: 期初营运资金 | C22: =71698.02-(31010.28-13939.17) -> 54626.91 | D22: =#REF! -> #REF! | E22: =D21 -> 393.71628 | F22: =E21 -> 300.00694 | G22: =F21 -> 355.08491 | H22: =G21 -> 422.71589
A23: 营运资本增加额 | C23: =C21-B21 -> -406.48818 | D23: =D21-C21 -> 58.839551 | E23: =E21-D21 -> -93.709344 | F23: =F21-E21 -> 55.077971 | G23: =G21-F21 -> 67.630981 | H23: =H21-G21 -> 29.321689

Sheet 非经营性资产和负债
B2: 项目 | C2: 账面值 | D2: 评估值
A3: 其他应收款 | B3: 往来款 | C3: =D3 -> 6051.167 | D3: =资产负债分析调整表!$F$13/10000 -> 6051.167
A4: 长期股权投资 | C4: =资产负债分析调整表!$F$23/10000 -> 1500 | D4: =14833859.84/10000 -> 1483.386
A5: 非经营性资产合计 | C5: =SUM(C3:C4) -> 7551.167 | D5: =SUM(D3:D4) -> 7534.553
A7: 其他应付款 | C7: =资产负债分析调整表!$F$54/10000 -> 1152.5 | D7: =C7 -> 1152.5
A8: 应交税费—增值税 | C8: =资产负债分析调整表!F52/10000 -> 0 | D8: =C8 -> 0
A9: 非经营性负债合计 | C9: =SUM(C7:C8) -> 1152.5 | D9: =SUM(D7:D8) -> 1152.5

Sheet 溢余资金测算表
D3: 期初货币资金 | E3: =资产负债分析调整表!$E$7/10000 -> 6.408064
D4: 经营最低现金保有量 | E4: =营运资金!B13 -> 75.505928
D5: 差额 | E5: =E3-E4 -> -69.097864
D6: 溢余资金额 | E6: 0

Sheet 评估值测算
A2: 项目\预测期 | B2: 2016年7-12 | C2: 2017年 | D2: 2018年 | E2: 2019年 | F2: 2020年 | G2: 2021年 | H2: 2022年 | I2: 2023年 | J2: 2025年
A3: 净利润 | B3: =#REF! -> #REF! | C3: =#REF! -> #REF! | D3: =预测利润表!C19 -> 198.29527 | E3: =预测利润表!D19 -> 395.24297 | F3: =预测利润表!E19 -> 591.20967 | G3: =预测利润表!F19 -> 798.77507 | H3: =预测利润表!G19 -> 830.83058 | I3: =预测利润表!H19 -> 713.54383 | J3: =预测利润表!I19 -> 0
A4: 净利润增长率 | C4: ——
A5: 加：折旧和摊销 | B5: =折旧和资本化支出!D54+折旧和资本化支出!D44 -> 211.89328 | C5: =折旧和资本化支出!E54+折旧和资本化支出!E44 -> 211.89328 | D5: =折旧和资本化支出!D59 -> 211.89328 | E5: =折旧和资本化支出!E59 -> 211.89328 | F5: =折旧和资本化支出!F59 -> 211.89328 | G5: =折旧和资本化支出!G59 -> 211.89328 | H5: =折旧和资本化支出!H59 -> 211.89328 | I5: =折旧和资本化支出!I59 -> 211.89328 | J5: =折旧和资本化支出!J59 -> 0
A6: 减：资本性支出 | B6: =折旧和资本化支出!#REF! -> #REF! | C6: =折旧和资本化支出!E60 -> 211.89328 | D6: =折旧和资本化支出!D60 -> 211.89328 | E6: =折旧和资本化支出!E60 -> 211.89328 | F6: =折旧和资本化支出!F60 -> 211.89328 | G6: =折旧和资本化支出!G60 -> 211.89328 | H6: =折旧和资本化支出!H60 -> 211.89328 | I6: =折旧和资本化支出!I60 -> 211.89328 | J6: =折旧和资本化支出!J60 -> 0
A7: 减：营运资本增加 | B7: =营运资金测算!C43 -> #REF! | C7: =营运资金!C23 -> -406.48818 | D7: =营运资金!C23 -> -406.48818 | E7: =营运资金!D23 -> 58.839551 | F7: =营运资金!E23 -> -93.709344 | G7: =营运资金!F23 -> 55.077971 | H7: =营运资金!G23 -> 67.630981 | I7: =营运资金!H23 -> 29.321689 | J7: =营运资金!I23 -> 0
A8: 六、股权自由现金流 | B8: =B3+B5-B6-B7 -> #REF! | C8: =C3+C5-C6-C7 -> #REF! | D8: =D3+D5-D6-D7 -> 604.78345 | E8: =E3+E5-E6-E7 -> 336.40342 | F8: =F3+F5-F6-F7 -> 684.91902 | G8: =G3+G5-G6-G7 -> 743.6971 | H8: =H3+H5-H6-H7 -> 763.1996 | I8: =I3+I5-I6-I7 -> 684.22214 | J8: =J3+J5-J6-J7 -> 0
A9: 加：税后的付息债务利息 | B9: =ROUND(财务费用!C17*(1-评估值测算!$L$9),2) -> 0 | C9: =ROUND(财务费用预测表!G9*(1-评估值测算!$L$9),2) -> 3204.46 | D9: 0 | E9: 0 | F9: 0 | G9: 0 | H9: 0 | I9: 0 | J9: =ROUND((#REF!+#REF!)*(1-评估值测算!$K$9),2) -> #REF! | K9: 0.25
A10: 七、企业自由现金流 | B10: =B8+B9 -> #REF! | C10: =C8+C9 -> #REF! | D10: =D8+D9 -> 604.78345 | E10: =E8+E9 -> 336.40342 | F10: =F8+F9 -> 684.91902 | G10: =G8+G9 -> 743.6971 | H10: =H8+H9 -> 763.1996 | I10: =I8+I9 -> 684.22214 | J10: =J8+J9 -> #REF!
A11: 折现率 | B11: =$K$11 -> 0.1509 | C11: 0.101 | D11: =K11 -> 0.1509 | E11: =D11 -> 0.1509 | F11: =E11 -> 0.1509 | G11: =F11 -> 0.1509 | H11: =G11 -> 0.1509 | I11: =H11 -> 0.1509 | J11: =#REF! -> #REF! | K11: 0.1509
A12: 折现期 | B12: =6/12/2 -> 0.25 | C12: 0.5 | D12: =1/2 -> 0.5 | E12: =D12+1 -> 1.5 | F12: =E12+1 -> 2.5 | G12: =F12+1 -> 3.5 | H12: =G12+1 -> 4.5 | I12: =H12+1 -> 5.5 | J12: =#REF!+1 -> #REF!
A13: 折现系数 | B13: =ROUND(1/(1+B11)^B12,2) -> 0.97 | C13: =ROUND(1/(1+C11)^C12,4) -> 0.953 | D13: =ROUND(1/(1+D11)^D12,4) -> 0.9321 | E13: =ROUND(1/(1+E11)^E12,4) -> 0.8099 | F13: =ROUND(1/(1+F11)^F12,4) -> 0.7037 | G13: =ROUND(1/(1+G11)^G12,4) -> 0.6115 | H13: =ROUND(1/(1+H11)^H12,4) -> 0.5313 | I13: =ROUND(1/I11*H13,4) -> 3.5209 | J13: =ROUND(1/(1+J11)^J12,4) -> #REF!
A14: 九、收益现值 | B14: =ROUND(B10*B13,2) -> #REF! | C14: =ROUND(C10*C13,2) -> #REF! | D14: =ROUND(D10*D13,2) -> 563.72 | E14: =ROUND(E10*E13,2) -> 272.45 | F14: =ROUND(F10*F13,2) -> 481.98 | G14: =ROUND(G10*G13,2) -> 454.77 | H14: =ROUND(H10*H13,2) -> 405.49 | I14: =ROUND(I10*I13,2) -> 2409.08 | J14: =ROUND(J10*J13,2) -> #REF!
A15: 十、收益现值合计 | B15: =SUM(D14:I14) -> 4587.49
A16: 加：溢余资金 | B16: =溢余资金测算表!E6 -> 0
A17: 加：非经营性资产 | C17: =非经营性资产和负债!D5 -> 7534.553
A18: 减：非经营性负债 | B18: =非经营性资产和负债!D9 -> 1152.5
A19: 减：有息负债 | B19: 0
A20: 加：子公司价值
A21: 十一、评估值 | B21: =B15+B16+C17-B18-B19+C20 -> 10969.543
J26: 44348.611

Sheet Sheet3
C4: 评估方法 | D4: 账面净资产 | E4: 评估值 | F4: 增减额 | G4: 增减率％
C5: 收益法 | D5: 9416.97 | E5: =评估值测算!B21 -> 10969.543 | F5: =E5-D5 -> 1552.573 | G5: =F5/D5 -> 0.1648697
C6: 资产基础法 | D6: 9416.97 | E6: ='[39]1-汇总表'!$C$29 -> 9552.94 | F6: =E6-D6 -> 135.97 | G6: =F6/D6 -> 0.014438827
C7: 差 异 | D7: 0 | E7: =E5-E6 -> 1416.603 | F7: =F5-F6 -> 1416.603 | G7: =G5-G6 -> 0.15043087
